Workbook
Name OLE_LINK41: Matrix!$U$13

Sheet Master Dashboard
A1: GAMMA WALL PROFILE | E1: SPX KING NODE — LIVE DASHBOARD | L1: ='King Node Model'!K26 -> Updated 17:39:36 | AM1: =MAX(MAX('King Node Model'!C29:C75),-MIN('King Node Model'!C29:C75)) -> 3137174 | AN1: ='King Node Model'!T22 -> 7825 | AO1: =MAX('King Node Model'!B29:B75) -> 4471438
A2: puts ◄ | B2: Hide unsafe | C2: ► calls | D2: offset | AM2: ='King Node Model'!B4 -> 7775.39 | AN2: ='King Node Model'!T23 -> 7770
A3: =IF(AND(ISNUMBER($AM3),$AM3<0,ISNUMBER($AO3),$AO$1>0),REPT("█",ROUND($AO3/$AO$1*26,0)),"") | B3: =TEXT(IF(IF('Level Engine'!$GJ$4=1,$AL3='Level Engine'!$GJ$3,AND($AL3-$AM$2>-2.5,$AL3-$AM$2<=2.5)),$AM$2,$AL3),"0")&IF($AL3=$AN$1," ★","")&IF($AL3=$AN$2," ★","")&IF($AL3=$AN$3," ◆","")&IF(AND(ISNUMBER($AN$4),$AL3=$AN$4)," Ⓕ","")&IF(OR(AND(ISNUMBER('Level Engine'!$BG$87),$AL3='Level Engine'!$BG$87),AND(ISNUMBER('Level Engine'!$BG$105),$AL3='Level Engine'!$BG$105))," ζ","")&IF(AND(ISNUMBER($AN$35),$AL3=$AN$35)," ⓏⒼ","")&IF(OR($AL3='Level Engine'!$CP$4,$AL3='Level Engine'!$CP$5,$AL3='Level Engine'!$CP$6,$AL3='Level Engine'!$CP$7)," ☄","")&IF(OR($AL3=$AN$5,$AL3=$AN$8)," ║1","")&IF(OR($AL3=$AN$6,$AL3=$AN$10)," ║2","")&IF(OR($AL3=$AN$7,$AL3=$AN$11)," ║3","")&IF(OR($AL3=$AN$13,$AL3=$AN$16)," ▣1","")&IF(OR($AL3=$AN$14,$AL3=$AN$17)," ▣2","")&IF(OR($AL3=$AN$15,$AL3=$AN$18)," ▣3","")&IF(AND(NOT(OR(AND(ISNUMBER(SEARCH("chop edge",$E$45)),IFERROR(ABS($AL3-'King Node Model'!$AL$42)<=5,FALSE),NOT(ISNUMBER(SEARCH("UNSAFE",$L$45)))),AND(ISNUMBER(SEARCH("chop edge",$E$46)),IFERROR(ABS($AL3-'King Node Model'!$AL$43)<=5,FALSE),NOT(ISNUMBER(SEARCH("UNSAFE",$L$46)))),AND(ISNUMBER(SEARCH("chop edge",$E$52)),IFERROR(ABS($AL3-'King Node Model'!$AL$49)<=5,FALSE),NOT(ISNUMBER(SEARCH("UNSAFE",$L$52)))),AND(ISNUMBER(SEARCH("chop edge",$E$53)),IFERROR(ABS($AL3-'King Node Model'!$AL$50)<=5,FALSE),NOT(ISNUMBER(SEARCH("UNSAFE",$L$53)))))),OR(AND(IFERROR(INDEX('Level Engine'!$IB$9:$IB$55,MATCH('King Node Model'!$AL$49,'Level Engine'!$AA$9:$AA$55,0)),0)<>1,$AL3=IFERROR(INDEX('Level Engine'!$AU$9:$AU$55,MATCH('King Node Model'!$AL$49,'Level Engine'!$AA$9:$AA$55,0)),""),IFERROR(INDEX('Level Engine'!$AU$9:$AU$55,MATCH('King Node Model'!$AL$49,'Level Engine'!$AA$9:$AA$55,0)),"")<>IFERROR(INDEX('Level Engine'!$AT$9:$AT$55,MATCH('King Node Model'!$AL$49,'Level Engine'!$AA$9:$AA$55,0)),"")),AND(IFERROR(INDEX('Level Engine'!$IB$9:$IB$55,MATCH('King Node Model'!$AL$50,'Level Engine'!$AA$9:$AA$55,0)),0)<>1,$AL3=IFERROR(INDEX('Level Engine'!$AU$9:$AU$55,MATCH('King Node Model'!$AL$50,'Level Engine'!$AA$9:$AA$55,0)),""),IFERROR(INDEX('Level Engine'!$AU$9:$AU$55,MATCH('King Node Model'!$AL$50,'Level Engine'!$AA$9:$AA$55,0)),"")<>IFERROR(INDEX('Level Engine'!$AT$9:$AT$55,MATCH('King Node Model'!$AL$50,'Level Engine'!$AA$9:$AA$55,0)),"")))),IF(OR('King Node Model'!$A$8="Neg",N('Level Engine'!$BG$72)=1),""," ⒷⒽ"),"")&IF(AND(NOT(OR(AND(ISNUMBER(SEARCH("chop edge",$E$45)),IFERROR(ABS($AL3-'King Node Model'!$AL$42)<=5,FALSE),NOT(ISNUMBER(SEARCH("UNSAFE",$L$45)))),AND(ISNUMBER(SEARCH("chop edge",$E$46)),IFERROR(ABS($AL3-'King Node Model'!$AL$43)<=5,FALSE),NOT(ISNUMBER(SEARCH("UNSAFE",$L$46)))),AND(ISNUMBER(SEARCH("chop edge",$E$52)),IFERROR(ABS($AL3-'King Node Model'!$AL$49)<=5,FALSE),NOT(ISNUMBER(SEARCH("UNSAFE",$L$52)))),AND(ISNUMBER(SEARCH("chop edge",$E$53)),IFERROR(ABS($AL3-'King Node Model'!$AL$50)<=5,FALSE),NOT(ISNUMBER(SEARCH("UNSAFE",$L$53)))))),OR(AND(IFERROR(INDEX('Level Engine'!$IB$9:$IB$55,MATCH('King Node Model'!$AL$42,'Level Engine'!$AA$9:$AA$55,0)),0)<>1,$AL3=IFERROR(INDEX('Level Engine'!$AT$9:$AT$55,MATCH('King Node Model'!$AL$42,'Level Engine'!$AA$9:$AA$55,0)),""),IFERROR(INDEX('Level Engine'!$AT$9:$AT$55,MATCH('King Node Model'!$AL$42,'Level Engine'!$AA$9:$AA$55,0)),"")<>IFERROR(INDEX('Level Engine'!$AU$9:$AU$55,MATCH('King Node Model'!$AL$42,'Level Engine'!$AA$9:$AA$55,0)),"")),AND(IFERROR(INDEX('Level Engine'!$IB$9:$IB$55,MATCH('King Node Model'!$AL$43,'Level Engine'!$AA$9:$AA$55,0)),0)<>1,$AL3=IFERROR(INDEX('Level Engine'!$AT$9:$AT$55,MATCH('King Node Model'!$AL$43,'Level Engine'!$AA$9:$AA$55,0)),""),IFERROR(INDEX('Level Engine'!$AT$9:$AT$55,MATCH('King Node Model'!$AL$43,'Level Engine'!$AA$9:$AA$55,0)),"")<>IFERROR(INDEX('Level Engine'!$AU$9:$AU$55,MATCH('King Node Model'!$AL$43,'Level Engine'!$AA$9:$AA$55,0)),"")))),IF(OR('King Node Model'!$A$8="Neg",N('Level Engine'!$BG$72)=1),""," ⒷⓁ"),"")&IF(OR(AND($AL3>='King Node Model'!$AM$17,$AL3<='King Node Model'!$AN$17,$AP$45="RASP"),AND($AL3>='King Node Model'!$AM$18,$AL3<='King Node Model'!$AN$18,$AP$46="RASP"),AND($AL3>='King Node Model'!$AM$19,$AL3<='King Node Model'!$AN$19,$AP$47="RASP"),AND($AL3>='King Node Model'!$AM$20,$AL3<='King Node Model'!$AN$20,$AP$52="RASP"),AND($AL3>='King Node Model'!$AM$21,$AL3<='King Node Model'!$AN$21,$AP$53="RASP"),AND($AL3>='King Node Model'!$AM$22,$AL3<='King Node Model'!$AN$22,$AP$54="RASP")),"","")&IF(IF('Level Engine'!$GJ$4=1,$AL3='Level Engine'!$GJ$3,AND($AL3-$AM$2>-2.5,$AL3-$AM$2<=2.5))," ◄","")&IF(IFERROR(INDEX('Level Engine'!$GV$9:$GV$55,MATCH($AL3,'Level Engine'!$AA$9:$AA$55,0)),0)=1," Ⓥ"&IF(IFERROR(INDEX('Level Engine'!$ET$9:$ET$55,MATCH($AL3,'Level Engine'!$AA$9:$AA$55,0)),0)=1,"+",""),"")&IF(OR(AND($AL3=$AN$38,IFERROR(INDEX('Level Engine'!$AN$9:$AN$55,MATCH($AL3,'Level Engine'!$AA$9:$AA$55,0)),0)<>1),$AL3=$AN$39)," ⊙","")&IF(AND(OR('King Node Model'!$A$8="Neg",N('Level Engine'!$BG$72)=1),ABS(MIN($AM$3:$AM$64))>MAX($AM$3:$AM$64),$AN$2<$AM$2,$AL3<$AM$2,ABS($AL3-$AN$2)<=5,IFERROR(VALUE(MID('King Node Model'!$K$26,FIND(":",'King Node Model'!$K$26)-2,2)),0)>=19,IFERROR(INDEX('Level Engine'!$EJ$9:$EJ$55,MATCH($AL3,'Level Engine'!$AA$9:$AA$55,0)),0)=0,$AN$3>$AM$2)," ⟲rev","")&IF($AL3='King Node Model'!$F$24," ⟂","")&$DJ3&IF(IFERROR(INDEX('Level Engine'!$EN$9:$EN$55,MATCH($AL3,'Level Engine'!$AA$9:$AA$55,0)),0)=1," Ⓟ"&IF(AND(OR('King Node Model'!$A$8="Neg",N('Level Engine'!$BG$72)=1),IFERROR(INDEX('Level Engine'!$AN$9:$AN$55,MATCH($AL3,'Level Engine'!$AA$9:$AA$55,0)),0)<>1)," NO-REV",""),"")&IF(AND(ISNUMBER($AL3),OR(AND(ISNUMBER(SEARCH("chop edge",$E$45)),$AL3='King Node Model'!$AL$42),AND(ISNUMBER(SEARCH("chop edge",$E$46)),$AL3='King Node Model'!$AL$43),AND(ISNUMBER(SEARCH("chop edge",$E$52)),$AL3='King Node Model'!$AL$49),AND(ISNUMBER(SEARCH("chop edge",$E$53)),$AL3='King Node Model'!$AL$50)))," ⒸⒺ","")&IF(AND('Level Engine'!$GJ$4=1,OR($AL3='Level Engine'!$GJ$1,$AL3='Level Engine'!$GJ$2)),"","")&IF(ABS(N(IFERROR(INDEX('Level Engine'!$AE$9:$AE$55,MATCH($AL3,'Level Engine'!$AA$9:$AA$55,0)),0)))>='Level Engine'!$BG$85,IF(N(IFERROR(INDEX('Level Engine'!$AE$9:$AE$55,MATCH($AL3,'Level Engine'!$AA$9:$AA$55,0)),0))>0," Δ+"," Δ−"),"")&IFERROR(IF(AND(ISNUMBER(MATCH($AL3,'Level Engine'!$AA$9:$AA$55,0)),ABS(N(IFERROR(INDEX('Level Engine'!$AE$9:$AE$55,MATCH($AL3,'Level Engine'!$AA$9:$AA$55,0)),0)))<'Level Engine'!$BG$85,ABS(N(IFERROR(INDEX('Level Engine'!$AE$9:$AE$55,MATCH($AL3,'Level Engine'!$AA$9:$AA$55,0)),0)))<=ABS(N(IFERROR(INDEX('Level Engine'!$AE$9:$AE$55,MATCH($AL3+5,'Level Engine'!$AA$9:$AA$55,0)),0))),ABS(N(IFERROR(INDEX('Level Engine'!$AE$9:$AE$55,MATCH($AL3,'Level Engine'!$AA$9:$AA$55,0)),0)))<=ABS(N(IFERROR(INDEX('Level Engine'!$AE$9:$AE$55,MATCH($AL3-5,'Level Engine'!$AA$9:$AA$55,0)),0))),OR(AND(ABS(N(IFERROR(INDEX('Level Engine'!$AE$9:$AE$55,MATCH($AL3+5,'Level Engine'!$AA$9:$AA$55,0)),0)))>='Level Engine'!$BG$85,ABS(N(IFERROR(INDEX('Level Engine'!$AE$9:$AE$55,MATCH($AL3,'Level Engine'!$AA$9:$AA$55,0)),0)))<='Level Engine'!$BG$88*ABS(N(IFERROR(INDEX('Level Engine'!$AE$9:$AE$55,MATCH($AL3+5,'Level Engine'!$AA$9:$AA$55,0)),0)))),AND(ABS(N(IFERROR(INDEX('Level Engine'!$AE$9:$AE$55,MATCH($AL3-5,'Level Engine'!$AA$9:$AA$55,0)),0)))>='Level Engine'!$BG$85,ABS(N(IFERROR(INDEX('Level Engine'!$AE$9:$AE$55,MATCH($AL3,'Level Engine'!$AA$9:$AA$55,0)),0)))<='Level Engine'!$BG$88*ABS(N(IFERROR(INDEX('Level Engine'!$AE$9:$AE$55,MATCH($AL3-5,'Level Engine'!$AA$9:$AA$55,0)),0)))))),IF(AND('King Node Model'!$A$8="Pos",N('Level Engine'!$BG$72)<>1),""," ∅"),""),"")&IF(IFERROR(INDEX('Level Engine'!$JD$9:$JD$55,MATCH($AL3,'Level Engine'!$AA$9:$AA$55,0)),"")="P"," P-OI",IF(IFERROR(INDEX('Level Engine'!$JD$9:$JD$55,MATCH($AL3,'Level Engine'!$AA$9:$AA$55,0)),"")="C"," C-OI","")) -> 7885 | C3: =IF(AND(ISNUMBER($AM3),$AM3>0,ISNUMBER($AO3),$AO$1>0),REPT("█",ROUND($AO3/$AO$1*26,0)),"") | D3: =IF(NOT(ISNUMBER($AL3)),"",IF(IFERROR(INDEX('Level Engine'!$FS$9:$FS$55,MATCH($AL3,'Level Engine'!$AA$9:$AA$55,0)),0)=1,"⊙","")) | E3: ="SPOT "&TEXT('King Node Model'!$B$4,"#,##0.0") -> SPOT 7,775.4 | G3: ="REGIME "&'King Node Model'!$A$8 -> REGIME Neg | I3: ="GAMMA FLIP "&TEXT('King Node Model'!$D$26,"0") -> GAMMA FLIP 7805 | K3: ="ZERO GAMMA "&IF(ISNUMBER('King Node Model'!$D$27),TEXT('King Node Model'!$D$27,"0"),"—") -> ZERO GAMMA 7775 | Q3: IV TRACKER | AL3: ='King Node Model'!A29 -> 7885 | AM3: ='King Node Model'!C29 -> 32827 | AN3: ='King Node Model'!B23 -> 7770 | AO3: ='King Node Model'!B29 -> 33280 | AY3: =IF(AND($B$2="Hide unsafe",$BB3=1),0,IF(AND(OR(AND(AND(ISNUMBER($AL3),OR(AND($AL3>=$AQ$22,$AL3<=$AR$22,$AS$22=1),$AL3=$AQ$22,$AL3=$AR$22,$AL3=$AQ$23,$AL3=$AR$23,$AL3=$AQ$24,$AL3=$AR$24),NOT(OR($AL3=$AN$5,$AL3=$AN$6,$AL3=$AN$7,$AL3=$AN$8,$AL3=$AN$10,$AL3=$AN$11))),NOT(OR(AND('King Node Model'!$P$13="Up",OR($AL3=$AQ$22,$AL3=$AQ$23,$AL3=$AQ$24,$AL3='King Node Model'!$AM$20,$AL3='King Node Model'!$AM$21,$AL3='King Node Model'!$AM$22),OR(AND('King Node Model'!$B$23-$AL3>=0,'King Node Model'!$B$23-$AL3<=5),AND('King Node Model'!$C$23-$AL3>=0,'King Node Model'!$C$23-$AL3<=5))),AND('King Node Model'!$P$13="Down",OR($AL3=$AR$22,$AL3=$AR$23,$AL3=$AR$24,$AL3='King Node Model'!$AN$20,$AL3='King Node Model'!$AN$21,$AL3='King Node Model'!$AN$22),OR(AND($AL3-'King Node Model'!$B$23>=0,$AL3-'King Node Model'!$B$23<=5),AND($AL3-'King Node Model'!$C$24>=0,$AL3-'King Node Model'!$C$24<=5)))))),AND(AND(ISNUMBER($AL3),OR(AND($AL3>=$AQ$22,$AL3<=$AR$22,$AS$22=1),$AL3=$AQ$22,$AL3=$AR$22,$AL3=$AQ$23,$AL3=$AR$23,$AL3=$AQ$24,$AL3=$AR$24,$AL3='King Node Model'!$AL$42,$AL3='King Node Model'!$AL$43),OR($AL3=$AN$5,$AL3=$AN$6,$AL3=$AN$7,$AL3=$AN$8,$AL3=$AN$10,$AL3=$AN$11)),NOT(OR(AND('King Node Model'!$P$13="Up",OR($AL3=$AQ$22,$AL3=$AQ$23,$AL3=$AQ$24,$AL3='King Node Model'!$AM$20,$AL3='King Node Model'!$AM$21,$AL3='King Node Model'!$AM$22),OR(AND('King Node Model'!$B$23-$AL3>=0,'King Node Model'!$B$23-$AL3<=5),AND('King Node Model'!$C$23-$AL3>=0,'King Node Model'!$C$23-$AL3<=5))),AND('King Node Model'!$P$13="Down",OR($AL3=$AR$22,$AL3=$AR$23,$AL3=$AR$24,$AL3='King Node Model'!$AN$20,$AL3='King Node Model'!$AN$21,$AL3='King Node Model'!$AN$22),OR(AND($AL3-'King Node Model'!$B$23>=0,$AL3-'King Node Model'!$B$23<=5),AND($AL3-'King Node Model'!$C$24>=0,$AL3-'King Node Model'!$C$24<=5)))))),AND(AND(ISNUMBER($AL3),OR(AND($AL3>='King Node Model'!$AM$20,$AL3<='King Node Model'!$AN$20,$AS$23=1),$AL3='King Node Model'!$AM$20,$AL3='King Node Model'!$AN$20,$AL3='King Node Model'!$AM$21,$AL3='King Node Model'!$AN$21,$AL3='King Node Model'!$AM$22,$AL3='King Node Model'!$AN$22),NOT(OR($AL3=$AN$5,$AL3=$AN$6,$AL3=$AN$7,$AL3=$AN$8,$AL3=$AN$10,$AL3=$AN$11))),NOT(AND(ISNUMBER('King Node Model'!$F$24),$AL3='King Node Model'!$F$24,IFERROR(INDEX('Level Engine'!$JN$9:$JN$55,MATCH($AL3,'Level Engine'!$AA$9:$AA$55,0)),0)<>1,$AL3<>'King Node Model'!$AL$49,$AL3<>'King Node Model'!$AL$50))),AND(AND(ISNUMBER($AL3),OR(AND($AL3>='King Node Model'!$AM$20,$AL3<='King Node Model'!$AN$20,$AS$23=1),$AL3='King Node Model'!$AM$20,$AL3='King Node Model'!$AN$20,$AL3='King Node Model'!$AM$21,$AL3='King Node Model'!$AN$21,$AL3='King Node Model'!$AM$22,$AL3='King Node Model'!$AN$22,$AL3='King Node Model'!$AL$49,$AL3='King Node Model'!$AL$50),OR($AL3=$AN$5,$AL3=$AN$6,$AL3=$AN$7,$AL3=$AN$8,$AL3=$AN$10,$AL3=$AN$11)),NOT(OR(AND('King Node Model'!$P$13="Up",OR($AL3=$AQ$22,$AL3=$AQ$23,$AL3=$AQ$24,$AL3='King Node Model'!$AM$20,$AL3='King Node Model'!$AM$21,$AL3='King Node Model'!$AM$22),OR(AND('King Node Model'!$B$23-$AL3>=0,'King Node Model'!$B$23-$AL3<=5),AND('King Node Model'!$C$23-$AL3>=0,'King Node Model'!$C$23-$AL3<=5))),AND('King Node Model'!$P$13="Down",OR($AL3=$AR$22,$AL3=$AR$23,$AL3=$AR$24,$AL3='King Node Model'!$AN$20,$AL3='King Node Model'!$AN$21,$AL3='King Node Model'!$AN$22),OR(AND($AL3-'King Node Model'!$B$23>=0,$AL3-'King Node Model'!$B$23<=5),AND($AL3-'King Node Model'!$C$24>=0,$AL3-'King Node Model'!$C$24<=5))))))),OR(COUNTIF('Level Engine'!$W$9:$W$14,$AL3)>0,COUNTIF('Level Engine'!$W$18:$W$23,$AL3)>0,$AL3='King Node Model'!$AL$42,$AL3='King Node Model'!$AL$43,$AL3='King Node Model'!$AL$44,$AL3='King Node Model'!$AL$49,$AL3='King Node Model'!$AL$50,$AL3='King Node Model'!$AL$51)),1,0)) -> 0 | AZ3: =IF($B$2="Hide unsafe",0,$BB3) -> 0 | BB3: =IF(OR(AND($AL3='King Node Model'!$AL$42,$AP$45<>"RASP"),AND($AL3='King Node Model'!$AL$43,$AP$46<>"RASP"),AND($AL3='King Node Model'!$AL$49,$AP$52<>"RASP"),AND($AL3='King Node Model'!$AL$50,$AP$53<>"RASP"),AND($AL3='King Node Model'!$AL$44,$AP$47<>"RASP"),AND($AL3='King Node Model'!$AL$51,$AP$54<>"RASP")),0,IF(AND(AND(ISNUMBER($AL3),OR(AND($AL3>=$AQ$22,$AL3<=$AR$22,$AP$45="RASP"),AND($AL3>=$AQ$23,$AL3<=$AR$23,$AP$46="RASP"),AND($AL3>=$AQ$24,$AL3<=$AR$24,$AP$47="RASP"),AND($AL3>='King Node Model'!$AM$20,$AL3<='King Node Model'!$AN$20,$AP$52="RASP",NOT($L$52=$AW$52)),AND($AL3='King Node Model'!$B$23,$AP$52="RASP",$L$52=$AW$52),AND($AL3>='King Node Model'!$AM$21,$AL3<='King Node Model'!$AN$21,$AP$53="RASP",NOT($L$53=$AW$53)),AND($AL3='King Node Model'!$B$23,$AP$53="RASP",$L$53=$AW$53),AND($AL3>='King Node Model'!$AM$22,$AL3<='King Node Model'!$AN$22,$AP$54="RASP"),AND($AL3>=IFERROR(INDEX('Level Engine'!$AT$9:$AT$55,MATCH('King Node Model'!$AL$42,'Level Engine'!$AA$9:$AA$55,0)),""),$AL3<=IFERROR(INDEX('Level Engine'!$AU$9:$AU$55,MATCH('King Node Model'!$AL$42,'Level Engine'!$AA$9:$AA$55,0)),""),$AP$45="RASP"),AND($AL3>=IFERROR(INDEX('Level Engine'!$AT$9:$AT$55,MATCH('King Node Model'!$AL$43,'Level Engine'!$AA$9:$AA$55,0)),""),$AL3<=IFERROR(INDEX('Level Engine'!$AU$9:$AU$55,MATCH('King Node Model'!$AL$43,'Level Engine'!$AA$9:$AA$55,0)),""),$AP$46="RASP"),AND($AL3>=IFERROR(INDEX('Level Engine'!$AT$9:$AT$55,MATCH('King Node Model'!$AL$44,'Level Engine'!$AA$9:$AA$55,0)),""),$AL3<=IFERROR(INDEX('Level Engine'!$AU$9:$AU$55,MATCH('King Node Model'!$AL$44,'Level Engine'!$AA$9:$AA$55,0)),""),$AP$47="RASP"),AND($AL3>=IFERROR(INDEX('Level Engine'!$AT$9:$AT$55,MATCH('King Node Model'!$AL$49,'Level Engine'!$AA$9:$AA$55,0)),""),$AL3<=IFERROR(INDEX('Level Engine'!$AU$9:$AU$55,MATCH('King Node Model'!$AL$49,'Level Engine'!$AA$9:$AA$55,0)),""),$AP$52="RASP",NOT($L$52=$AW$52)),AND($AL3>=IFERROR(INDEX('Level Engine'!$AT$9:$AT$55,MATCH('King Node Model'!$AL$50,'Level Engine'!$AA$9:$AA$55,0)),""),$AL3<=IFERROR(INDEX('Level Engine'!$AU$9:$AU$55,MATCH('King Node Model'!$AL$50,'Level Engine'!$AA$9:$AA$55,0)),""),$AP$53="RASP",NOT($L$53=$AW$53)),AND($AL3>=IFERROR(INDEX('Level Engine'!$AT$9:$AT$55,MATCH('King Node Model'!$AL$51,'Level Engine'!$AA$9:$AA$55,0)),""),$AL3<=IFERROR(INDEX('Level Engine'!$AU$9:$AU$55,MATCH('King Node Model'!$AL$51,'Level Engine'!$AA$9:$AA$55,0)),""),$AP$54="RASP"))),NOT(AND(ISNUMBER('King Node Model'!$F$24),$AL3='King Node Model'!$F$24,IFERROR(INDEX('Level Engine'!$JN$9:$JN$55,MATCH($AL3,'Level Engine'!$AA$9:$AA$55,0)),0)<>1,$AL3<>'King Node Model'!$AL$42,$AL3<>'King Node Model'!$AL$43,$AL3<>'King Node Model'!$AL$44,$AL3<>'King Node Model'!$AL$49,$AL3<>'King Node Model'!$AL$50,$AL3<>'King Node Model'!$AL$51))),1,0)) -> 0 | CO3: =IF(NOT(ISNUMBER($AL3)),"",IF(NOT(ISNUMBER(IFERROR(INDEX('Level Engine'!$FT$9:$FT$55,MATCH($AL3,'Level Engine'!$AA$9:$AA$55,0)),""))),"",IF(IFERROR(INDEX('Level Engine'!$FT$9:$FT$55,MATCH($AL3,'Level Engine'!$AA$9:$AA$55,0)),"")<0,0,2)+IF(ABS(IFERROR(INDEX('Level Engine'!$FT$9:$FT$55,MATCH($AL3,'Level Engine'!$AA$9:$AA$55,0)),""))>='Level Engine'!$FT$2,2,1))) -> 4 | DJ3: =IF(ISNUMBER($AL3),IF($AL3='Level Engine'!$BG$122," ⫪","")&IF($AL3='Level Engine'!$BG$118," S↑"&IFERROR(INDEX('Level Engine'!$MV$9:$MV$55,MATCH($AL3,'Level Engine'!$AA$9:$AA$55,0)),""),"")&IF($AL3='Level Engine'!$BG$119," S↓"&IFERROR(INDEX('Level Engine'!$MV$9:$MV$55,MATCH($AL3,'Level Engine'!$AA$9:$AA$55,0)),""),"")&IF($AL3='Level Engine'!$BG$120," D↑","")&IF($AL3='Level Engine'!$BG$121," D↓","")&IFERROR(INDEX('Level Engine'!$LG$9:$LG$55,MATCH($AL3,'Level Engine'!$AA$9:$AA$55,0)),"")&IF(IFERROR(INDEX('Level Engine'!$MA$9:$MA$55,MATCH($AL3,'Level Engine'!$AA$9:$AA$55,0)),0)=1," SAND","")&IF(IFERROR(INDEX('Level Engine'!$LM$9:$LM$55,MATCH($AL3,'Level Engine'!$AA$9:$AA$55,0)),0)>0," TP","")&IFERROR(" r"&MATCH($AL3,'Level Engine'!$W$9:$W$14,0),IFERROR(" s"&MATCH($AL3,'Level Engine'!$W$18:$W$23,0),""))&IF($AL3='Level Engine'!$BG$165," ◇","")&IF(N($DZ3)=1,IF($AL3>'Level Engine'!$BG$165," ⚠ DOM↓"," ⚠ DOM↑")&'Level Engine'!$BG$165,""),"") | DK3: =IF(AND(ISNUMBER($AL3),OR($AL3='King Node Model'!$AL$42,$AL3='King Node Model'!$AL$43,$AL3='King Node Model'!$AL$44)),IFERROR(MATCH($AL3,'Level Engine'!$W$9:$W$14,0),""),"") | DL3: =IF(AND(ISNUMBER($AL3),OR($AL3='King Node Model'!$AL$49,$AL3='King Node Model'!$AL$50,$AL3='King Node Model'!$AL$51)),IFERROR(MATCH($AL3,'Level Engine'!$W$18:$W$23,0),""),"") | DM3: =IF(AND(ISNUMBER($AL3),IFERROR(INDEX('Level Engine'!$LC$9:$LC$55,MATCH($AL3,'Level Engine'!$AA$9:$AA$55,0)),0)=1,OR($AL3=$AN$3,IFERROR(INDEX('Level Engine'!$LB$9:$LB$55,MATCH($AL3,'Level Engine'!$AA$9:$AA$55,0)),0)=1)),1,0) -> 0 | DZ3: =IF(ISNUMBER($AL3),IF(IFERROR(INDEX('Level Engine'!$NJ$9:$NJ$55,MATCH($AL3,'Level Engine'!$AA$9:$AA$55,0)),0)=1,1,0),0)
A4: =IF(AND(ISNUMBER($AM4),$AM4<0,ISNUMBER($AO4),$AO$1>0),REPT("█",ROUND($AO4/$AO$1*26,0)),"") | B4: =TEXT(IF(IF('Level Engine'!$GJ$4=1,$AL4='Level Engine'!$GJ$3,AND($AL4-$AM$2>-2.5,$AL4-$AM$2<=2.5)),$AM$2,$AL4),"0")&IF($AL4=$AN$1," ★","")&IF($AL4=$AN$2," ★","")&IF($AL4=$AN$3," ◆","")&IF(AND(ISNUMBER($AN$4),$AL4=$AN$4)," Ⓕ","")&IF(OR(AND(ISNUMBER('Level Engine'!$BG$87),$AL4='Level Engine'!$BG$87),AND(ISNUMBER('Level Engine'!$BG$105),$AL4='Level Engine'!$BG$105))," ζ","")&IF(AND(ISNUMBER($AN$35),$AL4=$AN$35)," ⓏⒼ","")&IF(OR($AL4='Level Engine'!$CP$4,$AL4='Level Engine'!$CP$5,$AL4='Level Engine'!$CP$6,$AL4='Level Engine'!$CP$7)," ☄","")&IF(OR($AL4=$AN$5,$AL4=$AN$8)," ║1","")&IF(OR($AL4=$AN$6,$AL4=$AN$10)," ║2","")&IF(OR($AL4=$AN$7,$AL4=$AN$11)," ║3","")&IF(OR($AL4=$AN$13,$AL4=$AN$16)," ▣1","")&IF(OR($AL4=$AN$14,$AL4=$AN$17)," ▣2","")&IF(OR($AL4=$AN$15,$AL4=$AN$18)," ▣3","")&IF(AND(NOT(OR(AND(ISNUMBER(SEARCH("chop edge",$E$45)),IFERROR(ABS($AL4-'King Node Model'!$AL$42)<=5,FALSE),NOT(ISNUMBER(SEARCH("UNSAFE",$L$45)))),AND(ISNUMBER(SEARCH("chop edge",$E$46)),IFERROR(ABS($AL4-'King Node Model'!$AL$43)<=5,FALSE),NOT(ISNUMBER(SEARCH("UNSAFE",$L$46)))),AND(ISNUMBER(SEARCH("chop edge",$E$52)),IFERROR(ABS($AL4-'King Node Model'!$AL$49)<=5,FALSE),NOT(ISNUMBER(SEARCH("UNSAFE",$L$52)))),AND(ISNUMBER(SEARCH("chop edge",$E$53)),IFERROR(ABS($AL4-'King Node Model'!$AL$50)<=5,FALSE),NOT(ISNUMBER(SEARCH("UNSAFE",$L$53)))))),OR(AND(IFERROR(INDEX('Level Engine'!$IB$9:$IB$55,MATCH('King Node Model'!$AL$49,'Level Engine'!$AA$9:$AA$55,0)),0)<>1,$AL4=IFERROR(INDEX('Level Engine'!$AU$9:$AU$55,MATCH('King Node Model'!$AL$49,'Level Engine'!$AA$9:$AA$55,0)),""),IFERROR(INDEX('Level Engine'!$AU$9:$AU$55,MATCH('King Node Model'!$AL$49,'Level Engine'!$AA$9:$AA$55,0)),"")<>IFERROR(INDEX('Level Engine'!$AT$9:$AT$55,MATCH('King Node Model'!$AL$49,'Level Engine'!$AA$9:$AA$55,0)),"")),AND(IFERROR(INDEX('Level Engine'!$IB$9:$IB$55,MATCH('King Node Model'!$AL$50,'Level Engine'!$AA$9:$AA$55,0)),0)<>1,$AL4=IFERROR(INDEX('Level Engine'!$AU$9:$AU$55,MATCH('King Node Model'!$AL$50,'Level Engine'!$AA$9:$AA$55,0)),""),IFERROR(INDEX('Level Engine'!$AU$9:$AU$55,MATCH('King Node Model'!$AL$50,'Level Engine'!$AA$9:$AA$55,0)),"")<>IFERROR(INDEX('Level Engine'!$AT$9:$AT$55,MATCH('King Node Model'!$AL$50,'Level Engine'!$AA$9:$AA$55,0)),"")))),IF(OR('King Node Model'!$A$8="Neg",N('Level Engine'!$BG$72)=1),""," ⒷⒽ"),"")&IF(AND(NOT(OR(AND(ISNUMBER(SEARCH("chop edge",$E$45)),IFERROR(ABS($AL4-'King Node Model'!$AL$42)<=5,FALSE),NOT(ISNUMBER(SEARCH("UNSAFE",$L$45)))),AND(ISNUMBER(SEARCH("chop edge",$E$46)),IFERROR(ABS($AL4-'King Node Model'!$AL$43)<=5,FALSE),NOT(ISNUMBER(SEARCH("UNSAFE",$L$46)))),AND(ISNUMBER(SEARCH("chop edge",$E$52)),IFERROR(ABS($AL4-'King Node Model'!$AL$49)<=5,FALSE),NOT(ISNUMBER(SEARCH("UNSAFE",$L$52)))),AND(ISNUMBER(SEARCH("chop edge",$E$53)),IFERROR(ABS($AL4-'King Node Model'!$AL$50)<=5,FALSE),NOT(ISNUMBER(SEARCH("UNSAFE",$L$53)))))),OR(AND(IFERROR(INDEX('Level Engine'!$IB$9:$IB$55,MATCH('King Node Model'!$AL$42,'Level Engine'!$AA$9:$AA$55,0)),0)<>1,$AL4=IFERROR(INDEX('Level Engine'!$AT$9:$AT$55,MATCH('King Node Model'!$AL$42,'Level Engine'!$AA$9:$AA$55,0)),""),IFERROR(INDEX('Level Engine'!$AT$9:$AT$55,MATCH('King Node Model'!$AL$42,'Level Engine'!$AA$9:$AA$55,0)),"")<>IFERROR(INDEX('Level Engine'!$AU$9:$AU$55,MATCH('King Node Model'!$AL$42,'Level Engine'!$AA$9:$AA$55,0)),"")),AND(IFERROR(INDEX('Level Engine'!$IB$9:$IB$55,MATCH('King Node Model'!$AL$43,'Level Engine'!$AA$9:$AA$55,0)),0)<>1,$AL4=IFERROR(INDEX('Level Engine'!$AT$9:$AT$55,MATCH('King Node Model'!$AL$43,'Level Engine'!$AA$9:$AA$55,0)),""),IFERROR(INDEX('Level Engine'!$AT$9:$AT$55,MATCH('King Node Model'!$AL$43,'Level Engine'!$AA$9:$AA$55,0)),"")<>IFERROR(INDEX('Level Engine'!$AU$9:$AU$55,MATCH('King Node Model'!$AL$43,'Level Engine'!$AA$9:$AA$55,0)),"")))),IF(OR('King Node Model'!$A$8="Neg",N('Level Engine'!$BG$72)=1),""," ⒷⓁ"),"")&IF(OR(AND($AL4>='King Node Model'!$AM$17,$AL4<='King Node Model'!$AN$17,$AP$45="RASP"),AND($AL4>='King Node Model'!$AM$18,$AL4<='King Node Model'!$AN$18,$AP$46="RASP"),AND($AL4>='King Node Model'!$AM$19,$AL4<='King Node Model'!$AN$19,$AP$47="RASP"),AND($AL4>='King Node Model'!$AM$20,$AL4<='King Node Model'!$AN$20,$AP$52="RASP"),AND($AL4>='King Node Model'!$AM$21,$AL4<='King Node Model'!$AN$21,$AP$53="RASP"),AND($AL4>='King Node Model'!$AM$22,$AL4<='King Node Model'!$AN$22,$AP$54="RASP")),"","")&IF(IF('Level Engine'!$GJ$4=1,$AL4='Level Engine'!$GJ$3,AND($AL4-$AM$2>-2.5,$AL4-$AM$2<=2.5))," ◄","")&IF(IFERROR(INDEX('Level Engine'!$GV$9:$GV$55,MATCH($AL4,'Level Engine'!$AA$9:$AA$55,0)),0)=1," Ⓥ"&IF(IFERROR(INDEX('Level Engine'!$ET$9:$ET$55,MATCH($AL4,'Level Engine'!$AA$9:$AA$55,0)),0)=1,"+",""),"")&IF(OR(AND($AL4=$AN$38,IFERROR(INDEX('Level Engine'!$AN$9:$AN$55,MATCH($AL4,'Level Engine'!$AA$9:$AA$55,0)),0)<>1),$AL4=$AN$39)," ⊙","")&IF(AND(OR('King Node Model'!$A$8="Neg",N('Level Engine'!$BG$72)=1),ABS(MIN($AM$3:$AM$64))>MAX($AM$3:$AM$64),$AN$2<$AM$2,$AL4<$AM$2,ABS($AL4-$AN$2)<=5,IFERROR(VALUE(MID('King Node Model'!$K$26,FIND(":",'King Node Model'!$K$26)-2,2)),0)>=19,IFERROR(INDEX('Level Engine'!$EJ$9:$EJ$55,MATCH($AL4,'Level Engine'!$AA$9:$AA$55,0)),0)=0,$AN$3>$AM$2)," ⟲rev","")&IF($AL4='King Node Model'!$F$24," ⟂","")&$DJ4&IF(IFERROR(INDEX('Level Engine'!$EN$9:$EN$55,MATCH($AL4,'Level Engine'!$AA$9:$AA$55,0)),0)=1," Ⓟ"&IF(AND(OR('King Node Model'!$A$8="Neg",N('Level Engine'!$BG$72)=1),IFERROR(INDEX('Level Engine'!$AN$9:$AN$55,MATCH($AL4,'Level Engine'!$AA$9:$AA$55,0)),0)<>1)," NO-REV",""),"")&IF(AND(ISNUMBER($AL4),OR(AND(ISNUMBER(SEARCH("chop edge",$E$45)),$AL4='King Node Model'!$AL$42),AND(ISNUMBER(SEARCH("chop edge",$E$46)),$AL4='King Node Model'!$AL$43),AND(ISNUMBER(SEARCH("chop edge",$E$52)),$AL4='King Node Model'!$AL$49),AND(ISNUMBER(SEARCH("chop edge",$E$53)),$AL4='King Node Model'!$AL$50)))," ⒸⒺ","")&IF(AND('Level Engine'!$GJ$4=1,OR($AL4='Level Engine'!$GJ$1,$AL4='Level Engine'!$GJ$2)),"","")&IF(ABS(N(IFERROR(INDEX('Level Engine'!$AE$9:$AE$55,MATCH($AL4,'Level Engine'!$AA$9:$AA$55,0)),0)))>='Level Engine'!$BG$85,IF(N(IFERROR(INDEX('Level Engine'!$AE$9:$AE$55,MATCH($AL4,'Level Engine'!$AA$9:$AA$55,0)),0))>0," Δ+"," Δ−"),"")&IFERROR(IF(AND(ISNUMBER(MATCH($AL4,'Level Engine'!$AA$9:$AA$55,0)),ABS(N(IFERROR(INDEX('Level Engine'!$AE$9:$AE$55,MATCH($AL4,'Level Engine'!$AA$9:$AA$55,0)),0)))<'Level Engine'!$BG$85,ABS(N(IFERROR(INDEX('Level Engine'!$AE$9:$AE$55,MATCH($AL4,'Level Engine'!$AA$9:$AA$55,0)),0)))<=ABS(N(IFERROR(INDEX('Level Engine'!$AE$9:$AE$55,MATCH($AL4+5,'Level Engine'!$AA$9:$AA$55,0)),0))),ABS(N(IFERROR(INDEX('Level Engine'!$AE$9:$AE$55,MATCH($AL4,'Level Engine'!$AA$9:$AA$55,0)),0)))<=ABS(N(IFERROR(INDEX('Level Engine'!$AE$9:$AE$55,MATCH($AL4-5,'Level Engine'!$AA$9:$AA$55,0)),0))),OR(AND(ABS(N(IFERROR(INDEX('Level Engine'!$AE$9:$AE$55,MATCH($AL4+5,'Level Engine'!$AA$9:$AA$55,0)),0)))>='Level Engine'!$BG$85,ABS(N(IFERROR(INDEX('Level Engine'!$AE$9:$AE$55,MATCH($AL4,'Level Engine'!$AA$9:$AA$55,0)),0)))<='Level Engine'!$BG$88*ABS(N(IFERROR(INDEX('Level Engine'!$AE$9:$AE$55,MATCH($AL4+5,'Level Engine'!$AA$9:$AA$55,0)),0)))),AND(ABS(N(IFERROR(INDEX('Level Engine'!$AE$9:$AE$55,MATCH($AL4-5,'Level Engine'!$AA$9:$AA$55,0)),0)))>='Level Engine'!$BG$85,ABS(N(IFERROR(INDEX('Level Engine'!$AE$9:$AE$55,MATCH($AL4,'Level Engine'!$AA$9:$AA$55,0)),0)))<='Level Engine'!$BG$88*ABS(N(IFERROR(INDEX('Level Engine'!$AE$9:$AE$55,MATCH($AL4-5,'Level Engine'!$AA$9:$AA$55,0)),0)))))),IF(AND('King Node Model'!$A$8="Pos",N('Level Engine'!$BG$72)<>1),""," ∅"),""),"")&IF(IFERROR(INDEX('Level Engine'!$JD$9:$JD$55,MATCH($AL4,'Level Engine'!$AA$9:$AA$55,0)),"")="P"," P-OI",IF(IFERROR(INDEX('Level Engine'!$JD$9:$JD$55,MATCH($AL4,'Level Engine'!$AA$9:$AA$55,0)),"")="C"," C-OI","")) -> 7880 C-OI | C4: =IF(AND(ISNUMBER($AM4),$AM4>0,ISNUMBER($AO4),$AO$1>0),REPT("█",ROUND($AO4/$AO$1*26,0)),"") | D4: =IF(NOT(ISNUMBER($AL4)),"",IF(IFERROR(INDEX('Level Engine'!$FS$9:$FS$55,MATCH($AL4,'Level Engine'!$AA$9:$AA$55,0)),0)=1,"⊙","")) | E4: ="VIX "&TEXT('King Node Model'!$B$5,"0.0") -> VIX 15.4 | G4: ="VVIX "&TEXT('King Node Model'!$D$5,"0.0") -> VVIX 86.6 | I4: ="VIX1D "&TEXT('King Node Model'!$F$5,"0.0") -> VIX1D 8.5 | Q4: Level | R4: Direction | S4: ATM IV | AL4: ='King Node Model'!A30 -> 7880 | AM4: ='King Node Model'!C30 -> 75905 | AN4: ='King Node Model'!D26 -> 7805 | AO4: ='King Node Model'!B30 -> 76929 | AY4: =IF(AND($B$2="Hide unsafe",$BB4=1),0,IF(AND(OR(AND(AND(ISNUMBER($AL4),OR(AND($AL4>=$AQ$22,$AL4<=$AR$22,$AS$22=1),$AL4=$AQ$22,$AL4=$AR$22,$AL4=$AQ$23,$AL4=$AR$23,$AL4=$AQ$24,$AL4=$AR$24),NOT(OR($AL4=$AN$5,$AL4=$AN$6,$AL4=$AN$7,$AL4=$AN$8,$AL4=$AN$10,$AL4=$AN$11))),NOT(OR(AND('King Node Model'!$P$13="Up",OR($AL4=$AQ$22,$AL4=$AQ$23,$AL4=$AQ$24,$AL4='King Node Model'!$AM$20,$AL4='King Node Model'!$AM$21,$AL4='King Node Model'!$AM$22),OR(AND('King Node Model'!$B$23-$AL4>=0,'King Node Model'!$B$23-$AL4<=5),AND('King Node Model'!$C$23-$AL4>=0,'King Node Model'!$C$23-$AL4<=5))),AND('King Node Model'!$P$13="Down",OR($AL4=$AR$22,$AL4=$AR$23,$AL4=$AR$24,$AL4='King Node Model'!$AN$20,$AL4='King Node Model'!$AN$21,$AL4='King Node Model'!$AN$22),OR(AND($AL4-'King Node Model'!$B$23>=0,$AL4-'King Node Model'!$B$23<=5),AND($AL4-'King Node Model'!$C$24>=0,$AL4-'King Node Model'!$C$24<=5)))))),AND(AND(ISNUMBER($AL4),OR(AND($AL4>=$AQ$22,$AL4<=$AR$22,$AS$22=1),$AL4=$AQ$22,$AL4=$AR$22,$AL4=$AQ$23,$AL4=$AR$23,$AL4=$AQ$24,$AL4=$AR$24,$AL4='King Node Model'!$AL$42,$AL4='King Node Model'!$AL$43),OR($AL4=$AN$5,$AL4=$AN$6,$AL4=$AN$7,$AL4=$AN$8,$AL4=$AN$10,$AL4=$AN$11)),NOT(OR(AND('King Node Model'!$P$13="Up",OR($AL4=$AQ$22,$AL4=$AQ$23,$AL4=$AQ$24,$AL4='King Node Model'!$AM$20,$AL4='King Node Model'!$AM$21,$AL4='King Node Model'!$AM$22),OR(AND('King Node Model'!$B$23-$AL4>=0,'King Node Model'!$B$23-$AL4<=5),AND('King Node Model'!$C$23-$AL4>=0,'King Node Model'!$C$23-$AL4<=5))),AND('King Node Model'!$P$13="Down",OR($AL4=$AR$22,$AL4=$AR$23,$AL4=$AR$24,$AL4='King Node Model'!$AN$20,$AL4='King Node Model'!$AN$21,$AL4='King Node Model'!$AN$22),OR(AND($AL4-'King Node Model'!$B$23>=0,$AL4-'King Node Model'!$B$23<=5),AND($AL4-'King Node Model'!$C$24>=0,$AL4-'King Node Model'!$C$24<=5)))))),AND(AND(ISNUMBER($AL4),OR(AND($AL4>='King Node Model'!$AM$20,$AL4<='King Node Model'!$AN$20,$AS$23=1),$AL4='King Node Model'!$AM$20,$AL4='King Node Model'!$AN$20,$AL4='King Node Model'!$AM$21,$AL4='King Node Model'!$AN$21,$AL4='King Node Model'!$AM$22,$AL4='King Node Model'!$AN$22),NOT(OR($AL4=$AN$5,$AL4=$AN$6,$AL4=$AN$7,$AL4=$AN$8,$AL4=$AN$10,$AL4=$AN$11))),NOT(AND(ISNUMBER('King Node Model'!$F$24),$AL4='King Node Model'!$F$24,IFERROR(INDEX('Level Engine'!$JN$9:$JN$55,MATCH($AL4,'Level Engine'!$AA$9:$AA$55,0)),0)<>1))),AND(AND(ISNUMBER($AL4),OR(AND($AL4>='King Node Model'!$AM$20,$AL4<='King Node Model'!$AN$20,$AS$23=1),$AL4='King Node Model'!$AM$20,$AL4='King Node Model'!$AN$20,$AL4='King Node Model'!$AM$21,$AL4='King Node Model'!$AN$21,$AL4='King Node Model'!$AM$22,$AL4='King Node Model'!$AN$22,$AL4='King Node Model'!$AL$49,$AL4='King Node Model'!$AL$50),OR($AL4=$AN$5,$AL4=$AN$6,$AL4=$AN$7,$AL4=$AN$8,$AL4=$AN$10,$AL4=$AN$11)),NOT(OR(AND('King Node Model'!$P$13="Up",OR($AL4=$AQ$22,$AL4=$AQ$23,$AL4=$AQ$24,$AL4='King Node Model'!$AM$20,$AL4='King Node Model'!$AM$21,$AL4='King Node Model'!$AM$22),OR(AND('King Node Model'!$B$23-$AL4>=0,'King Node Model'!$B$23-$AL4<=5),AND('King Node Model'!$C$23-$AL4>=0,'King Node Model'!$C$23-$AL4<=5))),AND('King Node Model'!$P$13="Down",OR($AL4=$AR$22,$AL4=$AR$23,$AL4=$AR$24,$AL4='King Node Model'!$AN$20,$AL4='King Node Model'!$AN$21,$AL4='King Node Model'!$AN$22),OR(AND($AL4-'King Node Model'!$B$23>=0,$AL4-'King Node Model'!$B$23<=5),AND($AL4-'King Node Model'!$C$24>=0,$AL4-'King Node Model'!$C$24<=5))))))),OR(COUNTIF('Level Engine'!$W$9:$W$14,$AL4)>0,COUNTIF('Level Engine'!$W$18:$W$23,$AL4)>0)),1,0)) -> 0 | AZ4: =IF($B$2="Hide unsafe",0,$BB4) -> 0 | BB4: =IF(OR(AND($AL4='King Node Model'!$AL$42,$AP$45<>"RASP"),AND($AL4='King Node Model'!$AL$43,$AP$46<>"RASP"),AND($AL4='King Node Model'!$AL$49,$AP$52<>"RASP"),AND($AL4='King Node Model'!$AL$50,$AP$53<>"RASP"),AND($AL4='King Node Model'!$AL$44,$AP$47<>"RASP"),AND($AL4='King Node Model'!$AL$51,$AP$54<>"RASP")),0,IF(AND(AND(ISNUMBER($AL4),OR(AND($AL4>=$AQ$22,$AL4<=$AR$22,$AP$45="RASP"),AND($AL4>=$AQ$23,$AL4<=$AR$23,$AP$46="RASP"),AND($AL4>=$AQ$24,$AL4<=$AR$24,$AP$47="RASP"),AND($AL4>='King Node Model'!$AM$20,$AL4<='King Node Model'!$AN$20,$AP$52="RASP",NOT($L$52=$AW$52)),AND($AL4='King Node Model'!$B$23,$AP$52="RASP",$L$52=$AW$52),AND($AL4>='King Node Model'!$AM$21,$AL4<='King Node Model'!$AN$21,$AP$53="RASP",NOT($L$53=$AW$53)),AND($AL4='King Node Model'!$B$23,$AP$53="RASP",$L$53=$AW$53),AND($AL4>='King Node Model'!$AM$22,$AL4<='King Node Model'!$AN$22,$AP$54="RASP"),AND($AL4>=IFERROR(INDEX('Level Engine'!$AT$9:$AT$55,MATCH('King Node Model'!$AL$42,'Level Engine'!$AA$9:$AA$55,0)),""),$AL4<=IFERROR(INDEX('Level Engine'!$AU$9:$AU$55,MATCH('King Node Model'!$AL$42,'Level Engine'!$AA$9:$AA$55,0)),""),$AP$45="RASP"),AND($AL4>=IFERROR(INDEX('Level Engine'!$AT$9:$AT$55,MATCH('King Node Model'!$AL$43,'Level Engine'!$AA$9:$AA$55,0)),""),$AL4<=IFERROR(INDEX('Level Engine'!$AU$9:$AU$55,MATCH('King Node Model'!$AL$43,'Level Engine'!$AA$9:$AA$55,0)),""),$AP$46="RASP"),AND($AL4>=IFERROR(INDEX('Level Engine'!$AT$9:$AT$55,MATCH('King Node Model'!$AL$44,'Level Engine'!$AA$9:$AA$55,0)),""),$AL4<=IFERROR(INDEX('Level Engine'!$AU$9:$AU$55,MATCH('King Node Model'!$AL$44,'Level Engine'!$AA$9:$AA$55,0)),""),$AP$47="RASP"),AND($AL4>=IFERROR(INDEX('Level Engine'!$AT$9:$AT$55,MATCH('King Node Model'!$AL$49,'Level Engine'!$AA$9:$AA$55,0)),""),$AL4<=IFERROR(INDEX('Level Engine'!$AU$9:$AU$55,MATCH('King Node Model'!$AL$49,'Level Engine'!$AA$9:$AA$55,0)),""),$AP$52="RASP",NOT($L$52=$AW$52)),AND($AL4>=IFERROR(INDEX('Level Engine'!$AT$9:$AT$55,MATCH('King Node Model'!$AL$50,'Level Engine'!$AA$9:$AA$55,0)),""),$AL4<=IFERROR(INDEX('Level Engine'!$AU$9:$AU$55,MATCH('King Node Model'!$AL$50,'Level Engine'!$AA$9:$AA$55,0)),""),$AP$53="RASP",NOT($L$53=$AW$53)),AND($AL4>=IFERROR(INDEX('Level Engine'!$AT$9:$AT$55,MATCH('King Node Model'!$AL$51,'Level Engine'!$AA$9:$AA$55,0)),""),$AL4<=IFERROR(INDEX('Level Engine'!$AU$9:$AU$55,MATCH('King Node Model'!$AL$51,'Level Engine'!$AA$9:$AA$55,0)),""),$AP$54="RASP"))),NOT(AND(ISNUMBER('King Node Model'!$F$24),$AL4='King Node Model'!$F$24,IFERROR(INDEX('Level Engine'!$JN$9:$JN$55,MATCH($AL4,'Level Engine'!$AA$9:$AA$55,0)),0)<>1,$AL4<>'King Node Model'!$AL$42,$AL4<>'King Node Model'!$AL$43,$AL4<>'King Node Model'!$AL$44,$AL4<>'King Node Model'!$AL$49,$AL4<>'King Node Model'!$AL$50,$AL4<>'King Node Model'!$AL$51))),1,0)) -> 0 | CO4: =IF(NOT(ISNUMBER($AL4)),"",IF(NOT(ISNUMBER(IFERROR(INDEX('Level Engine'!$FT$9:$FT$55,MATCH($AL4,'Level Engine'!$AA$9:$AA$55,0)),""))),"",IF(IFERROR(INDEX('Level Engine'!$FT$9:$FT$55,MATCH($AL4,'Level Engine'!$AA$9:$AA$55,0)),"")<0,0,2)+IF(ABS(IFERROR(INDEX('Level Engine'!$FT$9:$FT$55,MATCH($AL4,'Level Engine'!$AA$9:$AA$55,0)),""))>='Level Engine'!$FT$2,2,1))) -> 4 | DJ4: =IF(ISNUMBER($AL4),IF($AL4='Level Engine'!$BG$122," ⫪","")&IF($AL4='Level Engine'!$BG$118," S↑"&IFERROR(INDEX('Level Engine'!$MV$9:$MV$55,MATCH($AL4,'Level Engine'!$AA$9:$AA$55,0)),""),"")&IF($AL4='Level Engine'!$BG$119," S↓"&IFERROR(INDEX('Level Engine'!$MV$9:$MV$55,MATCH($AL4,'Level Engine'!$AA$9:$AA$55,0)),""),"")&IF($AL4='Level Engine'!$BG$120," D↑","")&IF($AL4='Level Engine'!$BG$121," D↓","")&IFERROR(INDEX('Level Engine'!$LG$9:$LG$55,MATCH($AL4,'Level Engine'!$AA$9:$AA$55,0)),"")&IF(IFERROR(INDEX('Level Engine'!$MA$9:$MA$55,MATCH($AL4,'Level Engine'!$AA$9:$AA$55,0)),0)=1," SAND","")&IF(IFERROR(INDEX('Level Engine'!$LM$9:$LM$55,MATCH($AL4,'Level Engine'!$AA$9:$AA$55,0)),0)>0," TP","")&IFERROR(" r"&MATCH($AL4,'Level Engine'!$W$9:$W$14,0),IFERROR(" s"&MATCH($AL4,'Level Engine'!$W$18:$W$23,0),""))&IF($AL4='Level Engine'!$BG$165," ◇","")&IF(N($DZ4)=1,IF($AL4>'Level Engine'!$BG$165," ⚠ DOM↓"," ⚠ DOM↑")&'Level Engine'!$BG$165,""),"") | DK4: =IF(AND(ISNUMBER($AL4),OR($AL4='King Node Model'!$AL$42,$AL4='King Node Model'!$AL$43,$AL4='King Node Model'!$AL$44)),IFERROR(MATCH($AL4,'Level Engine'!$W$9:$W$14,0),""),"") | DL4: =IF(AND(ISNUMBER($AL4),OR($AL4='King Node Model'!$AL$49,$AL4='King Node Model'!$AL$50,$AL4='King Node Model'!$AL$51)),IFERROR(MATCH($AL4,'Level Engine'!$W$18:$W$23,0),""),"") | DM4: =IF(AND(ISNUMBER($AL4),IFERROR(INDEX('Level Engine'!$LC$9:$LC$55,MATCH($AL4,'Level Engine'!$AA$9:$AA$55,0)),0)=1,OR($AL4=$AN$3,IFERROR(INDEX('Level Engine'!$LB$9:$LB$55,MATCH($AL4,'Level Engine'!$AA$9:$AA$55,0)),0)=1)),1,0) -> 0 | DZ4: =IF(ISNUMBER($AL4),IF(IFERROR(INDEX('Level Engine'!$NJ$9:$NJ$55,MATCH($AL4,'Level Engine'!$AA$9:$AA$55,0)),0)=1,1,0),0)
B5: =TEXT(IF(IF('Level Engine'!$GJ$4=1,$AL5='Level Engine'!$GJ$3,AND($AL5-$AM$2>-2.5,$AL5-$AM$2<=2.5)),$AM$2,$AL5),"0")&IF($AL5=$AN$1," ★","")&IF($AL5=$AN$2," ★","")&IF($AL5=$AN$3," ◆","")&IF(AND(ISNUMBER($AN$4),$AL5=$AN$4)," Ⓕ","")&IF(OR(AND(ISNUMBER('Level Engine'!$BG$87),$AL5='Level Engine'!$BG$87),AND(ISNUMBER('Level Engine'!$BG$105),$AL5='Level Engine'!$BG$105))," ζ","")&IF(AND(ISNUMBER($AN$35),$AL5=$AN$35)," ⓏⒼ","")&IF(OR($AL5='Level Engine'!$CP$4,$AL5='Level Engine'!$CP$5,$AL5='Level Engine'!$CP$6,$AL5='Level Engine'!$CP$7)," ☄","")&IF(OR($AL5=$AN$5,$AL5=$AN$8)," ║1","")&IF(OR($AL5=$AN$6,$AL5=$AN$10)," ║2","")&IF(OR($AL5=$AN$7,$AL5=$AN$11)," ║3","")&IF(OR($AL5=$AN$13,$AL5=$AN$16)," ▣1","")&IF(OR($AL5=$AN$14,$AL5=$AN$17)," ▣2","")&IF(OR($AL5=$AN$15,$AL5=$AN$18)," ▣3","")&IF(AND(NOT(OR(AND(ISNUMBER(SEARCH("chop edge",$E$45)),IFERROR(ABS($AL5-'King Node Model'!$AL$42)<=5,FALSE),NOT(ISNUMBER(SEARCH("UNSAFE",$L$45)))),AND(ISNUMBER(SEARCH("chop edge",$E$46)),IFERROR(ABS($AL5-'King Node Model'!$AL$43)<=5,FALSE),NOT(ISNUMBER(SEARCH("UNSAFE",$L$46)))),AND(ISNUMBER(SEARCH("chop edge",$E$52)),IFERROR(ABS($AL5-'King Node Model'!$AL$49)<=5,FALSE),NOT(ISNUMBER(SEARCH("UNSAFE",$L$52)))),AND(ISNUMBER(SEARCH("chop edge",$E$53)),IFERROR(ABS($AL5-'King Node Model'!$AL$50)<=5,FALSE),NOT(ISNUMBER(SEARCH("UNSAFE",$L$53)))))),OR(AND(IFERROR(INDEX('Level Engine'!$IB$9:$IB$55,MATCH('King Node Model'!$AL$49,'Level Engine'!$AA$9:$AA$55,0)),0)<>1,$AL5=IFERROR(INDEX('Level Engine'!$AU$9:$AU$55,MATCH('King Node Model'!$AL$49,'Level Engine'!$AA$9:$AA$55,0)),""),IFERROR(INDEX('Level Engine'!$AU$9:$AU$55,MATCH('King Node Model'!$AL$49,'Level Engine'!$AA$9:$AA$55,0)),"")<>IFERROR(INDEX('Level Engine'!$AT$9:$AT$55,MATCH('King Node Model'!$AL$49,'Level Engine'!$AA$9:$AA$55,0)),"")),AND(IFERROR(INDEX('Level Engine'!$IB$9:$IB$55,MATCH('King Node Model'!$AL$50,'Level Engine'!$AA$9:$AA$55,0)),0)<>1,$AL5=IFERROR(INDEX('Level Engine'!$AU$9:$AU$55,MATCH('King Node Model'!$AL$50,'Level Engine'!$AA$9:$AA$55,0)),""),IFERROR(INDEX('Level Engine'!$AU$9:$AU$55,MATCH('King Node Model'!$AL$50,'Level Engine'!$AA$9:$AA$55,0)),"")<>IFERROR(INDEX('Level Engine'!$AT$9:$AT$55,MATCH('King Node Model'!$AL$50,'Level Engine'!$AA$9:$AA$55,0)),"")))),IF(OR('King Node Model'!$A$8="Neg",N('Level Engine'!$BG$72)=1),""," ⒷⒽ"),"")&IF(AND(NOT(OR(AND(ISNUMBER(SEARCH("chop edge",$E$45)),IFERROR(ABS($AL5-'King Node Model'!$AL$42)<=5,FALSE),NOT(ISNUMBER(SEARCH("UNSAFE",$L$45)))),AND(ISNUMBER(SEARCH("chop edge",$E$46)),IFERROR(ABS($AL5-'King Node Model'!$AL$43)<=5,FALSE),NOT(ISNUMBER(SEARCH("UNSAFE",$L$46)))),AND(ISNUMBER(SEARCH("chop edge",$E$52)),IFERROR(ABS($AL5-'King Node Model'!$AL$49)<=5,FALSE),NOT(ISNUMBER(SEARCH("UNSAFE",$L$52)))),AND(ISNUMBER(SEARCH("chop edge",$E$53)),IFERROR(ABS($AL5-'King Node Model'!$AL$50)<=5,FALSE),NOT(ISNUMBER(SEARCH("UNSAFE",$L$53)))))),OR(AND(IFERROR(INDEX('Level Engine'!$IB$9:$IB$55,MATCH('King Node Model'!$AL$42,'Level Engine'!$AA$9:$AA$55,0)),0)<>1,$AL5=IFERROR(INDEX('Level Engine'!$AT$9:$AT$55,MATCH('King Node Model'!$AL$42,'Level Engine'!$AA$9:$AA$55,0)),""),IFERROR(INDEX('Level Engine'!$AT$9:$AT$55,MATCH('King Node Model'!$AL$42,'Level Engine'!$AA$9:$AA$55,0)),"")<>IFERROR(INDEX('Level Engine'!$AU$9:$AU$55,MATCH('King Node Model'!$AL$42,'Level Engine'!$AA$9:$AA$55,0)),"")),AND(IFERROR(INDEX('Level Engine'!$IB$9:$IB$55,MATCH('King Node Model'!$AL$43,'Level Engine'!$AA$9:$AA$55,0)),0)<>1,$AL5=IFERROR(INDEX('Level Engine'!$AT$9:$AT$55,MATCH('King Node Model'!$AL$43,'Level Engine'!$AA$9:$AA$55,0)),""),IFERROR(INDEX('Level Engine'!$AT$9:$AT$55,MATCH('King Node Model'!$AL$43,'Level Engine'!$AA$9:$AA$55,0)),"")<>IFERROR(INDEX('Level Engine'!$AU$9:$AU$55,MATCH('King Node Model'!$AL$43,'Level Engine'!$AA$9:$AA$55,0)),"")))),IF(OR('King Node Model'!$A$8="Neg",N('Level Engine'!$BG$72)=1),""," ⒷⓁ"),"")&IF(OR(AND($AL5>='King Node Model'!$AM$17,$AL5<='King Node Model'!$AN$17,$AP$45="RASP"),AND($AL5>='King Node Model'!$AM$18,$AL5<='King Node Model'!$AN$18,$AP$46="RASP"),AND($AL5>='King Node Model'!$AM$19,$AL5<='King Node Model'!$AN$19,$AP$47="RASP"),AND($AL5>='King Node Model'!$AM$20,$AL5<='King Node Model'!$AN$20,$AP$52="RASP"),AND($AL5>='King Node Model'!$AM$21,$AL5<='King Node Model'!$AN$21,$AP$53="RASP"),AND($AL5>='King Node Model'!$AM$22,$AL5<='King Node Model'!$AN$22,$AP$54="RASP")),"","")&IF(IF('Level Engine'!$GJ$4=1,$AL5='Level Engine'!$GJ$3,AND($AL5-$AM$2>-2.5,$AL5-$AM$2<=2.5))," ◄","")&IF(IFERROR(INDEX('Level Engine'!$GV$9:$GV$55,MATCH($AL5,'Level Engine'!$AA$9:$AA$55,0)),0)=1," Ⓥ"&IF(IFERROR(INDEX('Level Engine'!$ET$9:$ET$55,MATCH($AL5,'Level Engine'!$AA$9:$AA$55,0)),0)=1,"+",""),"")&IF(OR(AND($AL5=$AN$38,IFERROR(INDEX('Level Engine'!$AN$9:$AN$55,MATCH($AL5,'Level Engine'!$AA$9:$AA$55,0)),0)<>1),$AL5=$AN$39)," ⊙","")&IF(AND(OR('King Node Model'!$A$8="Neg",N('Level Engine'!$BG$72)=1),ABS(MIN($AM$3:$AM$64))>MAX($AM$3:$AM$64),$AN$2<$AM$2,$AL5<$AM$2,ABS($AL5-$AN$2)<=5,IFERROR(VALUE(MID('King Node Model'!$K$26,FIND(":",'King Node Model'!$K$26)-2,2)),0)>=19,IFERROR(INDEX('Level Engine'!$EJ$9:$EJ$55,MATCH($AL5,'Level Engine'!$AA$9:$AA$55,0)),0)=0,$AN$3>$AM$2)," ⟲rev","")&IF($AL5='King Node Model'!$F$24," ⟂","")&$DJ5&IF(IFERROR(INDEX('Level Engine'!$EN$9:$EN$55,MATCH($AL5,'Level Engine'!$AA$9:$AA$55,0)),0)=1," Ⓟ"&IF(AND(OR('King Node Model'!$A$8="Neg",N('Level Engine'!$BG$72)=1),IFERROR(INDEX('Level Engine'!$AN$9:$AN$55,MATCH($AL5,'Level Engine'!$AA$9:$AA$55,0)),0)<>1)," NO-REV",""),"")&IF(AND(ISNUMBER($AL5),OR(AND(ISNUMBER(SEARCH("chop edge",$E$45)),$AL5='King Node Model'!$AL$42),AND(ISNUMBER(SEARCH("chop edge",$E$46)),$AL5='King Node Model'!$AL$43),AND(ISNUMBER(SEARCH("chop edge",$E$52)),$AL5='King Node Model'!$AL$49),AND(ISNUMBER(SEARCH("chop edge",$E$53)),$AL5='King Node Model'!$AL$50)))," ⒸⒺ","")&IF(AND('Level Engine'!$GJ$4=1,OR($AL5='Level Engine'!$GJ$1,$AL5='Level Engine'!$GJ$2)),"","")&IF(ABS(N(IFERROR(INDEX('Level Engine'!$AE$9:$AE$55,MATCH($AL5,'Level Engine'!$AA$9:$AA$55,0)),0)))>='Level Engine'!$BG$85,IF(N(IFERROR(INDEX('Level Engine'!$AE$9:$AE$55,MATCH($AL5,'Level Engine'!$AA$9:$AA$55,0)),0))>0," Δ+"," Δ−"),"")&IFERROR(IF(AND(ISNUMBER(MATCH($AL5,'Level Engine'!$AA$9:$AA$55,0)),ABS(N(IFERROR(INDEX('Level Engine'!$AE$9:$AE$55,MATCH($AL5,'Level Engine'!$AA$9:$AA$55,0)),0)))<'Level Engine'!$BG$85,ABS(N(IFERROR(INDEX('Level Engine'!$AE$9:$AE$55,MATCH($AL5,'Level Engine'!$AA$9:$AA$55,0)),0)))<=ABS(N(IFERROR(INDEX('Level Engine'!$AE$9:$AE$55,MATCH($AL5+5,'Level Engine'!$AA$9:$AA$55,0)),0))),ABS(N(IFERROR(INDEX('Level Engine'!$AE$9:$AE$55,MATCH($AL5,'Level Engine'!$AA$9:$AA$55,0)),0)))<=ABS(N(IFERROR(INDEX('Level Engine'!$AE$9:$AE$55,MATCH($AL5-5,'Level Engine'!$AA$9:$AA$55,0)),0))),OR(AND(ABS(N(IFERROR(INDEX('Level Engine'!$AE$9:$AE$55,MATCH($AL5+5,'Level Engine'!$AA$9:$AA$55,0)),0)))>='Level Engine'!$BG$85,ABS(N(IFERROR(INDEX('Level Engine'!$AE$9:$AE$55,MATCH($AL5,'Level Engine'!$AA$9:$AA$55,0)),0)))<='Level Engine'!$BG$88*ABS(N(IFERROR(INDEX('Level Engine'!$AE$9:$AE$55,MATCH($AL5+5,'Level Engine'!$AA$9:$AA$55,0)),0)))),AND(ABS(N(IFERROR(INDEX('Level Engine'!$AE$9:$AE$55,MATCH($AL5-5,'Level Engine'!$AA$9:$AA$55,0)),0)))>='Level Engine'!$BG$85,ABS(N(IFERROR(INDEX('Level Engine'!$AE$9:$AE$55,MATCH($AL5,'Level Engine'!$AA$9:$AA$55,0)),0)))<='Level Engine'!$BG$88*ABS(N(IFERROR(INDEX('Level Engine'!$AE$9:$AE$55,MATCH($AL5-5,'Level Engine'!$AA$9:$AA$55,0)),0)))))),IF(AND('King Node Model'!$A$8="Pos",N('Level Engine'!$BG$72)<>1),""," ∅"),""),"")&IF(IFERROR(INDEX('Level Engine'!$JD$9:$JD$55,MATCH($AL5,'Level Engine'!$AA$9:$AA$55,0)),"")="P"," P-OI",IF(IFERROR(INDEX('Level Engine'!$JD$9:$JD$55,MATCH($AL5,'Level Engine'!$AA$9:$AA$55,0)),"")="C"," C-OI","")) -> 7875 | C5: =IF(AND(ISNUMBER($AM5),$AM5>0,ISNUMBER($AO5),$AO$1>0),REPT("█",ROUND($AO5/$AO$1*26,0)),"") | D5: =IF(NOT(ISNUMBER($AL5)),"",IF(IFERROR(INDEX('Level Engine'!$FS$9:$FS$55,MATCH($AL5,'Level Engine'!$AA$9:$AA$55,0)),0)=1,"⊙","")) | E5: ="IV REGIME "&'King Node Model'!$P$9 -> IV REGIME Recovery Day with Local Wiggle | K5: =IF(ISNUMBER(SEARCH("Coiled Spring",'King Node Model'!$P$9)),"VIX "&'King Node Model'!$P$4&" VVIX "&'King Node Model'!$P$5&" → "&IF(AND('King Node Model'!$P$4="Up",'King Node Model'!$P$5="Up"),"High",IF(AND('King Node Model'!$P$4="Down",'King Node Model'!$P$5="Down"),"Low","MIXED")),"") | M5: =IF($L$5<>"",UPPER($L$5)&" IV (override)",IF('King Node Model'!$P$10="MIXED","MIXED IV — set override",IF('King Node Model'!$L$5="","",UPPER('King Node Model'!$L$5)&" IV"))) -> LOW IV | Q5: =PROPER('King Node Model'!$L$5) -> Low | R5: =(IF('Level Engine'!$D$5="UP","Rising",IF('Level Engine'!$D$5="DOWN","Falling","Flat")))&IF('Level Engine'!$BG$80<>""," (fast: "&IF(UPPER('Level Engine'!$BG$80)="UP","Rising",IF(UPPER('Level Engine'!$BG$80)="DOWN","Falling","Flat"))&")","") -> Rising (fast: Rising) | S5: =IF(ISNUMBER('Level Engine'!$C$3),'Level Engine'!$C$3,"") -> 0.137 | AL5: ='King Node Model'!A31 -> 7875 | AM5: ='King Node Model'!C31 -> 55016 | AN5: ='King Node Model'!T25 -> 7795 | AO5: ='King Node Model'!B31 -> 57578 | AY5: =IF(AND($B$2="Hide unsafe",$BB5=1),0,IF(AND(OR(AND(AND(ISNUMBER($AL5),OR(AND($AL5>=$AQ$22,$AL5<=$AR$22,$AS$22=1),$AL5=$AQ$22,$AL5=$AR$22,$AL5=$AQ$23,$AL5=$AR$23,$AL5=$AQ$24,$AL5=$AR$24),NOT(OR($AL5=$AN$5,$AL5=$AN$6,$AL5=$AN$7,$AL5=$AN$8,$AL5=$AN$10,$AL5=$AN$11))),NOT(OR(AND('King Node Model'!$P$13="Up",OR($AL5=$AQ$22,$AL5=$AQ$23,$AL5=$AQ$24,$AL5='King Node Model'!$AM$20,$AL5='King Node Model'!$AM$21,$AL5='King Node Model'!$AM$22),OR(AND('King Node Model'!$B$23-$AL5>=0,'King Node Model'!$B$23-$AL5<=5),AND('King Node Model'!$C$23-$AL5>=0,'King Node Model'!$C$23-$AL5<=5))),AND('King Node Model'!$P$13="Down",OR($AL5=$AR$22,$AL5=$AR$23,$AL5=$AR$24,$AL5='King Node Model'!$AN$20,$AL5='King Node Model'!$AN$21,$AL5='King Node Model'!$AN$22),OR(AND($AL5-'King Node Model'!$B$23>=0,$AL5-'King Node Model'!$B$23<=5),AND($AL5-'King Node Model'!$C$24>=0,$AL5-'King Node Model'!$C$24<=5)))))),AND(AND(ISNUMBER($AL5),OR(AND($AL5>=$AQ$22,$AL5<=$AR$22,$AS$22=1),$AL5=$AQ$22,$AL5=$AR$22,$AL5=$AQ$23,$AL5=$AR$23,$AL5=$AQ$24,$AL5=$AR$24,$AL5='King Node Model'!$AL$42,$AL5='King Node Model'!$AL$43),OR($AL5=$AN$5,$AL5=$AN$6,$AL5=$AN$7,$AL5=$AN$8,$AL5=$AN$10,$AL5=$AN$11)),NOT(OR(AND('King Node Model'!$P$13="Up",OR($AL5=$AQ$22,$AL5=$AQ$23,$AL5=$AQ$24,$AL5='King Node Model'!$AM$20,$AL5='King Node Model'!$AM$21,$AL5='King Node Model'!$AM$22),OR(AND('King Node Model'!$B$23-$AL5>=0,'King Node Model'!$B$23-$AL5<=5),AND('King Node Model'!$C$23-$AL5>=0,'King Node Model'!$C$23-$AL5<=5))),AND('King Node Model'!$P$13="Down",OR($AL5=$AR$22,$AL5=$AR$23,$AL5=$AR$24,$AL5='King Node Model'!$AN$20,$AL5='King Node Model'!$AN$21,$AL5='King Node Model'!$AN$22),OR(AND($AL5-'King Node Model'!$B$23>=0,$AL5-'King Node Model'!$B$23<=5),AND($AL5-'King Node Model'!$C$24>=0,$AL5-'King Node Model'!$C$24<=5)))))),AND(AND(ISNUMBER($AL5),OR(AND($AL5>='King Node Model'!$AM$20,$AL5<='King Node Model'!$AN$20,$AS$23=1),$AL5='King Node Model'!$AM$20,$AL5='King Node Model'!$AN$20,$AL5='King Node Model'!$AM$21,$AL5='King Node Model'!$AN$21,$AL5='King Node Model'!$AM$22,$AL5='King Node Model'!$AN$22),NOT(OR($AL5=$AN$5,$AL5=$AN$6,$AL5=$AN$7,$AL5=$AN$8,$AL5=$AN$10,$AL5=$AN$11))),NOT(AND(ISNUMBER('King Node Model'!$F$24),$AL5='King Node Model'!$F$24,IFERROR(INDEX('Level Engine'!$JN$9:$JN$55,MATCH($AL5,'Level Engine'!$AA$9:$AA$55,0)),0)<>1))),AND(AND(ISNUMBER($AL5),OR(AND($AL5>='King Node Model'!$AM$20,$AL5<='King Node Model'!$AN$20,$AS$23=1),$AL5='King Node Model'!$AM$20,$AL5='King Node Model'!$AN$20,$AL5='King Node Model'!$AM$21,$AL5='King Node Model'!$AN$21,$AL5='King Node Model'!$AM$22,$AL5='King Node Model'!$AN$22,$AL5='King Node Model'!$AL$49,$AL5='King Node Model'!$AL$50),OR($AL5=$AN$5,$AL5=$AN$6,$AL5=$AN$7,$AL5=$AN$8,$AL5=$AN$10,$AL5=$AN$11)),NOT(OR(AND('King Node Model'!$P$13="Up",OR($AL5=$AQ$22,$AL5=$AQ$23,$AL5=$AQ$24,$AL5='King Node Model'!$AM$20,$AL5='King Node Model'!$AM$21,$AL5='King Node Model'!$AM$22),OR(AND('King Node Model'!$B$23-$AL5>=0,'King Node Model'!$B$23-$AL5<=5),AND('King Node Model'!$C$23-$AL5>=0,'King Node Model'!$C$23-$AL5<=5))),AND('King Node Model'!$P$13="Down",OR($AL5=$AR$22,$AL5=$AR$23,$AL5=$AR$24,$AL5='King Node Model'!$AN$20,$AL5='King Node Model'!$AN$21,$AL5='King Node Model'!$AN$22),OR(AND($AL5-'King Node Model'!$B$23>=0,$AL5-'King Node Model'!$B$23<=5),AND($AL5-'King Node Model'!$C$24>=0,$AL5-'King Node Model'!$C$24<=5))))))),OR(COUNTIF('Level Engine'!$W$9:$W$14,$AL5)>0,COUNTIF('Level Engine'!$W$18:$W$23,$AL5)>0)),1,0)) -> 0 | AZ5: =IF($B$2="Hide unsafe",0,$BB5) -> 0 | BB5: =IF(OR(AND($AL5='King Node Model'!$AL$42,$AP$45<>"RASP"),AND($AL5='King Node Model'!$AL$43,$AP$46<>"RASP"),AND($AL5='King Node Model'!$AL$49,$AP$52<>"RASP"),AND($AL5='King Node Model'!$AL$50,$AP$53<>"RASP"),AND($AL5='King Node Model'!$AL$44,$AP$47<>"RASP"),AND($AL5='King Node Model'!$AL$51,$AP$54<>"RASP")),0,IF(AND(AND(ISNUMBER($AL5),OR(AND($AL5>=$AQ$22,$AL5<=$AR$22,$AP$45="RASP"),AND($AL5>=$AQ$23,$AL5<=$AR$23,$AP$46="RASP"),AND($AL5>=$AQ$24,$AL5<=$AR$24,$AP$47="RASP"),AND($AL5>='King Node Model'!$AM$20,$AL5<='King Node Model'!$AN$20,$AP$52="RASP",NOT($L$52=$AW$52)),AND($AL5='King Node Model'!$B$23,$AP$52="RASP",$L$52=$AW$52),AND($AL5>='King Node Model'!$AM$21,$AL5<='King Node Model'!$AN$21,$AP$53="RASP",NOT($L$53=$AW$53)),AND($AL5='King Node Model'!$B$23,$AP$53="RASP",$L$53=$AW$53),AND($AL5>='King Node Model'!$AM$22,$AL5<='King Node Model'!$AN$22,$AP$54="RASP"),AND($AL5>=IFERROR(INDEX('Level Engine'!$AT$9:$AT$55,MATCH('King Node Model'!$AL$42,'Level Engine'!$AA$9:$AA$55,0)),""),$AL5<=IFERROR(INDEX('Level Engine'!$AU$9:$AU$55,MATCH('King Node Model'!$AL$42,'Level Engine'!$AA$9:$AA$55,0)),""),$AP$45="RASP"),AND($AL5>=IFERROR(INDEX('Level Engine'!$AT$9:$AT$55,MATCH('King Node Model'!$AL$43,'Level Engine'!$AA$9:$AA$55,0)),""),$AL5<=IFERROR(INDEX('Level Engine'!$AU$9:$AU$55,MATCH('King Node Model'!$AL$43,'Level Engine'!$AA$9:$AA$55,0)),""),$AP$46="RASP"),AND($AL5>=IFERROR(INDEX('Level Engine'!$AT$9:$AT$55,MATCH('King Node Model'!$AL$44,'Level Engine'!$AA$9:$AA$55,0)),""),$AL5<=IFERROR(INDEX('Level Engine'!$AU$9:$AU$55,MATCH('King Node Model'!$AL$44,'Level Engine'!$AA$9:$AA$55,0)),""),$AP$47="RASP"),AND($AL5>=IFERROR(INDEX('Level Engine'!$AT$9:$AT$55,MATCH('King Node Model'!$AL$49,'Level Engine'!$AA$9:$AA$55,0)),""),$AL5<=IFERROR(INDEX('Level Engine'!$AU$9:$AU$55,MATCH('King Node Model'!$AL$49,'Level Engine'!$AA$9:$AA$55,0)),""),$AP$52="RASP",NOT($L$52=$AW$52)),AND($AL5>=IFERROR(INDEX('Level Engine'!$AT$9:$AT$55,MATCH('King Node Model'!$AL$50,'Level Engine'!$AA$9:$AA$55,0)),""),$AL5<=IFERROR(INDEX('Level Engine'!$AU$9:$AU$55,MATCH('King Node Model'!$AL$50,'Level Engine'!$AA$9:$AA$55,0)),""),$AP$53="RASP",NOT($L$53=$AW$53)),AND($AL5>=IFERROR(INDEX('Level Engine'!$AT$9:$AT$55,MATCH('King Node Model'!$AL$51,'Level Engine'!$AA$9:$AA$55,0)),""),$AL5<=IFERROR(INDEX('Level Engine'!$AU$9:$AU$55,MATCH('King Node Model'!$AL$51,'Level Engine'!$AA$9:$AA$55,0)),""),$AP$54="RASP"))),NOT(AND(ISNUMBER('King Node Model'!$F$24),$AL5='King Node Model'!$F$24,IFERROR(INDEX('Level Engine'!$JN$9:$JN$55,MATCH($AL5,'Level Engine'!$AA$9:$AA$55,0)),0)<>1,$AL5<>'King Node Model'!$AL$42,$AL5<>'King Node Model'!$AL$43,$AL5<>'King Node Model'!$AL$44,$AL5<>'King Node Model'!$AL$49,$AL5<>'King Node Model'!$AL$50,$AL5<>'King Node Model'!$AL$51))),1,0)) -> 0 | CO5: =IF(NOT(ISNUMBER($AL5)),"",IF(NOT(ISNUMBER(IFERROR(INDEX('Level Engine'!$FT$9:$FT$55,MATCH($AL5,'Level Engine'!$AA$9:$AA$55,0)),""))),"",IF(IFERROR(INDEX('Level Engine'!$FT$9:$FT$55,MATCH($AL5,'Level Engine'!$AA$9:$AA$55,0)),"")<0,0,2)+IF(ABS(IFERROR(INDEX('Level Engine'!$FT$9:$FT$55,MATCH($AL5,'Level Engine'!$AA$9:$AA$55,0)),""))>='Level Engine'!$FT$2,2,1))) -> 4 | DJ5: =IF(ISNUMBER($AL5),IF($AL5='Level Engine'!$BG$122," ⫪","")&IF($AL5='Level Engine'!$BG$118," S↑"&IFERROR(INDEX('Level Engine'!$MV$9:$MV$55,MATCH($AL5,'Level Engine'!$AA$9:$AA$55,0)),""),"")&IF($AL5='Level Engine'!$BG$119," S↓"&IFERROR(INDEX('Level Engine'!$MV$9:$MV$55,MATCH($AL5,'Level Engine'!$AA$9:$AA$55,0)),""),"")&IF($AL5='Level Engine'!$BG$120," D↑","")&IF($AL5='Level Engine'!$BG$121," D↓","")&IFERROR(INDEX('Level Engine'!$LG$9:$LG$55,MATCH($AL5,'Level Engine'!$AA$9:$AA$55,0)),"")&IF(IFERROR(INDEX('Level Engine'!$MA$9:$MA$55,MATCH($AL5,'Level Engine'!$AA$9:$AA$55,0)),0)=1," SAND","")&IF(IFERROR(INDEX('Level Engine'!$LM$9:$LM$55,MATCH($AL5,'Level Engine'!$AA$9:$AA$55,0)),0)>0," TP","")&IFERROR(" r"&MATCH($AL5,'Level Engine'!$W$9:$W$14,0),IFERROR(" s"&MATCH($AL5,'Level Engine'!$W$18:$W$23,0),""))&IF($AL5='Level Engine'!$BG$165," ◇","")&IF(N($DZ5)=1,IF($AL5>'Level Engine'!$BG$165," ⚠ DOM↓"," ⚠ DOM↑")&'Level Engine'!$BG$165,""),"") | DK5: =IF(AND(ISNUMBER($AL5),OR($AL5='King Node Model'!$AL$42,$AL5='King Node Model'!$AL$43,$AL5='King Node Model'!$AL$44)),IFERROR(MATCH($AL5,'Level Engine'!$W$9:$W$14,0),""),"") | DL5: =IF(AND(ISNUMBER($AL5),OR($AL5='King Node Model'!$AL$49,$AL5='King Node Model'!$AL$50,$AL5='King Node Model'!$AL$51)),IFERROR(MATCH($AL5,'Level Engine'!$W$18:$W$23,0),""),"") | DM5: =IF(AND(ISNUMBER($AL5),IFERROR(INDEX('Level Engine'!$LC$9:$LC$55,MATCH($AL5,'Level Engine'!$AA$9:$AA$55,0)),0)=1,OR($AL5=$AN$3,IFERROR(INDEX('Level Engine'!$LB$9:$LB$55,MATCH($AL5,'Level Engine'!$AA$9:$AA$55,0)),0)=1)),1,0) -> 0 | DZ5: =IF(ISNUMBER($AL5),IF(IFERROR(INDEX('Level Engine'!$NJ$9:$NJ$55,MATCH($AL5,'Level Engine'!$AA$9:$AA$55,0)),0)=1,1,0),0)
A6: =IF(AND(ISNUMBER($AM6),$AM6<0,ISNUMBER($AO6),$AO$1>0),REPT("█",ROUND($AO6/$AO$1*26,0)),"") | B6: =TEXT(IF(IF('Level Engine'!$GJ$4=1,$AL6='Level Engine'!$GJ$3,AND($AL6-$AM$2>-2.5,$AL6-$AM$2<=2.5)),$AM$2,$AL6),"0")&IF($AL6=$AN$1," ★","")&IF($AL6=$AN$2," ★","")&IF($AL6=$AN$3," ◆","")&IF(AND(ISNUMBER($AN$4),$AL6=$AN$4)," Ⓕ","")&IF(OR(AND(ISNUMBER('Level Engine'!$BG$87),$AL6='Level Engine'!$BG$87),AND(ISNUMBER('Level Engine'!$BG$105),$AL6='Level Engine'!$BG$105))," ζ","")&IF(AND(ISNUMBER($AN$35),$AL6=$AN$35)," ⓏⒼ","")&IF(OR($AL6='Level Engine'!$CP$4,$AL6='Level Engine'!$CP$5,$AL6='Level Engine'!$CP$6,$AL6='Level Engine'!$CP$7)," ☄","")&IF(OR($AL6=$AN$5,$AL6=$AN$8)," ║1","")&IF(OR($AL6=$AN$6,$AL6=$AN$10)," ║2","")&IF(OR($AL6=$AN$7,$AL6=$AN$11)," ║3","")&IF(OR($AL6=$AN$13,$AL6=$AN$16)," ▣1","")&IF(OR($AL6=$AN$14,$AL6=$AN$17)," ▣2","")&IF(OR($AL6=$AN$15,$AL6=$AN$18)," ▣3","")&IF(AND(NOT(OR(AND(ISNUMBER(SEARCH("chop edge",$E$45)),IFERROR(ABS($AL6-'King Node Model'!$AL$42)<=5,FALSE),NOT(ISNUMBER(SEARCH("UNSAFE",$L$45)))),AND(ISNUMBER(SEARCH("chop edge",$E$46)),IFERROR(ABS($AL6-'King Node Model'!$AL$43)<=5,FALSE),NOT(ISNUMBER(SEARCH("UNSAFE",$L$46)))),AND(ISNUMBER(SEARCH("chop edge",$E$52)),IFERROR(ABS($AL6-'King Node Model'!$AL$49)<=5,FALSE),NOT(ISNUMBER(SEARCH("UNSAFE",$L$52)))),AND(ISNUMBER(SEARCH("chop edge",$E$53)),IFERROR(ABS($AL6-'King Node Model'!$AL$50)<=5,FALSE),NOT(ISNUMBER(SEARCH("UNSAFE",$L$53)))))),OR(AND(IFERROR(INDEX('Level Engine'!$IB$9:$IB$55,MATCH('King Node Model'!$AL$49,'Level Engine'!$AA$9:$AA$55,0)),0)<>1,$AL6=IFERROR(INDEX('Level Engine'!$AU$9:$AU$55,MATCH('King Node Model'!$AL$49,'Level Engine'!$AA$9:$AA$55,0)),""),IFERROR(INDEX('Level Engine'!$AU$9:$AU$55,MATCH('King Node Model'!$AL$49,'Level Engine'!$AA$9:$AA$55,0)),"")<>IFERROR(INDEX('Level Engine'!$AT$9:$AT$55,MATCH('King Node Model'!$AL$49,'Level Engine'!$AA$9:$AA$55,0)),"")),AND(IFERROR(INDEX('Level Engine'!$IB$9:$IB$55,MATCH('King Node Model'!$AL$50,'Level Engine'!$AA$9:$AA$55,0)),0)<>1,$AL6=IFERROR(INDEX('Level Engine'!$AU$9:$AU$55,MATCH('King Node Model'!$AL$50,'Level Engine'!$AA$9:$AA$55,0)),""),IFERROR(INDEX('Level Engine'!$AU$9:$AU$55,MATCH('King Node Model'!$AL$50,'Level Engine'!$AA$9:$AA$55,0)),"")<>IFERROR(INDEX('Level Engine'!$AT$9:$AT$55,MATCH('King Node Model'!$AL$50,'Level Engine'!$AA$9:$AA$55,0)),"")))),IF(OR('King Node Model'!$A$8="Neg",N('Level Engine'!$BG$72)=1),""," ⒷⒽ"),"")&IF(AND(NOT(OR(AND(ISNUMBER(SEARCH("chop edge",$E$45)),IFERROR(ABS($AL6-'King Node Model'!$AL$42)<=5,FALSE),NOT(ISNUMBER(SEARCH("UNSAFE",$L$45)))),AND(ISNUMBER(SEARCH("chop edge",$E$46)),IFERROR(ABS($AL6-'King Node Model'!$AL$43)<=5,FALSE),NOT(ISNUMBER(SEARCH("UNSAFE",$L$46)))),AND(ISNUMBER(SEARCH("chop edge",$E$52)),IFERROR(ABS($AL6-'King Node Model'!$AL$49)<=5,FALSE),NOT(ISNUMBER(SEARCH("UNSAFE",$L$52)))),AND(ISNUMBER(SEARCH("chop edge",$E$53)),IFERROR(ABS($AL6-'King Node Model'!$AL$50)<=5,FALSE),NOT(ISNUMBER(SEARCH("UNSAFE",$L$53)))))),OR(AND(IFERROR(INDEX('Level Engine'!$IB$9:$IB$55,MATCH('King Node Model'!$AL$42,'Level Engine'!$AA$9:$AA$55,0)),0)<>1,$AL6=IFERROR(INDEX('Level Engine'!$AT$9:$AT$55,MATCH('King Node Model'!$AL$42,'Level Engine'!$AA$9:$AA$55,0)),""),IFERROR(INDEX('Level Engine'!$AT$9:$AT$55,MATCH('King Node Model'!$AL$42,'Level Engine'!$AA$9:$AA$55,0)),"")<>IFERROR(INDEX('Level Engine'!$AU$9:$AU$55,MATCH('King Node Model'!$AL$42,'Level Engine'!$AA$9:$AA$55,0)),"")),AND(IFERROR(INDEX('Level Engine'!$IB$9:$IB$55,MATCH('King Node Model'!$AL$43,'Level Engine'!$AA$9:$AA$55,0)),0)<>1,$AL6=IFERROR(INDEX('Level Engine'!$AT$9:$AT$55,MATCH('King Node Model'!$AL$43,'Level Engine'!$AA$9:$AA$55,0)),""),IFERROR(INDEX('Level Engine'!$AT$9:$AT$55,MATCH('King Node Model'!$AL$43,'Level Engine'!$AA$9:$AA$55,0)),"")<>IFERROR(INDEX('Level Engine'!$AU$9:$AU$55,MATCH('King Node Model'!$AL$43,'Level Engine'!$AA$9:$AA$55,0)),"")))),IF(OR('King Node Model'!$A$8="Neg",N('Level Engine'!$BG$72)=1),""," ⒷⓁ"),"")&IF(OR(AND($AL6>='King Node Model'!$AM$17,$AL6<='King Node Model'!$AN$17,$AP$45="RASP"),AND($AL6>='King Node Model'!$AM$18,$AL6<='King Node Model'!$AN$18,$AP$46="RASP"),AND($AL6>='King Node Model'!$AM$19,$AL6<='King Node Model'!$AN$19,$AP$47="RASP"),AND($AL6>='King Node Model'!$AM$20,$AL6<='King Node Model'!$AN$20,$AP$52="RASP"),AND($AL6>='King Node Model'!$AM$21,$AL6<='King Node Model'!$AN$21,$AP$53="RASP"),AND($AL6>='King Node Model'!$AM$22,$AL6<='King Node Model'!$AN$22,$AP$54="RASP")),"","")&IF(IF('Level Engine'!$GJ$4=1,$AL6='Level Engine'!$GJ$3,AND($AL6-$AM$2>-2.5,$AL6-$AM$2<=2.5))," ◄","")&IF(IFERROR(INDEX('Level Engine'!$GV$9:$GV$55,MATCH($AL6,'Level Engine'!$AA$9:$AA$55,0)),0)=1," Ⓥ"&IF(IFERROR(INDEX('Level Engine'!$ET$9:$ET$55,MATCH($AL6,'Level Engine'!$AA$9:$AA$55,0)),0)=1,"+",""),"")&IF(OR(AND($AL6=$AN$38,IFERROR(INDEX('Level Engine'!$AN$9:$AN$55,MATCH($AL6,'Level Engine'!$AA$9:$AA$55,0)),0)<>1),$AL6=$AN$39)," ⊙","")&IF(AND(OR('King Node Model'!$A$8="Neg",N('Level Engine'!$BG$72)=1),ABS(MIN($AM$3:$AM$64))>MAX($AM$3:$AM$64),$AN$2<$AM$2,$AL6<$AM$2,ABS($AL6-$AN$2)<=5,IFERROR(VALUE(MID('King Node Model'!$K$26,FIND(":",'King Node Model'!$K$26)-2,2)),0)>=19,IFERROR(INDEX('Level Engine'!$EJ$9:$EJ$55,MATCH($AL6,'Level Engine'!$AA$9:$AA$55,0)),0)=0,$AN$3>$AM$2)," ⟲rev","")&IF($AL6='King Node Model'!$F$24," ⟂","")&$DJ6&IF(IFERROR(INDEX('Level Engine'!$EN$9:$EN$55,MATCH($AL6,'Level Engine'!$AA$9:$AA$55,0)),0)=1," Ⓟ"&IF(AND(OR('King Node Model'!$A$8="Neg",N('Level Engine'!$BG$72)=1),IFERROR(INDEX('Level Engine'!$AN$9:$AN$55,MATCH($AL6,'Level Engine'!$AA$9:$AA$55,0)),0)<>1)," NO-REV",""),"")&IF(AND(ISNUMBER($AL6),OR(AND(ISNUMBER(SEARCH("chop edge",$E$45)),$AL6='King Node Model'!$AL$42),AND(ISNUMBER(SEARCH("chop edge",$E$46)),$AL6='King Node Model'!$AL$43),AND(ISNUMBER(SEARCH("chop edge",$E$52)),$AL6='King Node Model'!$AL$49),AND(ISNUMBER(SEARCH("chop edge",$E$53)),$AL6='King Node Model'!$AL$50)))," ⒸⒺ","")&IF(AND('Level Engine'!$GJ$4=1,OR($AL6='Level Engine'!$GJ$1,$AL6='Level Engine'!$GJ$2)),"","")&IF(ABS(N(IFERROR(INDEX('Level Engine'!$AE$9:$AE$55,MATCH($AL6,'Level Engine'!$AA$9:$AA$55,0)),0)))>='Level Engine'!$BG$85,IF(N(IFERROR(INDEX('Level Engine'!$AE$9:$AE$55,MATCH($AL6,'Level Engine'!$AA$9:$AA$55,0)),0))>0," Δ+"," Δ−"),"")&IFERROR(IF(AND(ISNUMBER(MATCH($AL6,'Level Engine'!$AA$9:$AA$55,0)),ABS(N(IFERROR(INDEX('Level Engine'!$AE$9:$AE$55,MATCH($AL6,'Level Engine'!$AA$9:$AA$55,0)),0)))<'Level Engine'!$BG$85,ABS(N(IFERROR(INDEX('Level Engine'!$AE$9:$AE$55,MATCH($AL6,'Level Engine'!$AA$9:$AA$55,0)),0)))<=ABS(N(IFERROR(INDEX('Level Engine'!$AE$9:$AE$55,MATCH($AL6+5,'Level Engine'!$AA$9:$AA$55,0)),0))),ABS(N(IFERROR(INDEX('Level Engine'!$AE$9:$AE$55,MATCH($AL6,'Level Engine'!$AA$9:$AA$55,0)),0)))<=ABS(N(IFERROR(INDEX('Level Engine'!$AE$9:$AE$55,MATCH($AL6-5,'Level Engine'!$AA$9:$AA$55,0)),0))),OR(AND(ABS(N(IFERROR(INDEX('Level Engine'!$AE$9:$AE$55,MATCH($AL6+5,'Level Engine'!$AA$9:$AA$55,0)),0)))>='Level Engine'!$BG$85,ABS(N(IFERROR(INDEX('Level Engine'!$AE$9:$AE$55,MATCH($AL6,'Level Engine'!$AA$9:$AA$55,0)),0)))<='Level Engine'!$BG$88*ABS(N(IFERROR(INDEX('Level Engine'!$AE$9:$AE$55,MATCH($AL6+5,'Level Engine'!$AA$9:$AA$55,0)),0)))),AND(ABS(N(IFERROR(INDEX('Level Engine'!$AE$9:$AE$55,MATCH($AL6-5,'Level Engine'!$AA$9:$AA$55,0)),0)))>='Level Engine'!$BG$85,ABS(N(IFERROR(INDEX('Level Engine'!$AE$9:$AE$55,MATCH($AL6,'Level Engine'!$AA$9:$AA$55,0)),0)))<='Level Engine'!$BG$88*ABS(N(IFERROR(INDEX('Level Engine'!$AE$9:$AE$55,MATCH($AL6-5,'Level Engine'!$AA$9:$AA$55,0)),0)))))),IF(AND('King Node Model'!$A$8="Pos",N('Level Engine'!$BG$72)<>1),""," ∅"),""),"")&IF(IFERROR(INDEX('Level Engine'!$JD$9:$JD$55,MATCH($AL6,'Level Engine'!$AA$9:$AA$55,0)),"")="P"," P-OI",IF(IFERROR(INDEX('Level Engine'!$JD$9:$JD$55,MATCH($AL6,'Level Engine'!$AA$9:$AA$55,0)),"")="C"," C-OI","")) -> 7870 | C6: =IF(AND(ISNUMBER($AM6),$AM6>0,ISNUMBER($AO6),$AO$1>0),REPT("█",ROUND($AO6/$AO$1*26,0)),"") -> █ | D6: =IF(NOT(ISNUMBER($AL6)),"",IF(IFERROR(INDEX('Level Engine'!$FS$9:$FS$55,MATCH($AL6,'Level Engine'!$AA$9:$AA$55,0)),0)=1,"⊙","")) | E6: =IF('King Node Model'!S52<>"",'King Node Model'!S52,IF('King Node Model'!S38<>"",'King Node Model'!S38,"")) -> ⚠ DEX peaks in the middle at 7800! The market is engineered to chop! | Q6: =IF(NOT(ISNUMBER('Level Engine'!$E$3)),"Open Vol Response —","Open Vol Response "&TEXT('Level Engine'!$E$3,"0.00")&" · "&IF('Level Engine'!$E$3<0.8,"Slow Trend",IF('Level Engine'!$E$3<0.85,"Chop",IF('Level Engine'!$E$3<0.95,"Ordinary","Expansion")))) -> Open Vol Response 0.89 · Ordinary | AL6: ='King Node Model'!A32 -> 7870 | AM6: ='King Node Model'!C32 -> 84051 | AN6: ='King Node Model'!T26 -> 7805 | AO6: ='King Node Model'!B32 -> 86951 | AY6: =IF(AND($B$2="Hide unsafe",$BB6=1),0,IF(AND(OR(AND(AND(ISNUMBER($AL6),OR(AND($AL6>=$AQ$22,$AL6<=$AR$22,$AS$22=1),$AL6=$AQ$22,$AL6=$AR$22,$AL6=$AQ$23,$AL6=$AR$23,$AL6=$AQ$24,$AL6=$AR$24),NOT(OR($AL6=$AN$5,$AL6=$AN$6,$AL6=$AN$7,$AL6=$AN$8,$AL6=$AN$10,$AL6=$AN$11))),NOT(OR(AND('King Node Model'!$P$13="Up",OR($AL6=$AQ$22,$AL6=$AQ$23,$AL6=$AQ$24,$AL6='King Node Model'!$AM$20,$AL6='King Node Model'!$AM$21,$AL6='King Node Model'!$AM$22),OR(AND('King Node Model'!$B$23-$AL6>=0,'King Node Model'!$B$23-$AL6<=5),AND('King Node Model'!$C$23-$AL6>=0,'King Node Model'!$C$23-$AL6<=5))),AND('King Node Model'!$P$13="Down",OR($AL6=$AR$22,$AL6=$AR$23,$AL6=$AR$24,$AL6='King Node Model'!$AN$20,$AL6='King Node Model'!$AN$21,$AL6='King Node Model'!$AN$22),OR(AND($AL6-'King Node Model'!$B$23>=0,$AL6-'King Node Model'!$B$23<=5),AND($AL6-'King Node Model'!$C$24>=0,$AL6-'King Node Model'!$C$24<=5)))))),AND(AND(ISNUMBER($AL6),OR(AND($AL6>=$AQ$22,$AL6<=$AR$22,$AS$22=1),$AL6=$AQ$22,$AL6=$AR$22,$AL6=$AQ$23,$AL6=$AR$23,$AL6=$AQ$24,$AL6=$AR$24,$AL6='King Node Model'!$AL$42,$AL6='King Node Model'!$AL$43),OR($AL6=$AN$5,$AL6=$AN$6,$AL6=$AN$7,$AL6=$AN$8,$AL6=$AN$10,$AL6=$AN$11)),NOT(OR(AND('King Node Model'!$P$13="Up",OR($AL6=$AQ$22,$AL6=$AQ$23,$AL6=$AQ$24,$AL6='King Node Model'!$AM$20,$AL6='King Node Model'!$AM$21,$AL6='King Node Model'!$AM$22),OR(AND('King Node Model'!$B$23-$AL6>=0,'King Node Model'!$B$23-$AL6<=5),AND('King Node Model'!$C$23-$AL6>=0,'King Node Model'!$C$23-$AL6<=5))),AND('King Node Model'!$P$13="Down",OR($AL6=$AR$22,$AL6=$AR$23,$AL6=$AR$24,$AL6='King Node Model'!$AN$20,$AL6='King Node Model'!$AN$21,$AL6='King Node Model'!$AN$22),OR(AND($AL6-'King Node Model'!$B$23>=0,$AL6-'King Node Model'!$B$23<=5),AND($AL6-'King Node Model'!$C$24>=0,$AL6-'King Node Model'!$C$24<=5)))))),AND(AND(ISNUMBER($AL6),OR(AND($AL6>='King Node Model'!$AM$20,$AL6<='King Node Model'!$AN$20,$AS$23=1),$AL6='King Node Model'!$AM$20,$AL6='King Node Model'!$AN$20,$AL6='King Node Model'!$AM$21,$AL6='King Node Model'!$AN$21,$AL6='King Node Model'!$AM$22,$AL6='King Node Model'!$AN$22),NOT(OR($AL6=$AN$5,$AL6=$AN$6,$AL6=$AN$7,$AL6=$AN$8,$AL6=$AN$10,$AL6=$AN$11))),NOT(AND(ISNUMBER('King Node Model'!$F$24),$AL6='King Node Model'!$F$24,IFERROR(INDEX('Level Engine'!$JN$9:$JN$55,MATCH($AL6,'Level Engine'!$AA$9:$AA$55,0)),0)<>1))),AND(AND(ISNUMBER($AL6),OR(AND($AL6>='King Node Model'!$AM$20,$AL6<='King Node Model'!$AN$20,$AS$23=1),$AL6='King Node Model'!$AM$20,$AL6='King Node Model'!$AN$20,$AL6='King Node Model'!$AM$21,$AL6='King Node Model'!$AN$21,$AL6='King Node Model'!$AM$22,$AL6='King Node Model'!$AN$22,$AL6='King Node Model'!$AL$49,$AL6='King Node Model'!$AL$50),OR($AL6=$AN$5,$AL6=$AN$6,$AL6=$AN$7,$AL6=$AN$8,$AL6=$AN$10,$AL6=$AN$11)),NOT(OR(AND('King Node Model'!$P$13="Up",OR($AL6=$AQ$22,$AL6=$AQ$23,$AL6=$AQ$24,$AL6='King Node Model'!$AM$20,$AL6='King Node Model'!$AM$21,$AL6='King Node Model'!$AM$22),OR(AND('King Node Model'!$B$23-$AL6>=0,'King Node Model'!$B$23-$AL6<=5),AND('King Node Model'!$C$23-$AL6>=0,'King Node Model'!$C$23-$AL6<=5))),AND('King Node Model'!$P$13="Down",OR($AL6=$AR$22,$AL6=$AR$23,$AL6=$AR$24,$AL6='King Node Model'!$AN$20,$AL6='King Node Model'!$AN$21,$AL6='King Node Model'!$AN$22),OR(AND($AL6-'King Node Model'!$B$23>=0,$AL6-'King Node Model'!$B$23<=5),AND($AL6-'King Node Model'!$C$24>=0,$AL6-'King Node Model'!$C$24<=5))))))),OR(COUNTIF('Level Engine'!$W$9:$W$14,$AL6)>0,COUNTIF('Level Engine'!$W$18:$W$23,$AL6)>0)),1,0)) -> 0 | AZ6: =IF($B$2="Hide unsafe",0,$BB6) -> 0 | BB6: =IF(OR(AND($AL6='King Node Model'!$AL$42,$AP$45<>"RASP"),AND($AL6='King Node Model'!$AL$43,$AP$46<>"RASP"),AND($AL6='King Node Model'!$AL$49,$AP$52<>"RASP"),AND($AL6='King Node Model'!$AL$50,$AP$53<>"RASP"),AND($AL6='King Node Model'!$AL$44,$AP$47<>"RASP"),AND($AL6='King Node Model'!$AL$51,$AP$54<>"RASP")),0,IF(AND(AND(ISNUMBER($AL6),OR(AND($AL6>=$AQ$22,$AL6<=$AR$22,$AP$45="RASP"),AND($AL6>=$AQ$23,$AL6<=$AR$23,$AP$46="RASP"),AND($AL6>=$AQ$24,$AL6<=$AR$24,$AP$47="RASP"),AND($AL6>='King Node Model'!$AM$20,$AL6<='King Node Model'!$AN$20,$AP$52="RASP",NOT($L$52=$AW$52)),AND($AL6='King Node Model'!$B$23,$AP$52="RASP",$L$52=$AW$52),AND($AL6>='King Node Model'!$AM$21,$AL6<='King Node Model'!$AN$21,$AP$53="RASP",NOT($L$53=$AW$53)),AND($AL6='King Node Model'!$B$23,$AP$53="RASP",$L$53=$AW$53),AND($AL6>='King Node Model'!$AM$22,$AL6<='King Node Model'!$AN$22,$AP$54="RASP"),AND($AL6>=IFERROR(INDEX('Level Engine'!$AT$9:$AT$55,MATCH('King Node Model'!$AL$42,'Level Engine'!$AA$9:$AA$55,0)),""),$AL6<=IFERROR(INDEX('Level Engine'!$AU$9:$AU$55,MATCH('King Node Model'!$AL$42,'Level Engine'!$AA$9:$AA$55,0)),""),$AP$45="RASP"),AND($AL6>=IFERROR(INDEX('Level Engine'!$AT$9:$AT$55,MATCH('King Node Model'!$AL$43,'Level Engine'!$AA$9:$AA$55,0)),""),$AL6<=IFERROR(INDEX('Level Engine'!$AU$9:$AU$55,MATCH('King Node Model'!$AL$43,'Level Engine'!$AA$9:$AA$55,0)),""),$AP$46="RASP"),AND($AL6>=IFERROR(INDEX('Level Engine'!$AT$9:$AT$55,MATCH('King Node Model'!$AL$44,'Level Engine'!$AA$9:$AA$55,0)),""),$AL6<=IFERROR(INDEX('Level Engine'!$AU$9:$AU$55,MATCH('King Node Model'!$AL$44,'Level Engine'!$AA$9:$AA$55,0)),""),$AP$47="RASP"),AND($AL6>=IFERROR(INDEX('Level Engine'!$AT$9:$AT$55,MATCH('King Node Model'!$AL$49,'Level Engine'!$AA$9:$AA$55,0)),""),$AL6<=IFERROR(INDEX('Level Engine'!$AU$9:$AU$55,MATCH('King Node Model'!$AL$49,'Level Engine'!$AA$9:$AA$55,0)),""),$AP$52="RASP",NOT($L$52=$AW$52)),AND($AL6>=IFERROR(INDEX('Level Engine'!$AT$9:$AT$55,MATCH('King Node Model'!$AL$50,'Level Engine'!$AA$9:$AA$55,0)),""),$AL6<=IFERROR(INDEX('Level Engine'!$AU$9:$AU$55,MATCH('King Node Model'!$AL$50,'Level Engine'!$AA$9:$AA$55,0)),""),$AP$53="RASP",NOT($L$53=$AW$53)),AND($AL6>=IFERROR(INDEX('Level Engine'!$AT$9:$AT$55,MATCH('King Node Model'!$AL$51,'Level Engine'!$AA$9:$AA$55,0)),""),$AL6<=IFERROR(INDEX('Level Engine'!$AU$9:$AU$55,MATCH('King Node Model'!$AL$51,'Level Engine'!$AA$9:$AA$55,0)),""),$AP$54="RASP"))),NOT(AND(ISNUMBER('King Node Model'!$F$24),$AL6='King Node Model'!$F$24,IFERROR(INDEX('Level Engine'!$JN$9:$JN$55,MATCH($AL6,'Level Engine'!$AA$9:$AA$55,0)),0)<>1,$AL6<>'King Node Model'!$AL$42,$AL6<>'King Node Model'!$AL$43,$AL6<>'King Node Model'!$AL$44,$AL6<>'King Node Model'!$AL$49,$AL6<>'King Node Model'!$AL$50,$AL6<>'King Node Model'!$AL$51))),1,0)) -> 0 | CO6: =IF(NOT(ISNUMBER($AL6)),"",IF(NOT(ISNUMBER(IFERROR(INDEX('Level Engine'!$FT$9:$FT$55,MATCH($AL6,'Level Engine'!$AA$9:$AA$55,0)),""))),"",IF(IFERROR(INDEX('Level Engine'!$FT$9:$FT$55,MATCH($AL6,'Level Engine'!$AA$9:$AA$55,0)),"")<0,0,2)+IF(ABS(IFERROR(INDEX('Level Engine'!$FT$9:$FT$55,MATCH($AL6,'Level Engine'!$AA$9:$AA$55,0)),""))>='Level Engine'!$FT$2,2,1))) -> 4 | DJ6: =IF(ISNUMBER($AL6),IF($AL6='Level Engine'!$BG$122," ⫪","")&IF($AL6='Level Engine'!$BG$118," S↑"&IFERROR(INDEX('Level Engine'!$MV$9:$MV$55,MATCH($AL6,'Level Engine'!$AA$9:$AA$55,0)),""),"")&IF($AL6='Level Engine'!$BG$119," S↓"&IFERROR(INDEX('Level Engine'!$MV$9:$MV$55,MATCH($AL6,'Level Engine'!$AA$9:$AA$55,0)),""),"")&IF($AL6='Level Engine'!$BG$120," D↑","")&IF($AL6='Level Engine'!$BG$121," D↓","")&IFERROR(INDEX('Level Engine'!$LG$9:$LG$55,MATCH($AL6,'Level Engine'!$AA$9:$AA$55,0)),"")&IF(IFERROR(INDEX('Level Engine'!$MA$9:$MA$55,MATCH($AL6,'Level Engine'!$AA$9:$AA$55,0)),0)=1," SAND","")&IF(IFERROR(INDEX('Level Engine'!$LM$9:$LM$55,MATCH($AL6,'Level Engine'!$AA$9:$AA$55,0)),0)>0," TP","")&IFERROR(" r"&MATCH($AL6,'Level Engine'!$W$9:$W$14,0),IFERROR(" s"&MATCH($AL6,'Level Engine'!$W$18:$W$23,0),""))&IF($AL6='Level Engine'!$BG$165," ◇","")&IF(N($DZ6)=1,IF($AL6>'Level Engine'!$BG$165," ⚠ DOM↓"," ⚠ DOM↑")&'Level Engine'!$BG$165,""),"") | DK6: =IF(AND(ISNUMBER($AL6),OR($AL6='King Node Model'!$AL$42,$AL6='King Node Model'!$AL$43,$AL6='King Node Model'!$AL$44)),IFERROR(MATCH($AL6,'Level Engine'!$W$9:$W$14,0),""),"") | DL6: =IF(AND(ISNUMBER($AL6),OR($AL6='King Node Model'!$AL$49,$AL6='King Node Model'!$AL$50,$AL6='King Node Model'!$AL$51)),IFERROR(MATCH($AL6,'Level Engine'!$W$18:$W$23,0),""),"") | DM6: =IF(AND(ISNUMBER($AL6),IFERROR(INDEX('Level Engine'!$LC$9:$LC$55,MATCH($AL6,'Level Engine'!$AA$9:$AA$55,0)),0)=1,OR($AL6=$AN$3,IFERROR(INDEX('Level Engine'!$LB$9:$LB$55,MATCH($AL6,'Level Engine'!$AA$9:$AA$55,0)),0)=1)),1,0) -> 0 | DZ6: =IF(ISNUMBER($AL6),IF(IFERROR(INDEX('Level Engine'!$NJ$9:$NJ$55,MATCH($AL6,'Level Engine'!$AA$9:$AA$55,0)),0)=1,1,0),0)
A7: =IF(AND(ISNUMBER($AM7),$AM7<0,ISNUMBER($AO7),$AO$1>0),REPT("█",ROUND($AO7/$AO$1*26,0)),"") | B7: =TEXT(IF(IF('Level Engine'!$GJ$4=1,$AL7='Level Engine'!$GJ$3,AND($AL7-$AM$2>-2.5,$AL7-$AM$2<=2.5)),$AM$2,$AL7),"0")&IF($AL7=$AN$1," ★","")&IF($AL7=$AN$2," ★","")&IF($AL7=$AN$3," ◆","")&IF(AND(ISNUMBER($AN$4),$AL7=$AN$4)," Ⓕ","")&IF(OR(AND(ISNUMBER('Level Engine'!$BG$87),$AL7='Level Engine'!$BG$87),AND(ISNUMBER('Level Engine'!$BG$105),$AL7='Level Engine'!$BG$105))," ζ","")&IF(AND(ISNUMBER($AN$35),$AL7=$AN$35)," ⓏⒼ","")&IF(OR($AL7='Level Engine'!$CP$4,$AL7='Level Engine'!$CP$5,$AL7='Level Engine'!$CP$6,$AL7='Level Engine'!$CP$7)," ☄","")&IF(OR($AL7=$AN$5,$AL7=$AN$8)," ║1","")&IF(OR($AL7=$AN$6,$AL7=$AN$10)," ║2","")&IF(OR($AL7=$AN$7,$AL7=$AN$11)," ║3","")&IF(OR($AL7=$AN$13,$AL7=$AN$16)," ▣1","")&IF(OR($AL7=$AN$14,$AL7=$AN$17)," ▣2","")&IF(OR($AL7=$AN$15,$AL7=$AN$18)," ▣3","")&IF(AND(NOT(OR(AND(ISNUMBER(SEARCH("chop edge",$E$45)),IFERROR(ABS($AL7-'King Node Model'!$AL$42)<=5,FALSE),NOT(ISNUMBER(SEARCH("UNSAFE",$L$45)))),AND(ISNUMBER(SEARCH("chop edge",$E$46)),IFERROR(ABS($AL7-'King Node Model'!$AL$43)<=5,FALSE),NOT(ISNUMBER(SEARCH("UNSAFE",$L$46)))),AND(ISNUMBER(SEARCH("chop edge",$E$52)),IFERROR(ABS($AL7-'King Node Model'!$AL$49)<=5,FALSE),NOT(ISNUMBER(SEARCH("UNSAFE",$L$52)))),AND(ISNUMBER(SEARCH("chop edge",$E$53)),IFERROR(ABS($AL7-'King Node Model'!$AL$50)<=5,FALSE),NOT(ISNUMBER(SEARCH("UNSAFE",$L$53)))))),OR(AND(IFERROR(INDEX('Level Engine'!$IB$9:$IB$55,MATCH('King Node Model'!$AL$49,'Level Engine'!$AA$9:$AA$55,0)),0)<>1,$AL7=IFERROR(INDEX('Level Engine'!$AU$9:$AU$55,MATCH('King Node Model'!$AL$49,'Level Engine'!$AA$9:$AA$55,0)),""),IFERROR(INDEX('Level Engine'!$AU$9:$AU$55,MATCH('King Node Model'!$AL$49,'Level Engine'!$AA$9:$AA$55,0)),"")<>IFERROR(INDEX('Level Engine'!$AT$9:$AT$55,MATCH('King Node Model'!$AL$49,'Level Engine'!$AA$9:$AA$55,0)),"")),AND(IFERROR(INDEX('Level Engine'!$IB$9:$IB$55,MATCH('King Node Model'!$AL$50,'Level Engine'!$AA$9:$AA$55,0)),0)<>1,$AL7=IFERROR(INDEX('Level Engine'!$AU$9:$AU$55,MATCH('King Node Model'!$AL$50,'Level Engine'!$AA$9:$AA$55,0)),""),IFERROR(INDEX('Level Engine'!$AU$9:$AU$55,MATCH('King Node Model'!$AL$50,'Level Engine'!$AA$9:$AA$55,0)),"")<>IFERROR(INDEX('Level Engine'!$AT$9:$AT$55,MATCH('King Node Model'!$AL$50,'Level Engine'!$AA$9:$AA$55,0)),"")))),IF(OR('King Node Model'!$A$8="Neg",N('Level Engine'!$BG$72)=1),""," ⒷⒽ"),"")&IF(AND(NOT(OR(AND(ISNUMBER(SEARCH("chop edge",$E$45)),IFERROR(ABS($AL7-'King Node Model'!$AL$42)<=5,FALSE),NOT(ISNUMBER(SEARCH("UNSAFE",$L$45)))),AND(ISNUMBER(SEARCH("chop edge",$E$46)),IFERROR(ABS($AL7-'King Node Model'!$AL$43)<=5,FALSE),NOT(ISNUMBER(SEARCH("UNSAFE",$L$46)))),AND(ISNUMBER(SEARCH("chop edge",$E$52)),IFERROR(ABS($AL7-'King Node Model'!$AL$49)<=5,FALSE),NOT(ISNUMBER(SEARCH("UNSAFE",$L$52)))),AND(ISNUMBER(SEARCH("chop edge",$E$53)),IFERROR(ABS($AL7-'King Node Model'!$AL$50)<=5,FALSE),NOT(ISNUMBER(SEARCH("UNSAFE",$L$53)))))),OR(AND(IFERROR(INDEX('Level Engine'!$IB$9:$IB$55,MATCH('King Node Model'!$AL$42,'Level Engine'!$AA$9:$AA$55,0)),0)<>1,$AL7=IFERROR(INDEX('Level Engine'!$AT$9:$AT$55,MATCH('King Node Model'!$AL$42,'Level Engine'!$AA$9:$AA$55,0)),""),IFERROR(INDEX('Level Engine'!$AT$9:$AT$55,MATCH('King Node Model'!$AL$42,'Level Engine'!$AA$9:$AA$55,0)),"")<>IFERROR(INDEX('Level Engine'!$AU$9:$AU$55,MATCH('King Node Model'!$AL$42,'Level Engine'!$AA$9:$AA$55,0)),"")),AND(IFERROR(INDEX('Level Engine'!$IB$9:$IB$55,MATCH('King Node Model'!$AL$43,'Level Engine'!$AA$9:$AA$55,0)),0)<>1,$AL7=IFERROR(INDEX('Level Engine'!$AT$9:$AT$55,MATCH('King Node Model'!$AL$43,'Level Engine'!$AA$9:$AA$55,0)),""),IFERROR(INDEX('Level Engine'!$AT$9:$AT$55,MATCH('King Node Model'!$AL$43,'Level Engine'!$AA$9:$AA$55,0)),"")<>IFERROR(INDEX('Level Engine'!$AU$9:$AU$55,MATCH('King Node Model'!$AL$43,'Level Engine'!$AA$9:$AA$55,0)),"")))),IF(OR('King Node Model'!$A$8="Neg",N('Level Engine'!$BG$72)=1),""," ⒷⓁ"),"")&IF(OR(AND($AL7>='King Node Model'!$AM$17,$AL7<='King Node Model'!$AN$17,$AP$45="RASP"),AND($AL7>='King Node Model'!$AM$18,$AL7<='King Node Model'!$AN$18,$AP$46="RASP"),AND($AL7>='King Node Model'!$AM$19,$AL7<='King Node Model'!$AN$19,$AP$47="RASP"),AND($AL7>='King Node Model'!$AM$20,$AL7<='King Node Model'!$AN$20,$AP$52="RASP"),AND($AL7>='King Node Model'!$AM$21,$AL7<='King Node Model'!$AN$21,$AP$53="RASP"),AND($AL7>='King Node Model'!$AM$22,$AL7<='King Node Model'!$AN$22,$AP$54="RASP")),"","")&IF(IF('Level Engine'!$GJ$4=1,$AL7='Level Engine'!$GJ$3,AND($AL7-$AM$2>-2.5,$AL7-$AM$2<=2.5))," ◄","")&IF(IFERROR(INDEX('Level Engine'!$GV$9:$GV$55,MATCH($AL7,'Level Engine'!$AA$9:$AA$55,0)),0)=1," Ⓥ"&IF(IFERROR(INDEX('Level Engine'!$ET$9:$ET$55,MATCH($AL7,'Level Engine'!$AA$9:$AA$55,0)),0)=1,"+",""),"")&IF(OR(AND($AL7=$AN$38,IFERROR(INDEX('Level Engine'!$AN$9:$AN$55,MATCH($AL7,'Level Engine'!$AA$9:$AA$55,0)),0)<>1),$AL7=$AN$39)," ⊙","")&IF(AND(OR('King Node Model'!$A$8="Neg",N('Level Engine'!$BG$72)=1),ABS(MIN($AM$3:$AM$64))>MAX($AM$3:$AM$64),$AN$2<$AM$2,$AL7<$AM$2,ABS($AL7-$AN$2)<=5,IFERROR(VALUE(MID('King Node Model'!$K$26,FIND(":",'King Node Model'!$K$26)-2,2)),0)>=19,IFERROR(INDEX('Level Engine'!$EJ$9:$EJ$55,MATCH($AL7,'Level Engine'!$AA$9:$AA$55,0)),0)=0,$AN$3>$AM$2)," ⟲rev","")&IF($AL7='King Node Model'!$F$24," ⟂","")&$DJ7&IF(IFERROR(INDEX('Level Engine'!$EN$9:$EN$55,MATCH($AL7,'Level Engine'!$AA$9:$AA$55,0)),0)=1," Ⓟ"&IF(AND(OR('King Node Model'!$A$8="Neg",N('Level Engine'!$BG$72)=1),IFERROR(INDEX('Level Engine'!$AN$9:$AN$55,MATCH($AL7,'Level Engine'!$AA$9:$AA$55,0)),0)<>1)," NO-REV",""),"")&IF(AND(ISNUMBER($AL7),OR(AND(ISNUMBER(SEARCH("chop edge",$E$45)),$AL7='King Node Model'!$AL$42),AND(ISNUMBER(SEARCH("chop edge",$E$46)),$AL7='King Node Model'!$AL$43),AND(ISNUMBER(SEARCH("chop edge",$E$52)),$AL7='King Node Model'!$AL$49),AND(ISNUMBER(SEARCH("chop edge",$E$53)),$AL7='King Node Model'!$AL$50)))," ⒸⒺ","")&IF(AND('Level Engine'!$GJ$4=1,OR($AL7='Level Engine'!$GJ$1,$AL7='Level Engine'!$GJ$2)),"","")&IF(ABS(N(IFERROR(INDEX('Level Engine'!$AE$9:$AE$55,MATCH($AL7,'Level Engine'!$AA$9:$AA$55,0)),0)))>='Level Engine'!$BG$85,IF(N(IFERROR(INDEX('Level Engine'!$AE$9:$AE$55,MATCH($AL7,'Level Engine'!$AA$9:$AA$55,0)),0))>0," Δ+"," Δ−"),"")&IFERROR(IF(AND(ISNUMBER(MATCH($AL7,'Level Engine'!$AA$9:$AA$55,0)),ABS(N(IFERROR(INDEX('Level Engine'!$AE$9:$AE$55,MATCH($AL7,'Level Engine'!$AA$9:$AA$55,0)),0)))<'Level Engine'!$BG$85,ABS(N(IFERROR(INDEX('Level Engine'!$AE$9:$AE$55,MATCH($AL7,'Level Engine'!$AA$9:$AA$55,0)),0)))<=ABS(N(IFERROR(INDEX('Level Engine'!$AE$9:$AE$55,MATCH($AL7+5,'Level Engine'!$AA$9:$AA$55,0)),0))),ABS(N(IFERROR(INDEX('Level Engine'!$AE$9:$AE$55,MATCH($AL7,'Level Engine'!$AA$9:$AA$55,0)),0)))<=ABS(N(IFERROR(INDEX('Level Engine'!$AE$9:$AE$55,MATCH($AL7-5,'Level Engine'!$AA$9:$AA$55,0)),0))),OR(AND(ABS(N(IFERROR(INDEX('Level Engine'!$AE$9:$AE$55,MATCH($AL7+5,'Level Engine'!$AA$9:$AA$55,0)),0)))>='Level Engine'!$BG$85,ABS(N(IFERROR(INDEX('Level Engine'!$AE$9:$AE$55,MATCH($AL7,'Level Engine'!$AA$9:$AA$55,0)),0)))<='Level Engine'!$BG$88*ABS(N(IFERROR(INDEX('Level Engine'!$AE$9:$AE$55,MATCH($AL7+5,'Level Engine'!$AA$9:$AA$55,0)),0)))),AND(ABS(N(IFERROR(INDEX('Level Engine'!$AE$9:$AE$55,MATCH($AL7-5,'Level Engine'!$AA$9:$AA$55,0)),0)))>='Level Engine'!$BG$85,ABS(N(IFERROR(INDEX('Level Engine'!$AE$9:$AE$55,MATCH($AL7,'Level Engine'!$AA$9:$AA$55,0)),0)))<='Level Engine'!$BG$88*ABS(N(IFERROR(INDEX('Level Engine'!$AE$9:$AE$55,MATCH($AL7-5,'Level Engine'!$AA$9:$AA$55,0)),0)))))),IF(AND('King Node Model'!$A$8="Pos",N('Level Engine'!$BG$72)<>1),""," ∅"),""),"")&IF(IFERROR(INDEX('Level Engine'!$JD$9:$JD$55,MATCH($AL7,'Level Engine'!$AA$9:$AA$55,0)),"")="P"," P-OI",IF(IFERROR(INDEX('Level Engine'!$JD$9:$JD$55,MATCH($AL7,'Level Engine'!$AA$9:$AA$55,0)),"")="C"," C-OI","")) -> 7865 | C7: =IF(AND(ISNUMBER($AM7),$AM7>0,ISNUMBER($AO7),$AO$1>0),REPT("█",ROUND($AO7/$AO$1*26,0)),"") -> █ | D7: =IF(NOT(ISNUMBER($AL7)),"",IF(IFERROR(INDEX('Level Engine'!$FS$9:$FS$55,MATCH($AL7,'Level Engine'!$AA$9:$AA$55,0)),0)=1,"⊙","")) | AL7: ='King Node Model'!A33 -> 7865 | AM7: ='King Node Model'!C33 -> 101554 | AN7: ='King Node Model'!T27 -> 7810 | AO7: ='King Node Model'!B33 -> 104698 | AY7: =IF(AND($B$2="Hide unsafe",$BB7=1),0,IF(AND(OR(AND(AND(ISNUMBER($AL7),OR(AND($AL7>=$AQ$22,$AL7<=$AR$22,$AS$22=1),$AL7=$AQ$22,$AL7=$AR$22,$AL7=$AQ$23,$AL7=$AR$23,$AL7=$AQ$24,$AL7=$AR$24),NOT(OR($AL7=$AN$5,$AL7=$AN$6,$AL7=$AN$7,$AL7=$AN$8,$AL7=$AN$10,$AL7=$AN$11))),NOT(OR(AND('King Node Model'!$P$13="Up",OR($AL7=$AQ$22,$AL7=$AQ$23,$AL7=$AQ$24,$AL7='King Node Model'!$AM$20,$AL7='King Node Model'!$AM$21,$AL7='King Node Model'!$AM$22),OR(AND('King Node Model'!$B$23-$AL7>=0,'King Node Model'!$B$23-$AL7<=5),AND('King Node Model'!$C$23-$AL7>=0,'King Node Model'!$C$23-$AL7<=5))),AND('King Node Model'!$P$13="Down",OR($AL7=$AR$22,$AL7=$AR$23,$AL7=$AR$24,$AL7='King Node Model'!$AN$20,$AL7='King Node Model'!$AN$21,$AL7='King Node Model'!$AN$22),OR(AND($AL7-'King Node Model'!$B$23>=0,$AL7-'King Node Model'!$B$23<=5),AND($AL7-'King Node Model'!$C$24>=0,$AL7-'King Node Model'!$C$24<=5)))))),AND(AND(ISNUMBER($AL7),OR(AND($AL7>=$AQ$22,$AL7<=$AR$22,$AS$22=1),$AL7=$AQ$22,$AL7=$AR$22,$AL7=$AQ$23,$AL7=$AR$23,$AL7=$AQ$24,$AL7=$AR$24,$AL7='King Node Model'!$AL$42,$AL7='King Node Model'!$AL$43),OR($AL7=$AN$5,$AL7=$AN$6,$AL7=$AN$7,$AL7=$AN$8,$AL7=$AN$10,$AL7=$AN$11)),NOT(OR(AND('King Node Model'!$P$13="Up",OR($AL7=$AQ$22,$AL7=$AQ$23,$AL7=$AQ$24,$AL7='King Node Model'!$AM$20,$AL7='King Node Model'!$AM$21,$AL7='King Node Model'!$AM$22),OR(AND('King Node Model'!$B$23-$AL7>=0,'King Node Model'!$B$23-$AL7<=5),AND('King Node Model'!$C$23-$AL7>=0,'King Node Model'!$C$23-$AL7<=5))),AND('King Node Model'!$P$13="Down",OR($AL7=$AR$22,$AL7=$AR$23,$AL7=$AR$24,$AL7='King Node Model'!$AN$20,$AL7='King Node Model'!$AN$21,$AL7='King Node Model'!$AN$22),OR(AND($AL7-'King Node Model'!$B$23>=0,$AL7-'King Node Model'!$B$23<=5),AND($AL7-'King Node Model'!$C$24>=0,$AL7-'King Node Model'!$C$24<=5)))))),AND(AND(ISNUMBER($AL7),OR(AND($AL7>='King Node Model'!$AM$20,$AL7<='King Node Model'!$AN$20,$AS$23=1),$AL7='King Node Model'!$AM$20,$AL7='King Node Model'!$AN$20,$AL7='King Node Model'!$AM$21,$AL7='King Node Model'!$AN$21,$AL7='King Node Model'!$AM$22,$AL7='King Node Model'!$AN$22),NOT(OR($AL7=$AN$5,$AL7=$AN$6,$AL7=$AN$7,$AL7=$AN$8,$AL7=$AN$10,$AL7=$AN$11))),NOT(AND(ISNUMBER('King Node Model'!$F$24),$AL7='King Node Model'!$F$24,IFERROR(INDEX('Level Engine'!$JN$9:$JN$55,MATCH($AL7,'Level Engine'!$AA$9:$AA$55,0)),0)<>1))),AND(AND(ISNUMBER($AL7),OR(AND($AL7>='King Node Model'!$AM$20,$AL7<='King Node Model'!$AN$20,$AS$23=1),$AL7='King Node Model'!$AM$20,$AL7='King Node Model'!$AN$20,$AL7='King Node Model'!$AM$21,$AL7='King Node Model'!$AN$21,$AL7='King Node Model'!$AM$22,$AL7='King Node Model'!$AN$22,$AL7='King Node Model'!$AL$49,$AL7='King Node Model'!$AL$50),OR($AL7=$AN$5,$AL7=$AN$6,$AL7=$AN$7,$AL7=$AN$8,$AL7=$AN$10,$AL7=$AN$11)),NOT(OR(AND('King Node Model'!$P$13="Up",OR($AL7=$AQ$22,$AL7=$AQ$23,$AL7=$AQ$24,$AL7='King Node Model'!$AM$20,$AL7='King Node Model'!$AM$21,$AL7='King Node Model'!$AM$22),OR(AND('King Node Model'!$B$23-$AL7>=0,'King Node Model'!$B$23-$AL7<=5),AND('King Node Model'!$C$23-$AL7>=0,'King Node Model'!$C$23-$AL7<=5))),AND('King Node Model'!$P$13="Down",OR($AL7=$AR$22,$AL7=$AR$23,$AL7=$AR$24,$AL7='King Node Model'!$AN$20,$AL7='King Node Model'!$AN$21,$AL7='King Node Model'!$AN$22),OR(AND($AL7-'King Node Model'!$B$23>=0,$AL7-'King Node Model'!$B$23<=5),AND($AL7-'King Node Model'!$C$24>=0,$AL7-'King Node Model'!$C$24<=5))))))),OR(COUNTIF('Level Engine'!$W$9:$W$14,$AL7)>0,COUNTIF('Level Engine'!$W$18:$W$23,$AL7)>0)),1,0)) -> 0 | AZ7: =IF($B$2="Hide unsafe",0,$BB7) -> 0 | BB7: =IF(OR(AND($AL7='King Node Model'!$AL$42,$AP$45<>"RASP"),AND($AL7='King Node Model'!$AL$43,$AP$46<>"RASP"),AND($AL7='King Node Model'!$AL$49,$AP$52<>"RASP"),AND($AL7='King Node Model'!$AL$50,$AP$53<>"RASP"),AND($AL7='King Node Model'!$AL$44,$AP$47<>"RASP"),AND($AL7='King Node Model'!$AL$51,$AP$54<>"RASP")),0,IF(AND(AND(ISNUMBER($AL7),OR(AND($AL7>=$AQ$22,$AL7<=$AR$22,$AP$45="RASP"),AND($AL7>=$AQ$23,$AL7<=$AR$23,$AP$46="RASP"),AND($AL7>=$AQ$24,$AL7<=$AR$24,$AP$47="RASP"),AND($AL7>='King Node Model'!$AM$20,$AL7<='King Node Model'!$AN$20,$AP$52="RASP",NOT($L$52=$AW$52)),AND($AL7='King Node Model'!$B$23,$AP$52="RASP",$L$52=$AW$52),AND($AL7>='King Node Model'!$AM$21,$AL7<='King Node Model'!$AN$21,$AP$53="RASP",NOT($L$53=$AW$53)),AND($AL7='King Node Model'!$B$23,$AP$53="RASP",$L$53=$AW$53),AND($AL7>='King Node Model'!$AM$22,$AL7<='King Node Model'!$AN$22,$AP$54="RASP"),AND($AL7>=IFERROR(INDEX('Level Engine'!$AT$9:$AT$55,MATCH('King Node Model'!$AL$42,'Level Engine'!$AA$9:$AA$55,0)),""),$AL7<=IFERROR(INDEX('Level Engine'!$AU$9:$AU$55,MATCH('King Node Model'!$AL$42,'Level Engine'!$AA$9:$AA$55,0)),""),$AP$45="RASP"),AND($AL7>=IFERROR(INDEX('Level Engine'!$AT$9:$AT$55,MATCH('King Node Model'!$AL$43,'Level Engine'!$AA$9:$AA$55,0)),""),$AL7<=IFERROR(INDEX('Level Engine'!$AU$9:$AU$55,MATCH('King Node Model'!$AL$43,'Level Engine'!$AA$9:$AA$55,0)),""),$AP$46="RASP"),AND($AL7>=IFERROR(INDEX('Level Engine'!$AT$9:$AT$55,MATCH('King Node Model'!$AL$44,'Level Engine'!$AA$9:$AA$55,0)),""),$AL7<=IFERROR(INDEX('Level Engine'!$AU$9:$AU$55,MATCH('King Node Model'!$AL$44,'Level Engine'!$AA$9:$AA$55,0)),""),$AP$47="RASP"),AND($AL7>=IFERROR(INDEX('Level Engine'!$AT$9:$AT$55,MATCH('King Node Model'!$AL$49,'Level Engine'!$AA$9:$AA$55,0)),""),$AL7<=IFERROR(INDEX('Level Engine'!$AU$9:$AU$55,MATCH('King Node Model'!$AL$49,'Level Engine'!$AA$9:$AA$55,0)),""),$AP$52="RASP",NOT($L$52=$AW$52)),AND($AL7>=IFERROR(INDEX('Level Engine'!$AT$9:$AT$55,MATCH('King Node Model'!$AL$50,'Level Engine'!$AA$9:$AA$55,0)),""),$AL7<=IFERROR(INDEX('Level Engine'!$AU$9:$AU$55,MATCH('King Node Model'!$AL$50,'Level Engine'!$AA$9:$AA$55,0)),""),$AP$53="RASP",NOT($L$53=$AW$53)),AND($AL7>=IFERROR(INDEX('Level Engine'!$AT$9:$AT$55,MATCH('King Node Model'!$AL$51,'Level Engine'!$AA$9:$AA$55,0)),""),$AL7<=IFERROR(INDEX('Level Engine'!$AU$9:$AU$55,MATCH('King Node Model'!$AL$51,'Level Engine'!$AA$9:$AA$55,0)),""),$AP$54="RASP"))),NOT(AND(ISNUMBER('King Node Model'!$F$24),$AL7='King Node Model'!$F$24,IFERROR(INDEX('Level Engine'!$JN$9:$JN$55,MATCH($AL7,'Level Engine'!$AA$9:$AA$55,0)),0)<>1,$AL7<>'King Node Model'!$AL$42,$AL7<>'King Node Model'!$AL$43,$AL7<>'King Node Model'!$AL$44,$AL7<>'King Node Model'!$AL$49,$AL7<>'King Node Model'!$AL$50,$AL7<>'King Node Model'!$AL$51))),1,0)) -> 0 | CO7: =IF(NOT(ISNUMBER($AL7)),"",IF(NOT(ISNUMBER(IFERROR(INDEX('Level Engine'!$FT$9:$FT$55,MATCH($AL7,'Level Engine'!$AA$9:$AA$55,0)),""))),"",IF(IFERROR(INDEX('Level Engine'!$FT$9:$FT$55,MATCH($AL7,'Level Engine'!$AA$9:$AA$55,0)),"")<0,0,2)+IF(ABS(IFERROR(INDEX('Level Engine'!$FT$9:$FT$55,MATCH($AL7,'Level Engine'!$AA$9:$AA$55,0)),""))>='Level Engine'!$FT$2,2,1))) -> 4 | DJ7: =IF(ISNUMBER($AL7),IF($AL7='Level Engine'!$BG$122," ⫪","")&IF($AL7='Level Engine'!$BG$118," S↑"&IFERROR(INDEX('Level Engine'!$MV$9:$MV$55,MATCH($AL7,'Level Engine'!$AA$9:$AA$55,0)),""),"")&IF($AL7='Level Engine'!$BG$119," S↓"&IFERROR(INDEX('Level Engine'!$MV$9:$MV$55,MATCH($AL7,'Level Engine'!$AA$9:$AA$55,0)),""),"")&IF($AL7='Level Engine'!$BG$120," D↑","")&IF($AL7='Level Engine'!$BG$121," D↓","")&IFERROR(INDEX('Level Engine'!$LG$9:$LG$55,MATCH($AL7,'Level Engine'!$AA$9:$AA$55,0)),"")&IF(IFERROR(INDEX('Level Engine'!$MA$9:$MA$55,MATCH($AL7,'Level Engine'!$AA$9:$AA$55,0)),0)=1," SAND","")&IF(IFERROR(INDEX('Level Engine'!$LM$9:$LM$55,MATCH($AL7,'Level Engine'!$AA$9:$AA$55,0)),0)>0," TP","")&IFERROR(" r"&MATCH($AL7,'Level Engine'!$W$9:$W$14,0),IFERROR(" s"&MATCH($AL7,'Level Engine'!$W$18:$W$23,0),""))&IF($AL7='Level Engine'!$BG$165," ◇","")&IF(N($DZ7)=1,IF($AL7>'Level Engine'!$BG$165," ⚠ DOM↓"," ⚠ DOM↑")&'Level Engine'!$BG$165,""),"") | DK7: =IF(AND(ISNUMBER($AL7),OR($AL7='King Node Model'!$AL$42,$AL7='King Node Model'!$AL$43,$AL7='King Node Model'!$AL$44)),IFERROR(MATCH($AL7,'Level Engine'!$W$9:$W$14,0),""),"") | DL7: =IF(AND(ISNUMBER($AL7),OR($AL7='King Node Model'!$AL$49,$AL7='King Node Model'!$AL$50,$AL7='King Node Model'!$AL$51)),IFERROR(MATCH($AL7,'Level Engine'!$W$18:$W$23,0),""),"") | DM7: =IF(AND(ISNUMBER($AL7),IFERROR(INDEX('Level Engine'!$LC$9:$LC$55,MATCH($AL7,'Level Engine'!$AA$9:$AA$55,0)),0)=1,OR($AL7=$AN$3,IFERROR(INDEX('Level Engine'!$LB$9:$LB$55,MATCH($AL7,'Level Engine'!$AA$9:$AA$55,0)),0)=1)),1,0) -> 0 | DZ7: =IF(ISNUMBER($AL7),IF(IFERROR(INDEX('Level Engine'!$NJ$9:$NJ$55,MATCH($AL7,'Level Engine'!$AA$9:$AA$55,0)),0)=1,1,0),0)
A8: =IF(AND(ISNUMBER($AM8),$AM8<0,ISNUMBER($AO8),$AO$1>0),REPT("█",ROUND($AO8/$AO$1*26,0)),"") | B8: =TEXT(IF(IF('Level Engine'!$GJ$4=1,$AL8='Level Engine'!$GJ$3,AND($AL8-$AM$2>-2.5,$AL8-$AM$2<=2.5)),$AM$2,$AL8),"0")&IF($AL8=$AN$1," ★","")&IF($AL8=$AN$2," ★","")&IF($AL8=$AN$3," ◆","")&IF(AND(ISNUMBER($AN$4),$AL8=$AN$4)," Ⓕ","")&IF(OR(AND(ISNUMBER('Level Engine'!$BG$87),$AL8='Level Engine'!$BG$87),AND(ISNUMBER('Level Engine'!$BG$105),$AL8='Level Engine'!$BG$105))," ζ","")&IF(AND(ISNUMBER($AN$35),$AL8=$AN$35)," ⓏⒼ","")&IF(OR($AL8='Level Engine'!$CP$4,$AL8='Level Engine'!$CP$5,$AL8='Level Engine'!$CP$6,$AL8='Level Engine'!$CP$7)," ☄","")&IF(OR($AL8=$AN$5,$AL8=$AN$8)," ║1","")&IF(OR($AL8=$AN$6,$AL8=$AN$10)," ║2","")&IF(OR($AL8=$AN$7,$AL8=$AN$11)," ║3","")&IF(OR($AL8=$AN$13,$AL8=$AN$16)," ▣1","")&IF(OR($AL8=$AN$14,$AL8=$AN$17)," ▣2","")&IF(OR($AL8=$AN$15,$AL8=$AN$18)," ▣3","")&IF(AND(NOT(OR(AND(ISNUMBER(SEARCH("chop edge",$E$45)),IFERROR(ABS($AL8-'King Node Model'!$AL$42)<=5,FALSE),NOT(ISNUMBER(SEARCH("UNSAFE",$L$45)))),AND(ISNUMBER(SEARCH("chop edge",$E$46)),IFERROR(ABS($AL8-'King Node Model'!$AL$43)<=5,FALSE),NOT(ISNUMBER(SEARCH("UNSAFE",$L$46)))),AND(ISNUMBER(SEARCH("chop edge",$E$52)),IFERROR(ABS($AL8-'King Node Model'!$AL$49)<=5,FALSE),NOT(ISNUMBER(SEARCH("UNSAFE",$L$52)))),AND(ISNUMBER(SEARCH("chop edge",$E$53)),IFERROR(ABS($AL8-'King Node Model'!$AL$50)<=5,FALSE),NOT(ISNUMBER(SEARCH("UNSAFE",$L$53)))))),OR(AND(IFERROR(INDEX('Level Engine'!$IB$9:$IB$55,MATCH('King Node Model'!$AL$49,'Level Engine'!$AA$9:$AA$55,0)),0)<>1,$AL8=IFERROR(INDEX('Level Engine'!$AU$9:$AU$55,MATCH('King Node Model'!$AL$49,'Level Engine'!$AA$9:$AA$55,0)),""),IFERROR(INDEX('Level Engine'!$AU$9:$AU$55,MATCH('King Node Model'!$AL$49,'Level Engine'!$AA$9:$AA$55,0)),"")<>IFERROR(INDEX('Level Engine'!$AT$9:$AT$55,MATCH('King Node Model'!$AL$49,'Level Engine'!$AA$9:$AA$55,0)),"")),AND(IFERROR(INDEX('Level Engine'!$IB$9:$IB$55,MATCH('King Node Model'!$AL$50,'Level Engine'!$AA$9:$AA$55,0)),0)<>1,$AL8=IFERROR(INDEX('Level Engine'!$AU$9:$AU$55,MATCH('King Node Model'!$AL$50,'Level Engine'!$AA$9:$AA$55,0)),""),IFERROR(INDEX('Level Engine'!$AU$9:$AU$55,MATCH('King Node Model'!$AL$50,'Level Engine'!$AA$9:$AA$55,0)),"")<>IFERROR(INDEX('Level Engine'!$AT$9:$AT$55,MATCH('King Node Model'!$AL$50,'Level Engine'!$AA$9:$AA$55,0)),"")))),IF(OR('King Node Model'!$A$8="Neg",N('Level Engine'!$BG$72)=1),""," ⒷⒽ"),"")&IF(AND(NOT(OR(AND(ISNUMBER(SEARCH("chop edge",$E$45)),IFERROR(ABS($AL8-'King Node Model'!$AL$42)<=5,FALSE),NOT(ISNUMBER(SEARCH("UNSAFE",$L$45)))),AND(ISNUMBER(SEARCH("chop edge",$E$46)),IFERROR(ABS($AL8-'King Node Model'!$AL$43)<=5,FALSE),NOT(ISNUMBER(SEARCH("UNSAFE",$L$46)))),AND(ISNUMBER(SEARCH("chop edge",$E$52)),IFERROR(ABS($AL8-'King Node Model'!$AL$49)<=5,FALSE),NOT(ISNUMBER(SEARCH("UNSAFE",$L$52)))),AND(ISNUMBER(SEARCH("chop edge",$E$53)),IFERROR(ABS($AL8-'King Node Model'!$AL$50)<=5,FALSE),NOT(ISNUMBER(SEARCH("UNSAFE",$L$53)))))),OR(AND(IFERROR(INDEX('Level Engine'!$IB$9:$IB$55,MATCH('King Node Model'!$AL$42,'Level Engine'!$AA$9:$AA$55,0)),0)<>1,$AL8=IFERROR(INDEX('Level Engine'!$AT$9:$AT$55,MATCH('King Node Model'!$AL$42,'Level Engine'!$AA$9:$AA$55,0)),""),IFERROR(INDEX('Level Engine'!$AT$9:$AT$55,MATCH('King Node Model'!$AL$42,'Level Engine'!$AA$9:$AA$55,0)),"")<>IFERROR(INDEX('Level Engine'!$AU$9:$AU$55,MATCH('King Node Model'!$AL$42,'Level Engine'!$AA$9:$AA$55,0)),"")),AND(IFERROR(INDEX('Level Engine'!$IB$9:$IB$55,MATCH('King Node Model'!$AL$43,'Level Engine'!$AA$9:$AA$55,0)),0)<>1,$AL8=IFERROR(INDEX('Level Engine'!$AT$9:$AT$55,MATCH('King Node Model'!$AL$43,'Level Engine'!$AA$9:$AA$55,0)),""),IFERROR(INDEX('Level Engine'!$AT$9:$AT$55,MATCH('King Node Model'!$AL$43,'Level Engine'!$AA$9:$AA$55,0)),"")<>IFERROR(INDEX('Level Engine'!$AU$9:$AU$55,MATCH('King Node Model'!$AL$43,'Level Engine'!$AA$9:$AA$55,0)),"")))),IF(OR('King Node Model'!$A$8="Neg",N('Level Engine'!$BG$72)=1),""," ⒷⓁ"),"")&IF(OR(AND($AL8>='King Node Model'!$AM$17,$AL8<='King Node Model'!$AN$17,$AP$45="RASP"),AND($AL8>='King Node Model'!$AM$18,$AL8<='King Node Model'!$AN$18,$AP$46="RASP"),AND($AL8>='King Node Model'!$AM$19,$AL8<='King Node Model'!$AN$19,$AP$47="RASP"),AND($AL8>='King Node Model'!$AM$20,$AL8<='King Node Model'!$AN$20,$AP$52="RASP"),AND($AL8>='King Node Model'!$AM$21,$AL8<='King Node Model'!$AN$21,$AP$53="RASP"),AND($AL8>='King Node Model'!$AM$22,$AL8<='King Node Model'!$AN$22,$AP$54="RASP")),"","")&IF(IF('Level Engine'!$GJ$4=1,$AL8='Level Engine'!$GJ$3,AND($AL8-$AM$2>-2.5,$AL8-$AM$2<=2.5))," ◄","")&IF(IFERROR(INDEX('Level Engine'!$GV$9:$GV$55,MATCH($AL8,'Level Engine'!$AA$9:$AA$55,0)),0)=1," Ⓥ"&IF(IFERROR(INDEX('Level Engine'!$ET$9:$ET$55,MATCH($AL8,'Level Engine'!$AA$9:$AA$55,0)),0)=1,"+",""),"")&IF(OR(AND($AL8=$AN$38,IFERROR(INDEX('Level Engine'!$AN$9:$AN$55,MATCH($AL8,'Level Engine'!$AA$9:$AA$55,0)),0)<>1),$AL8=$AN$39)," ⊙","")&IF(AND(OR('King Node Model'!$A$8="Neg",N('Level Engine'!$BG$72)=1),ABS(MIN($AM$3:$AM$64))>MAX($AM$3:$AM$64),$AN$2<$AM$2,$AL8<$AM$2,ABS($AL8-$AN$2)<=5,IFERROR(VALUE(MID('King Node Model'!$K$26,FIND(":",'King Node Model'!$K$26)-2,2)),0)>=19,IFERROR(INDEX('Level Engine'!$EJ$9:$EJ$55,MATCH($AL8,'Level Engine'!$AA$9:$AA$55,0)),0)=0,$AN$3>$AM$2)," ⟲rev","")&IF($AL8='King Node Model'!$F$24," ⟂","")&$DJ8&IF(IFERROR(INDEX('Level Engine'!$EN$9:$EN$55,MATCH($AL8,'Level Engine'!$AA$9:$AA$55,0)),0)=1," Ⓟ"&IF(AND(OR('King Node Model'!$A$8="Neg",N('Level Engine'!$BG$72)=1),IFERROR(INDEX('Level Engine'!$AN$9:$AN$55,MATCH($AL8,'Level Engine'!$AA$9:$AA$55,0)),0)<>1)," NO-REV",""),"")&IF(AND(ISNUMBER($AL8),OR(AND(ISNUMBER(SEARCH("chop edge",$E$45)),$AL8='King Node Model'!$AL$42),AND(ISNUMBER(SEARCH("chop edge",$E$46)),$AL8='King Node Model'!$AL$43),AND(ISNUMBER(SEARCH("chop edge",$E$52)),$AL8='King Node Model'!$AL$49),AND(ISNUMBER(SEARCH("chop edge",$E$53)),$AL8='King Node Model'!$AL$50)))," ⒸⒺ","")&IF(AND('Level Engine'!$GJ$4=1,OR($AL8='Level Engine'!$GJ$1,$AL8='Level Engine'!$GJ$2)),"","")&IF(ABS(N(IFERROR(INDEX('Level Engine'!$AE$9:$AE$55,MATCH($AL8,'Level Engine'!$AA$9:$AA$55,0)),0)))>='Level Engine'!$BG$85,IF(N(IFERROR(INDEX('Level Engine'!$AE$9:$AE$55,MATCH($AL8,'Level Engine'!$AA$9:$AA$55,0)),0))>0," Δ+"," Δ−"),"")&IFERROR(IF(AND(ISNUMBER(MATCH($AL8,'Level Engine'!$AA$9:$AA$55,0)),ABS(N(IFERROR(INDEX('Level Engine'!$AE$9:$AE$55,MATCH($AL8,'Level Engine'!$AA$9:$AA$55,0)),0)))<'Level Engine'!$BG$85,ABS(N(IFERROR(INDEX('Level Engine'!$AE$9:$AE$55,MATCH($AL8,'Level Engine'!$AA$9:$AA$55,0)),0)))<=ABS(N(IFERROR(INDEX('Level Engine'!$AE$9:$AE$55,MATCH($AL8+5,'Level Engine'!$AA$9:$AA$55,0)),0))),ABS(N(IFERROR(INDEX('Level Engine'!$AE$9:$AE$55,MATCH($AL8,'Level Engine'!$AA$9:$AA$55,0)),0)))<=ABS(N(IFERROR(INDEX('Level Engine'!$AE$9:$AE$55,MATCH($AL8-5,'Level Engine'!$AA$9:$AA$55,0)),0))),OR(AND(ABS(N(IFERROR(INDEX('Level Engine'!$AE$9:$AE$55,MATCH($AL8+5,'Level Engine'!$AA$9:$AA$55,0)),0)))>='Level Engine'!$BG$85,ABS(N(IFERROR(INDEX('Level Engine'!$AE$9:$AE$55,MATCH($AL8,'Level Engine'!$AA$9:$AA$55,0)),0)))<='Level Engine'!$BG$88*ABS(N(IFERROR(INDEX('Level Engine'!$AE$9:$AE$55,MATCH($AL8+5,'Level Engine'!$AA$9:$AA$55,0)),0)))),AND(ABS(N(IFERROR(INDEX('Level Engine'!$AE$9:$AE$55,MATCH($AL8-5,'Level Engine'!$AA$9:$AA$55,0)),0)))>='Level Engine'!$BG$85,ABS(N(IFERROR(INDEX('Level Engine'!$AE$9:$AE$55,MATCH($AL8,'Level Engine'!$AA$9:$AA$55,0)),0)))<='Level Engine'!$BG$88*ABS(N(IFERROR(INDEX('Level Engine'!$AE$9:$AE$55,MATCH($AL8-5,'Level Engine'!$AA$9:$AA$55,0)),0)))))),IF(AND('King Node Model'!$A$8="Pos",N('Level Engine'!$BG$72)<>1),""," ∅"),""),"")&IF(IFERROR(INDEX('Level Engine'!$JD$9:$JD$55,MATCH($AL8,'Level Engine'!$AA$9:$AA$55,0)),"")="P"," P-OI",IF(IFERROR(INDEX('Level Engine'!$JD$9:$JD$55,MATCH($AL8,'Level Engine'!$AA$9:$AA$55,0)),"")="C"," C-OI","")) -> 7860 | C8: =IF(AND(ISNUMBER($AM8),$AM8>0,ISNUMBER($AO8),$AO$1>0),REPT("█",ROUND($AO8/$AO$1*26,0)),"") -> █ | D8: =IF(NOT(ISNUMBER($AL8)),"",IF(IFERROR(INDEX('Level Engine'!$FS$9:$FS$55,MATCH($AL8,'Level Engine'!$AA$9:$AA$55,0)),0)=1,"⊙","")) | E8: REGIME READ | G8: ='King Node Model'!A20 -> BUY-LEAN REGIME - buy dips per matrix guidance. | AL8: ='King Node Model'!A34 -> 7860 | AM8: ='King Node Model'!C34 -> 89475 | AN8: ='King Node Model'!T28 -> 7770 | AO8: ='King Node Model'!B34 -> 95407 | AY8: =IF(AND($B$2="Hide unsafe",$BB8=1),0,IF(AND(OR(AND(AND(ISNUMBER($AL8),OR(AND($AL8>=$AQ$22,$AL8<=$AR$22,$AS$22=1),$AL8=$AQ$22,$AL8=$AR$22,$AL8=$AQ$23,$AL8=$AR$23,$AL8=$AQ$24,$AL8=$AR$24),NOT(OR($AL8=$AN$5,$AL8=$AN$6,$AL8=$AN$7,$AL8=$AN$8,$AL8=$AN$10,$AL8=$AN$11))),NOT(OR(AND('King Node Model'!$P$13="Up",OR($AL8=$AQ$22,$AL8=$AQ$23,$AL8=$AQ$24,$AL8='King Node Model'!$AM$20,$AL8='King Node Model'!$AM$21,$AL8='King Node Model'!$AM$22),OR(AND('King Node Model'!$B$23-$AL8>=0,'King Node Model'!$B$23-$AL8<=5),AND('King Node Model'!$C$23-$AL8>=0,'King Node Model'!$C$23-$AL8<=5))),AND('King Node Model'!$P$13="Down",OR($AL8=$AR$22,$AL8=$AR$23,$AL8=$AR$24,$AL8='King Node Model'!$AN$20,$AL8='King Node Model'!$AN$21,$AL8='King Node Model'!$AN$22),OR(AND($AL8-'King Node Model'!$B$23>=0,$AL8-'King Node Model'!$B$23<=5),AND($AL8-'King Node Model'!$C$24>=0,$AL8-'King Node Model'!$C$24<=5)))))),AND(AND(ISNUMBER($AL8),OR(AND($AL8>=$AQ$22,$AL8<=$AR$22,$AS$22=1),$AL8=$AQ$22,$AL8=$AR$22,$AL8=$AQ$23,$AL8=$AR$23,$AL8=$AQ$24,$AL8=$AR$24,$AL8='King Node Model'!$AL$42,$AL8='King Node Model'!$AL$43),OR($AL8=$AN$5,$AL8=$AN$6,$AL8=$AN$7,$AL8=$AN$8,$AL8=$AN$10,$AL8=$AN$11)),NOT(OR(AND('King Node Model'!$P$13="Up",OR($AL8=$AQ$22,$AL8=$AQ$23,$AL8=$AQ$24,$AL8='King Node Model'!$AM$20,$AL8='King Node Model'!$AM$21,$AL8='King Node Model'!$AM$22),OR(AND('King Node Model'!$B$23-$AL8>=0,'King Node Model'!$B$23-$AL8<=5),AND('King Node Model'!$C$23-$AL8>=0,'King Node Model'!$C$23-$AL8<=5))),AND('King Node Model'!$P$13="Down",OR($AL8=$AR$22,$AL8=$AR$23,$AL8=$AR$24,$AL8='King Node Model'!$AN$20,$AL8='King Node Model'!$AN$21,$AL8='King Node Model'!$AN$22),OR(AND($AL8-'King Node Model'!$B$23>=0,$AL8-'King Node Model'!$B$23<=5),AND($AL8-'King Node Model'!$C$24>=0,$AL8-'King Node Model'!$C$24<=5)))))),AND(AND(ISNUMBER($AL8),OR(AND($AL8>='King Node Model'!$AM$20,$AL8<='King Node Model'!$AN$20,$AS$23=1),$AL8='King Node Model'!$AM$20,$AL8='King Node Model'!$AN$20,$AL8='King Node Model'!$AM$21,$AL8='King Node Model'!$AN$21,$AL8='King Node Model'!$AM$22,$AL8='King Node Model'!$AN$22),NOT(OR($AL8=$AN$5,$AL8=$AN$6,$AL8=$AN$7,$AL8=$AN$8,$AL8=$AN$10,$AL8=$AN$11))),NOT(AND(ISNUMBER('King Node Model'!$F$24),$AL8='King Node Model'!$F$24,IFERROR(INDEX('Level Engine'!$JN$9:$JN$55,MATCH($AL8,'Level Engine'!$AA$9:$AA$55,0)),0)<>1))),AND(AND(ISNUMBER($AL8),OR(AND($AL8>='King Node Model'!$AM$20,$AL8<='King Node Model'!$AN$20,$AS$23=1),$AL8='King Node Model'!$AM$20,$AL8='King Node Model'!$AN$20,$AL8='King Node Model'!$AM$21,$AL8='King Node Model'!$AN$21,$AL8='King Node Model'!$AM$22,$AL8='King Node Model'!$AN$22,$AL8='King Node Model'!$AL$49,$AL8='King Node Model'!$AL$50),OR($AL8=$AN$5,$AL8=$AN$6,$AL8=$AN$7,$AL8=$AN$8,$AL8=$AN$10,$AL8=$AN$11)),NOT(OR(AND('King Node Model'!$P$13="Up",OR($AL8=$AQ$22,$AL8=$AQ$23,$AL8=$AQ$24,$AL8='King Node Model'!$AM$20,$AL8='King Node Model'!$AM$21,$AL8='King Node Model'!$AM$22),OR(AND('King Node Model'!$B$23-$AL8>=0,'King Node Model'!$B$23-$AL8<=5),AND('King Node Model'!$C$23-$AL8>=0,'King Node Model'!$C$23-$AL8<=5))),AND('King Node Model'!$P$13="Down",OR($AL8=$AR$22,$AL8=$AR$23,$AL8=$AR$24,$AL8='King Node Model'!$AN$20,$AL8='King Node Model'!$AN$21,$AL8='King Node Model'!$AN$22),OR(AND($AL8-'King Node Model'!$B$23>=0,$AL8-'King Node Model'!$B$23<=5),AND($AL8-'King Node Model'!$C$24>=0,$AL8-'King Node Model'!$C$24<=5))))))),OR(COUNTIF('Level Engine'!$W$9:$W$14,$AL8)>0,COUNTIF('Level Engine'!$W$18:$W$23,$AL8)>0)),1,0)) -> 0 | AZ8: =IF($B$2="Hide unsafe",0,$BB8) -> 0 | BB8: =IF(OR(AND($AL8='King Node Model'!$AL$42,$AP$45<>"RASP"),AND($AL8='King Node Model'!$AL$43,$AP$46<>"RASP"),AND($AL8='King Node Model'!$AL$49,$AP$52<>"RASP"),AND($AL8='King Node Model'!$AL$50,$AP$53<>"RASP"),AND($AL8='King Node Model'!$AL$44,$AP$47<>"RASP"),AND($AL8='King Node Model'!$AL$51,$AP$54<>"RASP")),0,IF(AND(AND(ISNUMBER($AL8),OR(AND($AL8>=$AQ$22,$AL8<=$AR$22,$AP$45="RASP"),AND($AL8>=$AQ$23,$AL8<=$AR$23,$AP$46="RASP"),AND($AL8>=$AQ$24,$AL8<=$AR$24,$AP$47="RASP"),AND($AL8>='King Node Model'!$AM$20,$AL8<='King Node Model'!$AN$20,$AP$52="RASP",NOT($L$52=$AW$52)),AND($AL8='King Node Model'!$B$23,$AP$52="RASP",$L$52=$AW$52),AND($AL8>='King Node Model'!$AM$21,$AL8<='King Node Model'!$AN$21,$AP$53="RASP",NOT($L$53=$AW$53)),AND($AL8='King Node Model'!$B$23,$AP$53="RASP",$L$53=$AW$53),AND($AL8>='King Node Model'!$AM$22,$AL8<='King Node Model'!$AN$22,$AP$54="RASP"),AND($AL8>=IFERROR(INDEX('Level Engine'!$AT$9:$AT$55,MATCH('King Node Model'!$AL$42,'Level Engine'!$AA$9:$AA$55,0)),""),$AL8<=IFERROR(INDEX('Level Engine'!$AU$9:$AU$55,MATCH('King Node Model'!$AL$42,'Level Engine'!$AA$9:$AA$55,0)),""),$AP$45="RASP"),AND($AL8>=IFERROR(INDEX('Level Engine'!$AT$9:$AT$55,MATCH('King Node Model'!$AL$43,'Level Engine'!$AA$9:$AA$55,0)),""),$AL8<=IFERROR(INDEX('Level Engine'!$AU$9:$AU$55,MATCH('King Node Model'!$AL$43,'Level Engine'!$AA$9:$AA$55,0)),""),$AP$46="RASP"),AND($AL8>=IFERROR(INDEX('Level Engine'!$AT$9:$AT$55,MATCH('King Node Model'!$AL$44,'Level Engine'!$AA$9:$AA$55,0)),""),$AL8<=IFERROR(INDEX('Level Engine'!$AU$9:$AU$55,MATCH('King Node Model'!$AL$44,'Level Engine'!$AA$9:$AA$55,0)),""),$AP$47="RASP"),AND($AL8>=IFERROR(INDEX('Level Engine'!$AT$9:$AT$55,MATCH('King Node Model'!$AL$49,'Level Engine'!$AA$9:$AA$55,0)),""),$AL8<=IFERROR(INDEX('Level Engine'!$AU$9:$AU$55,MATCH('King Node Model'!$AL$49,'Level Engine'!$AA$9:$AA$55,0)),""),$AP$52="RASP",NOT($L$52=$AW$52)),AND($AL8>=IFERROR(INDEX('Level Engine'!$AT$9:$AT$55,MATCH('King Node Model'!$AL$50,'Level Engine'!$AA$9:$AA$55,0)),""),$AL8<=IFERROR(INDEX('Level Engine'!$AU$9:$AU$55,MATCH('King Node Model'!$AL$50,'Level Engine'!$AA$9:$AA$55,0)),""),$AP$53="RASP",NOT($L$53=$AW$53)),AND($AL8>=IFERROR(INDEX('Level Engine'!$AT$9:$AT$55,MATCH('King Node Model'!$AL$51,'Level Engine'!$AA$9:$AA$55,0)),""),$AL8<=IFERROR(INDEX('Level Engine'!$AU$9:$AU$55,MATCH('King Node Model'!$AL$51,'Level Engine'!$AA$9:$AA$55,0)),""),$AP$54="RASP"))),NOT(AND(ISNUMBER('King Node Model'!$F$24),$AL8='King Node Model'!$F$24,IFERROR(INDEX('Level Engine'!$JN$9:$JN$55,MATCH($AL8,'Level Engine'!$AA$9:$AA$55,0)),0)<>1,$AL8<>'King Node Model'!$AL$42,$AL8<>'King Node Model'!$AL$43,$AL8<>'King Node Model'!$AL$44,$AL8<>'King Node Model'!$AL$49,$AL8<>'King Node Model'!$AL$50,$AL8<>'King Node Model'!$AL$51))),1,0)) -> 0 | CO8: =IF(NOT(ISNUMBER($AL8)),"",IF(NOT(ISNUMBER(IFERROR(INDEX('Level Engine'!$FT$9:$FT$55,MATCH($AL8,'Level Engine'!$AA$9:$AA$55,0)),""))),"",IF(IFERROR(INDEX('Level Engine'!$FT$9:$FT$55,MATCH($AL8,'Level Engine'!$AA$9:$AA$55,0)),"")<0,0,2)+IF(ABS(IFERROR(INDEX('Level Engine'!$FT$9:$FT$55,MATCH($AL8,'Level Engine'!$AA$9:$AA$55,0)),""))>='Level Engine'!$FT$2,2,1))) -> 4 | DJ8: =IF(ISNUMBER($AL8),IF($AL8='Level Engine'!$BG$122," ⫪","")&IF($AL8='Level Engine'!$BG$118," S↑"&IFERROR(INDEX('Level Engine'!$MV$9:$MV$55,MATCH($AL8,'Level Engine'!$AA$9:$AA$55,0)),""),"")&IF($AL8='Level Engine'!$BG$119," S↓"&IFERROR(INDEX('Level Engine'!$MV$9:$MV$55,MATCH($AL8,'Level Engine'!$AA$9:$AA$55,0)),""),"")&IF($AL8='Level Engine'!$BG$120," D↑","")&IF($AL8='Level Engine'!$BG$121," D↓","")&IFERROR(INDEX('Level Engine'!$LG$9:$LG$55,MATCH($AL8,'Level Engine'!$AA$9:$AA$55,0)),"")&IF(IFERROR(INDEX('Level Engine'!$MA$9:$MA$55,MATCH($AL8,'Level Engine'!$AA$9:$AA$55,0)),0)=1," SAND","")&IF(IFERROR(INDEX('Level Engine'!$LM$9:$LM$55,MATCH($AL8,'Level Engine'!$AA$9:$AA$55,0)),0)>0," TP","")&IFERROR(" r"&MATCH($AL8,'Level Engine'!$W$9:$W$14,0),IFERROR(" s"&MATCH($AL8,'Level Engine'!$W$18:$W$23,0),""))&IF($AL8='Level Engine'!$BG$165," ◇","")&IF(N($DZ8)=1,IF($AL8>'Level Engine'!$BG$165," ⚠ DOM↓"," ⚠ DOM↑")&'Level Engine'!$BG$165,""),"") | DK8: =IF(AND(ISNUMBER($AL8),OR($AL8='King Node Model'!$AL$42,$AL8='King Node Model'!$AL$43,$AL8='King Node Model'!$AL$44)),IFERROR(MATCH($AL8,'Level Engine'!$W$9:$W$14,0),""),"") | DL8: =IF(AND(ISNUMBER($AL8),OR($AL8='King Node Model'!$AL$49,$AL8='King Node Model'!$AL$50,$AL8='King Node Model'!$AL$51)),IFERROR(MATCH($AL8,'Level Engine'!$W$18:$W$23,0),""),"") | DM8: =IF(AND(ISNUMBER($AL8),IFERROR(INDEX('Level Engine'!$LC$9:$LC$55,MATCH($AL8,'Level Engine'!$AA$9:$AA$55,0)),0)=1,OR($AL8=$AN$3,IFERROR(INDEX('Level Engine'!$LB$9:$LB$55,MATCH($AL8,'Level Engine'!$AA$9:$AA$55,0)),0)=1)),1,0) -> 0 | DZ8: =IF(ISNUMBER($AL8),IF(IFERROR(INDEX('Level Engine'!$NJ$9:$NJ$55,MATCH($AL8,'Level Engine'!$AA$9:$AA$55,0)),0)=1,1,0),0)
A9: =IF(AND(ISNUMBER($AM9),$AM9<0,ISNUMBER($AO9),$AO$1>0),REPT("█",ROUND($AO9/$AO$1*26,0)),"") | B9: =TEXT(IF(IF('Level Engine'!$GJ$4=1,$AL9='Level Engine'!$GJ$3,AND($AL9-$AM$2>-2.5,$AL9-$AM$2<=2.5)),$AM$2,$AL9),"0")&IF($AL9=$AN$1," ★","")&IF($AL9=$AN$2," ★","")&IF($AL9=$AN$3," ◆","")&IF(AND(ISNUMBER($AN$4),$AL9=$AN$4)," Ⓕ","")&IF(OR(AND(ISNUMBER('Level Engine'!$BG$87),$AL9='Level Engine'!$BG$87),AND(ISNUMBER('Level Engine'!$BG$105),$AL9='Level Engine'!$BG$105))," ζ","")&IF(AND(ISNUMBER($AN$35),$AL9=$AN$35)," ⓏⒼ","")&IF(OR($AL9='Level Engine'!$CP$4,$AL9='Level Engine'!$CP$5,$AL9='Level Engine'!$CP$6,$AL9='Level Engine'!$CP$7)," ☄","")&IF(OR($AL9=$AN$5,$AL9=$AN$8)," ║1","")&IF(OR($AL9=$AN$6,$AL9=$AN$10)," ║2","")&IF(OR($AL9=$AN$7,$AL9=$AN$11)," ║3","")&IF(OR($AL9=$AN$13,$AL9=$AN$16)," ▣1","")&IF(OR($AL9=$AN$14,$AL9=$AN$17)," ▣2","")&IF(OR($AL9=$AN$15,$AL9=$AN$18)," ▣3","")&IF(AND(NOT(OR(AND(ISNUMBER(SEARCH("chop edge",$E$45)),IFERROR(ABS($AL9-'King Node Model'!$AL$42)<=5,FALSE),NOT(ISNUMBER(SEARCH("UNSAFE",$L$45)))),AND(ISNUMBER(SEARCH("chop edge",$E$46)),IFERROR(ABS($AL9-'King Node Model'!$AL$43)<=5,FALSE),NOT(ISNUMBER(SEARCH("UNSAFE",$L$46)))),AND(ISNUMBER(SEARCH("chop edge",$E$52)),IFERROR(ABS($AL9-'King Node Model'!$AL$49)<=5,FALSE),NOT(ISNUMBER(SEARCH("UNSAFE",$L$52)))),AND(ISNUMBER(SEARCH("chop edge",$E$53)),IFERROR(ABS($AL9-'King Node Model'!$AL$50)<=5,FALSE),NOT(ISNUMBER(SEARCH("UNSAFE",$L$53)))))),OR(AND(IFERROR(INDEX('Level Engine'!$IB$9:$IB$55,MATCH('King Node Model'!$AL$49,'Level Engine'!$AA$9:$AA$55,0)),0)<>1,$AL9=IFERROR(INDEX('Level Engine'!$AU$9:$AU$55,MATCH('King Node Model'!$AL$49,'Level Engine'!$AA$9:$AA$55,0)),""),IFERROR(INDEX('Level Engine'!$AU$9:$AU$55,MATCH('King Node Model'!$AL$49,'Level Engine'!$AA$9:$AA$55,0)),"")<>IFERROR(INDEX('Level Engine'!$AT$9:$AT$55,MATCH('King Node Model'!$AL$49,'Level Engine'!$AA$9:$AA$55,0)),"")),AND(IFERROR(INDEX('Level Engine'!$IB$9:$IB$55,MATCH('King Node Model'!$AL$50,'Level Engine'!$AA$9:$AA$55,0)),0)<>1,$AL9=IFERROR(INDEX('Level Engine'!$AU$9:$AU$55,MATCH('King Node Model'!$AL$50,'Level Engine'!$AA$9:$AA$55,0)),""),IFERROR(INDEX('Level Engine'!$AU$9:$AU$55,MATCH('King Node Model'!$AL$50,'Level Engine'!$AA$9:$AA$55,0)),"")<>IFERROR(INDEX('Level Engine'!$AT$9:$AT$55,MATCH('King Node Model'!$AL$50,'Level Engine'!$AA$9:$AA$55,0)),"")))),IF(OR('King Node Model'!$A$8="Neg",N('Level Engine'!$BG$72)=1),""," ⒷⒽ"),"")&IF(AND(NOT(OR(AND(ISNUMBER(SEARCH("chop edge",$E$45)),IFERROR(ABS($AL9-'King Node Model'!$AL$42)<=5,FALSE),NOT(ISNUMBER(SEARCH("UNSAFE",$L$45)))),AND(ISNUMBER(SEARCH("chop edge",$E$46)),IFERROR(ABS($AL9-'King Node Model'!$AL$43)<=5,FALSE),NOT(ISNUMBER(SEARCH("UNSAFE",$L$46)))),AND(ISNUMBER(SEARCH("chop edge",$E$52)),IFERROR(ABS($AL9-'King Node Model'!$AL$49)<=5,FALSE),NOT(ISNUMBER(SEARCH("UNSAFE",$L$52)))),AND(ISNUMBER(SEARCH("chop edge",$E$53)),IFERROR(ABS($AL9-'King Node Model'!$AL$50)<=5,FALSE),NOT(ISNUMBER(SEARCH("UNSAFE",$L$53)))))),OR(AND(IFERROR(INDEX('Level Engine'!$IB$9:$IB$55,MATCH('King Node Model'!$AL$42,'Level Engine'!$AA$9:$AA$55,0)),0)<>1,$AL9=IFERROR(INDEX('Level Engine'!$AT$9:$AT$55,MATCH('King Node Model'!$AL$42,'Level Engine'!$AA$9:$AA$55,0)),""),IFERROR(INDEX('Level Engine'!$AT$9:$AT$55,MATCH('King Node Model'!$AL$42,'Level Engine'!$AA$9:$AA$55,0)),"")<>IFERROR(INDEX('Level Engine'!$AU$9:$AU$55,MATCH('King Node Model'!$AL$42,'Level Engine'!$AA$9:$AA$55,0)),"")),AND(IFERROR(INDEX('Level Engine'!$IB$9:$IB$55,MATCH('King Node Model'!$AL$43,'Level Engine'!$AA$9:$AA$55,0)),0)<>1,$AL9=IFERROR(INDEX('Level Engine'!$AT$9:$AT$55,MATCH('King Node Model'!$AL$43,'Level Engine'!$AA$9:$AA$55,0)),""),IFERROR(INDEX('Level Engine'!$AT$9:$AT$55,MATCH('King Node Model'!$AL$43,'Level Engine'!$AA$9:$AA$55,0)),"")<>IFERROR(INDEX('Level Engine'!$AU$9:$AU$55,MATCH('King Node Model'!$AL$43,'Level Engine'!$AA$9:$AA$55,0)),"")))),IF(OR('King Node Model'!$A$8="Neg",N('Level Engine'!$BG$72)=1),""," ⒷⓁ"),"")&IF(OR(AND($AL9>='King Node Model'!$AM$17,$AL9<='King Node Model'!$AN$17,$AP$45="RASP"),AND($AL9>='King Node Model'!$AM$18,$AL9<='King Node Model'!$AN$18,$AP$46="RASP"),AND($AL9>='King Node Model'!$AM$19,$AL9<='King Node Model'!$AN$19,$AP$47="RASP"),AND($AL9>='King Node Model'!$AM$20,$AL9<='King Node Model'!$AN$20,$AP$52="RASP"),AND($AL9>='King Node Model'!$AM$21,$AL9<='King Node Model'!$AN$21,$AP$53="RASP"),AND($AL9>='King Node Model'!$AM$22,$AL9<='King Node Model'!$AN$22,$AP$54="RASP")),"","")&IF(IF('Level Engine'!$GJ$4=1,$AL9='Level Engine'!$GJ$3,AND($AL9-$AM$2>-2.5,$AL9-$AM$2<=2.5))," ◄","")&IF(IFERROR(INDEX('Level Engine'!$GV$9:$GV$55,MATCH($AL9,'Level Engine'!$AA$9:$AA$55,0)),0)=1," Ⓥ"&IF(IFERROR(INDEX('Level Engine'!$ET$9:$ET$55,MATCH($AL9,'Level Engine'!$AA$9:$AA$55,0)),0)=1,"+",""),"")&IF(OR(AND($AL9=$AN$38,IFERROR(INDEX('Level Engine'!$AN$9:$AN$55,MATCH($AL9,'Level Engine'!$AA$9:$AA$55,0)),0)<>1),$AL9=$AN$39)," ⊙","")&IF(AND(OR('King Node Model'!$A$8="Neg",N('Level Engine'!$BG$72)=1),ABS(MIN($AM$3:$AM$64))>MAX($AM$3:$AM$64),$AN$2<$AM$2,$AL9<$AM$2,ABS($AL9-$AN$2)<=5,IFERROR(VALUE(MID('King Node Model'!$K$26,FIND(":",'King Node Model'!$K$26)-2,2)),0)>=19,IFERROR(INDEX('Level Engine'!$EJ$9:$EJ$55,MATCH($AL9,'Level Engine'!$AA$9:$AA$55,0)),0)=0,$AN$3>$AM$2)," ⟲rev","")&IF($AL9='King Node Model'!$F$24," ⟂","")&$DJ9&IF(IFERROR(INDEX('Level Engine'!$EN$9:$EN$55,MATCH($AL9,'Level Engine'!$AA$9:$AA$55,0)),0)=1," Ⓟ"&IF(AND(OR('King Node Model'!$A$8="Neg",N('Level Engine'!$BG$72)=1),IFERROR(INDEX('Level Engine'!$AN$9:$AN$55,MATCH($AL9,'Level Engine'!$AA$9:$AA$55,0)),0)<>1)," NO-REV",""),"")&IF(AND(ISNUMBER($AL9),OR(AND(ISNUMBER(SEARCH("chop edge",$E$45)),$AL9='King Node Model'!$AL$42),AND(ISNUMBER(SEARCH("chop edge",$E$46)),$AL9='King Node Model'!$AL$43),AND(ISNUMBER(SEARCH("chop edge",$E$52)),$AL9='King Node Model'!$AL$49),AND(ISNUMBER(SEARCH("chop edge",$E$53)),$AL9='King Node Model'!$AL$50)))," ⒸⒺ","")&IF(AND('Level Engine'!$GJ$4=1,OR($AL9='Level Engine'!$GJ$1,$AL9='Level Engine'!$GJ$2)),"","")&IF(ABS(N(IFERROR(INDEX('Level Engine'!$AE$9:$AE$55,MATCH($AL9,'Level Engine'!$AA$9:$AA$55,0)),0)))>='Level Engine'!$BG$85,IF(N(IFERROR(INDEX('Level Engine'!$AE$9:$AE$55,MATCH($AL9,'Level Engine'!$AA$9:$AA$55,0)),0))>0," Δ+"," Δ−"),"")&IFERROR(IF(AND(ISNUMBER(MATCH($AL9,'Level Engine'!$AA$9:$AA$55,0)),ABS(N(IFERROR(INDEX('Level Engine'!$AE$9:$AE$55,MATCH($AL9,'Level Engine'!$AA$9:$AA$55,0)),0)))<'Level Engine'!$BG$85,ABS(N(IFERROR(INDEX('Level Engine'!$AE$9:$AE$55,MATCH($AL9,'Level Engine'!$AA$9:$AA$55,0)),0)))<=ABS(N(IFERROR(INDEX('Level Engine'!$AE$9:$AE$55,MATCH($AL9+5,'Level Engine'!$AA$9:$AA$55,0)),0))),ABS(N(IFERROR(INDEX('Level Engine'!$AE$9:$AE$55,MATCH($AL9,'Level Engine'!$AA$9:$AA$55,0)),0)))<=ABS(N(IFERROR(INDEX('Level Engine'!$AE$9:$AE$55,MATCH($AL9-5,'Level Engine'!$AA$9:$AA$55,0)),0))),OR(AND(ABS(N(IFERROR(INDEX('Level Engine'!$AE$9:$AE$55,MATCH($AL9+5,'Level Engine'!$AA$9:$AA$55,0)),0)))>='Level Engine'!$BG$85,ABS(N(IFERROR(INDEX('Level Engine'!$AE$9:$AE$55,MATCH($AL9,'Level Engine'!$AA$9:$AA$55,0)),0)))<='Level Engine'!$BG$88*ABS(N(IFERROR(INDEX('Level Engine'!$AE$9:$AE$55,MATCH($AL9+5,'Level Engine'!$AA$9:$AA$55,0)),0)))),AND(ABS(N(IFERROR(INDEX('Level Engine'!$AE$9:$AE$55,MATCH($AL9-5,'Level Engine'!$AA$9:$AA$55,0)),0)))>='Level Engine'!$BG$85,ABS(N(IFERROR(INDEX('Level Engine'!$AE$9:$AE$55,MATCH($AL9,'Level Engine'!$AA$9:$AA$55,0)),0)))<='Level Engine'!$BG$88*ABS(N(IFERROR(INDEX('Level Engine'!$AE$9:$AE$55,MATCH($AL9-5,'Level Engine'!$AA$9:$AA$55,0)),0)))))),IF(AND('King Node Model'!$A$8="Pos",N('Level Engine'!$BG$72)<>1),""," ∅"),""),"")&IF(IFERROR(INDEX('Level Engine'!$JD$9:$JD$55,MATCH($AL9,'Level Engine'!$AA$9:$AA$55,0)),"")="P"," P-OI",IF(IFERROR(INDEX('Level Engine'!$JD$9:$JD$55,MATCH($AL9,'Level Engine'!$AA$9:$AA$55,0)),"")="C"," C-OI","")) -> 7855 | C9: =IF(AND(ISNUMBER($AM9),$AM9>0,ISNUMBER($AO9),$AO$1>0),REPT("█",ROUND($AO9/$AO$1*26,0)),"") -> █ | D9: =IF(NOT(ISNUMBER($AL9)),"",IF(IFERROR(INDEX('Level Engine'!$FS$9:$FS$55,MATCH($AL9,'Level Engine'!$AA$9:$AA$55,0)),0)=1,"⊙","")) | E9: Melt-up check | F9: FLOW SHIFT · off · C/P 1.42 → 1.08 · fires when C/P jumps from ≤ 1.00 to ≥ 1.20 within 15 min | AL9: ='King Node Model'!A35 -> 7855 | AM9: ='King Node Model'!C35 -> 75167 | AO9: ='King Node Model'!B35 -> 87098 | AY9: =IF(AND($B$2="Hide unsafe",$BB9=1),0,IF(AND(OR(AND(AND(ISNUMBER($AL9),OR(AND($AL9>=$AQ$22,$AL9<=$AR$22,$AS$22=1),$AL9=$AQ$22,$AL9=$AR$22,$AL9=$AQ$23,$AL9=$AR$23,$AL9=$AQ$24,$AL9=$AR$24),NOT(OR($AL9=$AN$5,$AL9=$AN$6,$AL9=$AN$7,$AL9=$AN$8,$AL9=$AN$10,$AL9=$AN$11))),NOT(OR(AND('King Node Model'!$P$13="Up",OR($AL9=$AQ$22,$AL9=$AQ$23,$AL9=$AQ$24,$AL9='King Node Model'!$AM$20,$AL9='King Node Model'!$AM$21,$AL9='King Node Model'!$AM$22),OR(AND('King Node Model'!$B$23-$AL9>=0,'King Node Model'!$B$23-$AL9<=5),AND('King Node Model'!$C$23-$AL9>=0,'King Node Model'!$C$23-$AL9<=5))),AND('King Node Model'!$P$13="Down",OR($AL9=$AR$22,$AL9=$AR$23,$AL9=$AR$24,$AL9='King Node Model'!$AN$20,$AL9='King Node Model'!$AN$21,$AL9='King Node Model'!$AN$22),OR(AND($AL9-'King Node Model'!$B$23>=0,$AL9-'King Node Model'!$B$23<=5),AND($AL9-'King Node Model'!$C$24>=0,$AL9-'King Node Model'!$C$24<=5)))))),AND(AND(ISNUMBER($AL9),OR(AND($AL9>=$AQ$22,$AL9<=$AR$22,$AS$22=1),$AL9=$AQ$22,$AL9=$AR$22,$AL9=$AQ$23,$AL9=$AR$23,$AL9=$AQ$24,$AL9=$AR$24,$AL9='King Node Model'!$AL$42,$AL9='King Node Model'!$AL$43),OR($AL9=$AN$5,$AL9=$AN$6,$AL9=$AN$7,$AL9=$AN$8,$AL9=$AN$10,$AL9=$AN$11)),NOT(OR(AND('King Node Model'!$P$13="Up",OR($AL9=$AQ$22,$AL9=$AQ$23,$AL9=$AQ$24,$AL9='King Node Model'!$AM$20,$AL9='King Node Model'!$AM$21,$AL9='King Node Model'!$AM$22),OR(AND('King Node Model'!$B$23-$AL9>=0,'King Node Model'!$B$23-$AL9<=5),AND('King Node Model'!$C$23-$AL9>=0,'King Node Model'!$C$23-$AL9<=5))),AND('King Node Model'!$P$13="Down",OR($AL9=$AR$22,$AL9=$AR$23,$AL9=$AR$24,$AL9='King Node Model'!$AN$20,$AL9='King Node Model'!$AN$21,$AL9='King Node Model'!$AN$22),OR(AND($AL9-'King Node Model'!$B$23>=0,$AL9-'King Node Model'!$B$23<=5),AND($AL9-'King Node Model'!$C$24>=0,$AL9-'King Node Model'!$C$24<=5)))))),AND(AND(ISNUMBER($AL9),OR(AND($AL9>='King Node Model'!$AM$20,$AL9<='King Node Model'!$AN$20,$AS$23=1),$AL9='King Node Model'!$AM$20,$AL9='King Node Model'!$AN$20,$AL9='King Node Model'!$AM$21,$AL9='King Node Model'!$AN$21,$AL9='King Node Model'!$AM$22,$AL9='King Node Model'!$AN$22),NOT(OR($AL9=$AN$5,$AL9=$AN$6,$AL9=$AN$7,$AL9=$AN$8,$AL9=$AN$10,$AL9=$AN$11))),NOT(AND(ISNUMBER('King Node Model'!$F$24),$AL9='King Node Model'!$F$24,IFERROR(INDEX('Level Engine'!$JN$9:$JN$55,MATCH($AL9,'Level Engine'!$AA$9:$AA$55,0)),0)<>1))),AND(AND(ISNUMBER($AL9),OR(AND($AL9>='King Node Model'!$AM$20,$AL9<='King Node Model'!$AN$20,$AS$23=1),$AL9='King Node Model'!$AM$20,$AL9='King Node Model'!$AN$20,$AL9='King Node Model'!$AM$21,$AL9='King Node Model'!$AN$21,$AL9='King Node Model'!$AM$22,$AL9='King Node Model'!$AN$22,$AL9='King Node Model'!$AL$49,$AL9='King Node Model'!$AL$50),OR($AL9=$AN$5,$AL9=$AN$6,$AL9=$AN$7,$AL9=$AN$8,$AL9=$AN$10,$AL9=$AN$11)),NOT(OR(AND('King Node Model'!$P$13="Up",OR($AL9=$AQ$22,$AL9=$AQ$23,$AL9=$AQ$24,$AL9='King Node Model'!$AM$20,$AL9='King Node Model'!$AM$21,$AL9='King Node Model'!$AM$22),OR(AND('King Node Model'!$B$23-$AL9>=0,'King Node Model'!$B$23-$AL9<=5),AND('King Node Model'!$C$23-$AL9>=0,'King Node Model'!$C$23-$AL9<=5))),AND('King Node Model'!$P$13="Down",OR($AL9=$AR$22,$AL9=$AR$23,$AL9=$AR$24,$AL9='King Node Model'!$AN$20,$AL9='King Node Model'!$AN$21,$AL9='King Node Model'!$AN$22),OR(AND($AL9-'King Node Model'!$B$23>=0,$AL9-'King Node Model'!$B$23<=5),AND($AL9-'King Node Model'!$C$24>=0,$AL9-'King Node Model'!$C$24<=5))))))),OR(COUNTIF('Level Engine'!$W$9:$W$14,$AL9)>0,COUNTIF('Level Engine'!$W$18:$W$23,$AL9)>0)),1,0)) -> 0 | AZ9: =IF($B$2="Hide unsafe",0,$BB9) -> 0 | BB9: =IF(OR(AND($AL9='King Node Model'!$AL$42,$AP$45<>"RASP"),AND($AL9='King Node Model'!$AL$43,$AP$46<>"RASP"),AND($AL9='King Node Model'!$AL$49,$AP$52<>"RASP"),AND($AL9='King Node Model'!$AL$50,$AP$53<>"RASP"),AND($AL9='King Node Model'!$AL$44,$AP$47<>"RASP"),AND($AL9='King Node Model'!$AL$51,$AP$54<>"RASP")),0,IF(AND(AND(ISNUMBER($AL9),OR(AND($AL9>=$AQ$22,$AL9<=$AR$22,$AP$45="RASP"),AND($AL9>=$AQ$23,$AL9<=$AR$23,$AP$46="RASP"),AND($AL9>=$AQ$24,$AL9<=$AR$24,$AP$47="RASP"),AND($AL9>='King Node Model'!$AM$20,$AL9<='King Node Model'!$AN$20,$AP$52="RASP",NOT($L$52=$AW$52)),AND($AL9='King Node Model'!$B$23,$AP$52="RASP",$L$52=$AW$52),AND($AL9>='King Node Model'!$AM$21,$AL9<='King Node Model'!$AN$21,$AP$53="RASP",NOT($L$53=$AW$53)),AND($AL9='King Node Model'!$B$23,$AP$53="RASP",$L$53=$AW$53),AND($AL9>='King Node Model'!$AM$22,$AL9<='King Node Model'!$AN$22,$AP$54="RASP"),AND($AL9>=IFERROR(INDEX('Level Engine'!$AT$9:$AT$55,MATCH('King Node Model'!$AL$42,'Level Engine'!$AA$9:$AA$55,0)),""),$AL9<=IFERROR(INDEX('Level Engine'!$AU$9:$AU$55,MATCH('King Node Model'!$AL$42,'Level Engine'!$AA$9:$AA$55,0)),""),$AP$45="RASP"),AND($AL9>=IFERROR(INDEX('Level Engine'!$AT$9:$AT$55,MATCH('King Node Model'!$AL$43,'Level Engine'!$AA$9:$AA$55,0)),""),$AL9<=IFERROR(INDEX('Level Engine'!$AU$9:$AU$55,MATCH('King Node Model'!$AL$43,'Level Engine'!$AA$9:$AA$55,0)),""),$AP$46="RASP"),AND($AL9>=IFERROR(INDEX('Level Engine'!$AT$9:$AT$55,MATCH('King Node Model'!$AL$44,'Level Engine'!$AA$9:$AA$55,0)),""),$AL9<=IFERROR(INDEX('Level Engine'!$AU$9:$AU$55,MATCH('King Node Model'!$AL$44,'Level Engine'!$AA$9:$AA$55,0)),""),$AP$47="RASP"),AND($AL9>=IFERROR(INDEX('Level Engine'!$AT$9:$AT$55,MATCH('King Node Model'!$AL$49,'Level Engine'!$AA$9:$AA$55,0)),""),$AL9<=IFERROR(INDEX('Level Engine'!$AU$9:$AU$55,MATCH('King Node Model'!$AL$49,'Level Engine'!$AA$9:$AA$55,0)),""),$AP$52="RASP",NOT($L$52=$AW$52)),AND($AL9>=IFERROR(INDEX('Level Engine'!$AT$9:$AT$55,MATCH('King Node Model'!$AL$50,'Level Engine'!$AA$9:$AA$55,0)),""),$AL9<=IFERROR(INDEX('Level Engine'!$AU$9:$AU$55,MATCH('King Node Model'!$AL$50,'Level Engine'!$AA$9:$AA$55,0)),""),$AP$53="RASP",NOT($L$53=$AW$53)),AND($AL9>=IFERROR(INDEX('Level Engine'!$AT$9:$AT$55,MATCH('King Node Model'!$AL$51,'Level Engine'!$AA$9:$AA$55,0)),""),$AL9<=IFERROR(INDEX('Level Engine'!$AU$9:$AU$55,MATCH('King Node Model'!$AL$51,'Level Engine'!$AA$9:$AA$55,0)),""),$AP$54="RASP"))),NOT(AND(ISNUMBER('King Node Model'!$F$24),$AL9='King Node Model'!$F$24,IFERROR(INDEX('Level Engine'!$JN$9:$JN$55,MATCH($AL9,'Level Engine'!$AA$9:$AA$55,0)),0)<>1,$AL9<>'King Node Model'!$AL$42,$AL9<>'King Node Model'!$AL$43,$AL9<>'King Node Model'!$AL$44,$AL9<>'King Node Model'!$AL$49,$AL9<>'King Node Model'!$AL$50,$AL9<>'King Node Model'!$AL$51))),1,0)) -> 0 | CO9: =IF(NOT(ISNUMBER($AL9)),"",IF(NOT(ISNUMBER(IFERROR(INDEX('Level Engine'!$FT$9:$FT$55,MATCH($AL9,'Level Engine'!$AA$9:$AA$55,0)),""))),"",IF(IFERROR(INDEX('Level Engine'!$FT$9:$FT$55,MATCH($AL9,'Level Engine'!$AA$9:$AA$55,0)),"")<0,0,2)+IF(ABS(IFERROR(INDEX('Level Engine'!$FT$9:$FT$55,MATCH($AL9,'Level Engine'!$AA$9:$AA$55,0)),""))>='Level Engine'!$FT$2,2,1))) -> 4 | DJ9: =IF(ISNUMBER($AL9),IF($AL9='Level Engine'!$BG$122," ⫪","")&IF($AL9='Level Engine'!$BG$118," S↑"&IFERROR(INDEX('Level Engine'!$MV$9:$MV$55,MATCH($AL9,'Level Engine'!$AA$9:$AA$55,0)),""),"")&IF($AL9='Level Engine'!$BG$119," S↓"&IFERROR(INDEX('Level Engine'!$MV$9:$MV$55,MATCH($AL9,'Level Engine'!$AA$9:$AA$55,0)),""),"")&IF($AL9='Level Engine'!$BG$120," D↑","")&IF($AL9='Level Engine'!$BG$121," D↓","")&IFERROR(INDEX('Level Engine'!$LG$9:$LG$55,MATCH($AL9,'Level Engine'!$AA$9:$AA$55,0)),"")&IF(IFERROR(INDEX('Level Engine'!$MA$9:$MA$55,MATCH($AL9,'Level Engine'!$AA$9:$AA$55,0)),0)=1," SAND","")&IF(IFERROR(INDEX('Level Engine'!$LM$9:$LM$55,MATCH($AL9,'Level Engine'!$AA$9:$AA$55,0)),0)>0," TP","")&IFERROR(" r"&MATCH($AL9,'Level Engine'!$W$9:$W$14,0),IFERROR(" s"&MATCH($AL9,'Level Engine'!$W$18:$W$23,0),""))&IF($AL9='Level Engine'!$BG$165," ◇","")&IF(N($DZ9)=1,IF($AL9>'Level Engine'!$BG$165," ⚠ DOM↓"," ⚠ DOM↑")&'Level Engine'!$BG$165,""),"") | DK9: =IF(AND(ISNUMBER($AL9),OR($AL9='King Node Model'!$AL$42,$AL9='King Node Model'!$AL$43,$AL9='King Node Model'!$AL$44)),IFERROR(MATCH($AL9,'Level Engine'!$W$9:$W$14,0),""),"") | DL9: =IF(AND(ISNUMBER($AL9),OR($AL9='King Node Model'!$AL$49,$AL9='King Node Model'!$AL$50,$AL9='King Node Model'!$AL$51)),IFERROR(MATCH($AL9,'Level Engine'!$W$18:$W$23,0),""),"") | DM9: =IF(AND(ISNUMBER($AL9),IFERROR(INDEX('Level Engine'!$LC$9:$LC$55,MATCH($AL9,'Level Engine'!$AA$9:$AA$55,0)),0)=1,OR($AL9=$AN$3,IFERROR(INDEX('Level Engine'!$LB$9:$LB$55,MATCH($AL9,'Level Engine'!$AA$9:$AA$55,0)),0)=1)),1,0) -> 0 | DZ9: =IF(ISNUMBER($AL9),IF(IFERROR(INDEX('Level Engine'!$NJ$9:$NJ$55,MATCH($AL9,'Level Engine'!$AA$9:$AA$55,0)),0)=1,1,0),0)
A10: =IF(AND(ISNUMBER($AM10),$AM10<0,ISNUMBER($AO10),$AO$1>0),REPT("█",ROUND($AO10/$AO$1*26,0)),"") | B10: =TEXT(IF(IF('Level Engine'!$GJ$4=1,$AL10='Level Engine'!$GJ$3,AND($AL10-$AM$2>-2.5,$AL10-$AM$2<=2.5)),$AM$2,$AL10),"0")&IF($AL10=$AN$1," ★","")&IF($AL10=$AN$2," ★","")&IF($AL10=$AN$3," ◆","")&IF(AND(ISNUMBER($AN$4),$AL10=$AN$4)," Ⓕ","")&IF(OR(AND(ISNUMBER('Level Engine'!$BG$87),$AL10='Level Engine'!$BG$87),AND(ISNUMBER('Level Engine'!$BG$105),$AL10='Level Engine'!$BG$105))," ζ","")&IF(AND(ISNUMBER($AN$35),$AL10=$AN$35)," ⓏⒼ","")&IF(OR($AL10='Level Engine'!$CP$4,$AL10='Level Engine'!$CP$5,$AL10='Level Engine'!$CP$6,$AL10='Level Engine'!$CP$7)," ☄","")&IF(OR($AL10=$AN$5,$AL10=$AN$8)," ║1","")&IF(OR($AL10=$AN$6,$AL10=$AN$10)," ║2","")&IF(OR($AL10=$AN$7,$AL10=$AN$11)," ║3","")&IF(OR($AL10=$AN$13,$AL10=$AN$16)," ▣1","")&IF(OR($AL10=$AN$14,$AL10=$AN$17)," ▣2","")&IF(OR($AL10=$AN$15,$AL10=$AN$18)," ▣3","")&IF(AND(NOT(OR(AND(ISNUMBER(SEARCH("chop edge",$E$45)),IFERROR(ABS($AL10-'King Node Model'!$AL$42)<=5,FALSE),NOT(ISNUMBER(SEARCH("UNSAFE",$L$45)))),AND(ISNUMBER(SEARCH("chop edge",$E$46)),IFERROR(ABS($AL10-'King Node Model'!$AL$43)<=5,FALSE),NOT(ISNUMBER(SEARCH("UNSAFE",$L$46)))),AND(ISNUMBER(SEARCH("chop edge",$E$52)),IFERROR(ABS($AL10-'King Node Model'!$AL$49)<=5,FALSE),NOT(ISNUMBER(SEARCH("UNSAFE",$L$52)))),AND(ISNUMBER(SEARCH("chop edge",$E$53)),IFERROR(ABS($AL10-'King Node Model'!$AL$50)<=5,FALSE),NOT(ISNUMBER(SEARCH("UNSAFE",$L$53)))))),OR(AND(IFERROR(INDEX('Level Engine'!$IB$9:$IB$55,MATCH('King Node Model'!$AL$49,'Level Engine'!$AA$9:$AA$55,0)),0)<>1,$AL10=IFERROR(INDEX('Level Engine'!$AU$9:$AU$55,MATCH('King Node Model'!$AL$49,'Level Engine'!$AA$9:$AA$55,0)),""),IFERROR(INDEX('Level Engine'!$AU$9:$AU$55,MATCH('King Node Model'!$AL$49,'Level Engine'!$AA$9:$AA$55,0)),"")<>IFERROR(INDEX('Level Engine'!$AT$9:$AT$55,MATCH('King Node Model'!$AL$49,'Level Engine'!$AA$9:$AA$55,0)),"")),AND(IFERROR(INDEX('Level Engine'!$IB$9:$IB$55,MATCH('King Node Model'!$AL$50,'Level Engine'!$AA$9:$AA$55,0)),0)<>1,$AL10=IFERROR(INDEX('Level Engine'!$AU$9:$AU$55,MATCH('King Node Model'!$AL$50,'Level Engine'!$AA$9:$AA$55,0)),""),IFERROR(INDEX('Level Engine'!$AU$9:$AU$55,MATCH('King Node Model'!$AL$50,'Level Engine'!$AA$9:$AA$55,0)),"")<>IFERROR(INDEX('Level Engine'!$AT$9:$AT$55,MATCH('King Node Model'!$AL$50,'Level Engine'!$AA$9:$AA$55,0)),"")))),IF(OR('King Node Model'!$A$8="Neg",N('Level Engine'!$BG$72)=1),""," ⒷⒽ"),"")&IF(AND(NOT(OR(AND(ISNUMBER(SEARCH("chop edge",$E$45)),IFERROR(ABS($AL10-'King Node Model'!$AL$42)<=5,FALSE),NOT(ISNUMBER(SEARCH("UNSAFE",$L$45)))),AND(ISNUMBER(SEARCH("chop edge",$E$46)),IFERROR(ABS($AL10-'King Node Model'!$AL$43)<=5,FALSE),NOT(ISNUMBER(SEARCH("UNSAFE",$L$46)))),AND(ISNUMBER(SEARCH("chop edge",$E$52)),IFERROR(ABS($AL10-'King Node Model'!$AL$49)<=5,FALSE),NOT(ISNUMBER(SEARCH("UNSAFE",$L$52)))),AND(ISNUMBER(SEARCH("chop edge",$E$53)),IFERROR(ABS($AL10-'King Node Model'!$AL$50)<=5,FALSE),NOT(ISNUMBER(SEARCH("UNSAFE",$L$53)))))),OR(AND(IFERROR(INDEX('Level Engine'!$IB$9:$IB$55,MATCH('King Node Model'!$AL$42,'Level Engine'!$AA$9:$AA$55,0)),0)<>1,$AL10=IFERROR(INDEX('Level Engine'!$AT$9:$AT$55,MATCH('King Node Model'!$AL$42,'Level Engine'!$AA$9:$AA$55,0)),""),IFERROR(INDEX('Level Engine'!$AT$9:$AT$55,MATCH('King Node Model'!$AL$42,'Level Engine'!$AA$9:$AA$55,0)),"")<>IFERROR(INDEX('Level Engine'!$AU$9:$AU$55,MATCH('King Node Model'!$AL$42,'Level Engine'!$AA$9:$AA$55,0)),"")),AND(IFERROR(INDEX('Level Engine'!$IB$9:$IB$55,MATCH('King Node Model'!$AL$43,'Level Engine'!$AA$9:$AA$55,0)),0)<>1,$AL10=IFERROR(INDEX('Level Engine'!$AT$9:$AT$55,MATCH('King Node Model'!$AL$43,'Level Engine'!$AA$9:$AA$55,0)),""),IFERROR(INDEX('Level Engine'!$AT$9:$AT$55,MATCH('King Node Model'!$AL$43,'Level Engine'!$AA$9:$AA$55,0)),"")<>IFERROR(INDEX('Level Engine'!$AU$9:$AU$55,MATCH('King Node Model'!$AL$43,'Level Engine'!$AA$9:$AA$55,0)),"")))),IF(OR('King Node Model'!$A$8="Neg",N('Level Engine'!$BG$72)=1),""," ⒷⓁ"),"")&IF(OR(AND($AL10>='King Node Model'!$AM$17,$AL10<='King Node Model'!$AN$17,$AP$45="RASP"),AND($AL10>='King Node Model'!$AM$18,$AL10<='King Node Model'!$AN$18,$AP$46="RASP"),AND($AL10>='King Node Model'!$AM$19,$AL10<='King Node Model'!$AN$19,$AP$47="RASP"),AND($AL10>='King Node Model'!$AM$20,$AL10<='King Node Model'!$AN$20,$AP$52="RASP"),AND($AL10>='King Node Model'!$AM$21,$AL10<='King Node Model'!$AN$21,$AP$53="RASP"),AND($AL10>='King Node Model'!$AM$22,$AL10<='King Node Model'!$AN$22,$AP$54="RASP")),"","")&IF(IF('Level Engine'!$GJ$4=1,$AL10='Level Engine'!$GJ$3,AND($AL10-$AM$2>-2.5,$AL10-$AM$2<=2.5))," ◄","")&IF(IFERROR(INDEX('Level Engine'!$GV$9:$GV$55,MATCH($AL10,'Level Engine'!$AA$9:$AA$55,0)),0)=1," Ⓥ"&IF(IFERROR(INDEX('Level Engine'!$ET$9:$ET$55,MATCH($AL10,'Level Engine'!$AA$9:$AA$55,0)),0)=1,"+",""),"")&IF(OR(AND($AL10=$AN$38,IFERROR(INDEX('Level Engine'!$AN$9:$AN$55,MATCH($AL10,'Level Engine'!$AA$9:$AA$55,0)),0)<>1),$AL10=$AN$39)," ⊙","")&IF(AND(OR('King Node Model'!$A$8="Neg",N('Level Engine'!$BG$72)=1),ABS(MIN($AM$3:$AM$64))>MAX($AM$3:$AM$64),$AN$2<$AM$2,$AL10<$AM$2,ABS($AL10-$AN$2)<=5,IFERROR(VALUE(MID('King Node Model'!$K$26,FIND(":",'King Node Model'!$K$26)-2,2)),0)>=19,IFERROR(INDEX('Level Engine'!$EJ$9:$EJ$55,MATCH($AL10,'Level Engine'!$AA$9:$AA$55,0)),0)=0,$AN$3>$AM$2)," ⟲rev","")&IF($AL10='King Node Model'!$F$24," ⟂","")&$DJ10&IF(IFERROR(INDEX('Level Engine'!$EN$9:$EN$55,MATCH($AL10,'Level Engine'!$AA$9:$AA$55,0)),0)=1," Ⓟ"&IF(AND(OR('King Node Model'!$A$8="Neg",N('Level Engine'!$BG$72)=1),IFERROR(INDEX('Level Engine'!$AN$9:$AN$55,MATCH($AL10,'Level Engine'!$AA$9:$AA$55,0)),0)<>1)," NO-REV",""),"")&IF(AND(ISNUMBER($AL10),OR(AND(ISNUMBER(SEARCH("chop edge",$E$45)),$AL10='King Node Model'!$AL$42),AND(ISNUMBER(SEARCH("chop edge",$E$46)),$AL10='King Node Model'!$AL$43),AND(ISNUMBER(SEARCH("chop edge",$E$52)),$AL10='King Node Model'!$AL$49),AND(ISNUMBER(SEARCH("chop edge",$E$53)),$AL10='King Node Model'!$AL$50)))," ⒸⒺ","")&IF(AND('Level Engine'!$GJ$4=1,OR($AL10='Level Engine'!$GJ$1,$AL10='Level Engine'!$GJ$2)),"","")&IF(ABS(N(IFERROR(INDEX('Level Engine'!$AE$9:$AE$55,MATCH($AL10,'Level Engine'!$AA$9:$AA$55,0)),0)))>='Level Engine'!$BG$85,IF(N(IFERROR(INDEX('Level Engine'!$AE$9:$AE$55,MATCH($AL10,'Level Engine'!$AA$9:$AA$55,0)),0))>0," Δ+"," Δ−"),"")&IFERROR(IF(AND(ISNUMBER(MATCH($AL10,'Level Engine'!$AA$9:$AA$55,0)),ABS(N(IFERROR(INDEX('Level Engine'!$AE$9:$AE$55,MATCH($AL10,'Level Engine'!$AA$9:$AA$55,0)),0)))<'Level Engine'!$BG$85,ABS(N(IFERROR(INDEX('Level Engine'!$AE$9:$AE$55,MATCH($AL10,'Level Engine'!$AA$9:$AA$55,0)),0)))<=ABS(N(IFERROR(INDEX('Level Engine'!$AE$9:$AE$55,MATCH($AL10+5,'Level Engine'!$AA$9:$AA$55,0)),0))),ABS(N(IFERROR(INDEX('Level Engine'!$AE$9:$AE$55,MATCH($AL10,'Level Engine'!$AA$9:$AA$55,0)),0)))<=ABS(N(IFERROR(INDEX('Level Engine'!$AE$9:$AE$55,MATCH($AL10-5,'Level Engine'!$AA$9:$AA$55,0)),0))),OR(AND(ABS(N(IFERROR(INDEX('Level Engine'!$AE$9:$AE$55,MATCH($AL10+5,'Level Engine'!$AA$9:$AA$55,0)),0)))>='Level Engine'!$BG$85,ABS(N(IFERROR(INDEX('Level Engine'!$AE$9:$AE$55,MATCH($AL10,'Level Engine'!$AA$9:$AA$55,0)),0)))<='Level Engine'!$BG$88*ABS(N(IFERROR(INDEX('Level Engine'!$AE$9:$AE$55,MATCH($AL10+5,'Level Engine'!$AA$9:$AA$55,0)),0)))),AND(ABS(N(IFERROR(INDEX('Level Engine'!$AE$9:$AE$55,MATCH($AL10-5,'Level Engine'!$AA$9:$AA$55,0)),0)))>='Level Engine'!$BG$85,ABS(N(IFERROR(INDEX('Level Engine'!$AE$9:$AE$55,MATCH($AL10,'Level Engine'!$AA$9:$AA$55,0)),0)))<='Level Engine'!$BG$88*ABS(N(IFERROR(INDEX('Level Engine'!$AE$9:$AE$55,MATCH($AL10-5,'Level Engine'!$AA$9:$AA$55,0)),0)))))),IF(AND('King Node Model'!$A$8="Pos",N('Level Engine'!$BG$72)<>1),""," ∅"),""),"")&IF(IFERROR(INDEX('Level Engine'!$JD$9:$JD$55,MATCH($AL10,'Level Engine'!$AA$9:$AA$55,0)),"")="P"," P-OI",IF(IFERROR(INDEX('Level Engine'!$JD$9:$JD$55,MATCH($AL10,'Level Engine'!$AA$9:$AA$55,0)),"")="C"," C-OI","")) -> 7850 ▣1 P-OI | C10: =IF(AND(ISNUMBER($AM10),$AM10>0,ISNUMBER($AO10),$AO$1>0),REPT("█",ROUND($AO10/$AO$1*26,0)),"") -> ██ | D10: =IF(NOT(ISNUMBER($AL10)),"",IF(IFERROR(INDEX('Level Engine'!$FS$9:$FS$55,MATCH($AL10,'Level Engine'!$AA$9:$AA$55,0)),0)=1,"⊙","")) | E10: Phenomenon | F10: ='King Node Model'!C11&IF(ISNUMBER(SEARCH("Long Gamma Compression — Reinforced",'King Node Model'!C11))," · Drift bias UP (11 of 14 sessions, pullbacks expected) · monitor DEX for guidance",IF(ISNUMBER(SEARCH("Two-Way Long-Gamma Vol Compression",'King Node Model'!C11))," · Drift bias unclear (7 of 12 sessions up, wide range) · monitor DEX for guidance","")) -> Low-Vol Grind-Up / Melt-Up — Dealers Comfortable with Upside Drift | Q10: IV MATRIX | AL10: ='King Node Model'!A36 -> 7850 | AM10: ='King Node Model'!C36 -> 214075 | AN10: ='King Node Model'!T29 -> 7775 | AO10: ='King Node Model'!B36 -> 351467 | AY10: =IF(AND($B$2="Hide unsafe",$BB10=1),0,IF(AND(OR(AND(AND(ISNUMBER($AL10),OR(AND($AL10>=$AQ$22,$AL10<=$AR$22,$AS$22=1),$AL10=$AQ$22,$AL10=$AR$22,$AL10=$AQ$23,$AL10=$AR$23,$AL10=$AQ$24,$AL10=$AR$24),NOT(OR($AL10=$AN$5,$AL10=$AN$6,$AL10=$AN$7,$AL10=$AN$8,$AL10=$AN$10,$AL10=$AN$11))),NOT(OR(AND('King Node Model'!$P$13="Up",OR($AL10=$AQ$22,$AL10=$AQ$23,$AL10=$AQ$24,$AL10='King Node Model'!$AM$20,$AL10='King Node Model'!$AM$21,$AL10='King Node Model'!$AM$22),OR(AND('King Node Model'!$B$23-$AL10>=0,'King Node Model'!$B$23-$AL10<=5),AND('King Node Model'!$C$23-$AL10>=0,'King Node Model'!$C$23-$AL10<=5))),AND('King Node Model'!$P$13="Down",OR($AL10=$AR$22,$AL10=$AR$23,$AL10=$AR$24,$AL10='King Node Model'!$AN$20,$AL10='King Node Model'!$AN$21,$AL10='King Node Model'!$AN$22),OR(AND($AL10-'King Node Model'!$B$23>=0,$AL10-'King Node Model'!$B$23<=5),AND($AL10-'King Node Model'!$C$24>=0,$AL10-'King Node Model'!$C$24<=5)))))),AND(AND(ISNUMBER($AL10),OR(AND($AL10>=$AQ$22,$AL10<=$AR$22,$AS$22=1),$AL10=$AQ$22,$AL10=$AR$22,$AL10=$AQ$23,$AL10=$AR$23,$AL10=$AQ$24,$AL10=$AR$24,$AL10='King Node Model'!$AL$42,$AL10='King Node Model'!$AL$43),OR($AL10=$AN$5,$AL10=$AN$6,$AL10=$AN$7,$AL10=$AN$8,$AL10=$AN$10,$AL10=$AN$11)),NOT(OR(AND('King Node Model'!$P$13="Up",OR($AL10=$AQ$22,$AL10=$AQ$23,$AL10=$AQ$24,$AL10='King Node Model'!$AM$20,$AL10='King Node Model'!$AM$21,$AL10='King Node Model'!$AM$22),OR(AND('King Node Model'!$B$23-$AL10>=0,'King Node Model'!$B$23-$AL10<=5),AND('King Node Model'!$C$23-$AL10>=0,'King Node Model'!$C$23-$AL10<=5))),AND('King Node Model'!$P$13="Down",OR($AL10=$AR$22,$AL10=$AR$23,$AL10=$AR$24,$AL10='King Node Model'!$AN$20,$AL10='King Node Model'!$AN$21,$AL10='King Node Model'!$AN$22),OR(AND($AL10-'King Node Model'!$B$23>=0,$AL10-'King Node Model'!$B$23<=5),AND($AL10-'King Node Model'!$C$24>=0,$AL10-'King Node Model'!$C$24<=5)))))),AND(AND(ISNUMBER($AL10),OR(AND($AL10>='King Node Model'!$AM$20,$AL10<='King Node Model'!$AN$20,$AS$23=1),$AL10='King Node Model'!$AM$20,$AL10='King Node Model'!$AN$20,$AL10='King Node Model'!$AM$21,$AL10='King Node Model'!$AN$21,$AL10='King Node Model'!$AM$22,$AL10='King Node Model'!$AN$22),NOT(OR($AL10=$AN$5,$AL10=$AN$6,$AL10=$AN$7,$AL10=$AN$8,$AL10=$AN$10,$AL10=$AN$11))),NOT(AND(ISNUMBER('King Node Model'!$F$24),$AL10='King Node Model'!$F$24,IFERROR(INDEX('Level Engine'!$JN$9:$JN$55,MATCH($AL10,'Level Engine'!$AA$9:$AA$55,0)),0)<>1))),AND(AND(ISNUMBER($AL10),OR(AND($AL10>='King Node Model'!$AM$20,$AL10<='King Node Model'!$AN$20,$AS$23=1),$AL10='King Node Model'!$AM$20,$AL10='King Node Model'!$AN$20,$AL10='King Node Model'!$AM$21,$AL10='King Node Model'!$AN$21,$AL10='King Node Model'!$AM$22,$AL10='King Node Model'!$AN$22,$AL10='King Node Model'!$AL$49,$AL10='King Node Model'!$AL$50),OR($AL10=$AN$5,$AL10=$AN$6,$AL10=$AN$7,$AL10=$AN$8,$AL10=$AN$10,$AL10=$AN$11)),NOT(OR(AND('King Node Model'!$P$13="Up",OR($AL10=$AQ$22,$AL10=$AQ$23,$AL10=$AQ$24,$AL10='King Node Model'!$AM$20,$AL10='King Node Model'!$AM$21,$AL10='King Node Model'!$AM$22),OR(AND('King Node Model'!$B$23-$AL10>=0,'King Node Model'!$B$23-$AL10<=5),AND('King Node Model'!$C$23-$AL10>=0,'King Node Model'!$C$23-$AL10<=5))),AND('King Node Model'!$P$13="Down",OR($AL10=$AR$22,$AL10=$AR$23,$AL10=$AR$24,$AL10='King Node Model'!$AN$20,$AL10='King Node Model'!$AN$21,$AL10='King Node Model'!$AN$22),OR(AND($AL10-'King Node Model'!$B$23>=0,$AL10-'King Node Model'!$B$23<=5),AND($AL10-'King Node Model'!$C$24>=0,$AL10-'King Node Model'!$C$24<=5))))))),OR(COUNTIF('Level Engine'!$W$9:$W$14,$AL10)>0,COUNTIF('Level Engine'!$W$18:$W$23,$AL10)>0)),1,0)) -> 0 | AZ10: =IF($B$2="Hide unsafe",0,$BB10) -> 0 | BB10: =IF(OR(AND($AL10='King Node Model'!$AL$42,$AP$45<>"RASP"),AND($AL10='King Node Model'!$AL$43,$AP$46<>"RASP"),AND($AL10='King Node Model'!$AL$49,$AP$52<>"RASP"),AND($AL10='King Node Model'!$AL$50,$AP$53<>"RASP"),AND($AL10='King Node Model'!$AL$44,$AP$47<>"RASP"),AND($AL10='King Node Model'!$AL$51,$AP$54<>"RASP")),0,IF(AND(AND(ISNUMBER($AL10),OR(AND($AL10>=$AQ$22,$AL10<=$AR$22,$AP$45="RASP"),AND($AL10>=$AQ$23,$AL10<=$AR$23,$AP$46="RASP"),AND($AL10>=$AQ$24,$AL10<=$AR$24,$AP$47="RASP"),AND($AL10>='King Node Model'!$AM$20,$AL10<='King Node Model'!$AN$20,$AP$52="RASP",NOT($L$52=$AW$52)),AND($AL10='King Node Model'!$B$23,$AP$52="RASP",$L$52=$AW$52),AND($AL10>='King Node Model'!$AM$21,$AL10<='King Node Model'!$AN$21,$AP$53="RASP",NOT($L$53=$AW$53)),AND($AL10='King Node Model'!$B$23,$AP$53="RASP",$L$53=$AW$53),AND($AL10>='King Node Model'!$AM$22,$AL10<='King Node Model'!$AN$22,$AP$54="RASP"),AND($AL10>=IFERROR(INDEX('Level Engine'!$AT$9:$AT$55,MATCH('King Node Model'!$AL$42,'Level Engine'!$AA$9:$AA$55,0)),""),$AL10<=IFERROR(INDEX('Level Engine'!$AU$9:$AU$55,MATCH('King Node Model'!$AL$42,'Level Engine'!$AA$9:$AA$55,0)),""),$AP$45="RASP"),AND($AL10>=IFERROR(INDEX('Level Engine'!$AT$9:$AT$55,MATCH('King Node Model'!$AL$43,'Level Engine'!$AA$9:$AA$55,0)),""),$AL10<=IFERROR(INDEX('Level Engine'!$AU$9:$AU$55,MATCH('King Node Model'!$AL$43,'Level Engine'!$AA$9:$AA$55,0)),""),$AP$46="RASP"),AND($AL10>=IFERROR(INDEX('Level Engine'!$AT$9:$AT$55,MATCH('King Node Model'!$AL$44,'Level Engine'!$AA$9:$AA$55,0)),""),$AL10<=IFERROR(INDEX('Level Engine'!$AU$9:$AU$55,MATCH('King Node Model'!$AL$44,'Level Engine'!$AA$9:$AA$55,0)),""),$AP$47="RASP"),AND($AL10>=IFERROR(INDEX('Level Engine'!$AT$9:$AT$55,MATCH('King Node Model'!$AL$49,'Level Engine'!$AA$9:$AA$55,0)),""),$AL10<=IFERROR(INDEX('Level Engine'!$AU$9:$AU$55,MATCH('King Node Model'!$AL$49,'Level Engine'!$AA$9:$AA$55,0)),""),$AP$52="RASP",NOT($L$52=$AW$52)),AND($AL10>=IFERROR(INDEX('Level Engine'!$AT$9:$AT$55,MATCH('King Node Model'!$AL$50,'Level Engine'!$AA$9:$AA$55,0)),""),$AL10<=IFERROR(INDEX('Level Engine'!$AU$9:$AU$55,MATCH('King Node Model'!$AL$50,'Level Engine'!$AA$9:$AA$55,0)),""),$AP$53="RASP",NOT($L$53=$AW$53)),AND($AL10>=IFERROR(INDEX('Level Engine'!$AT$9:$AT$55,MATCH('King Node Model'!$AL$51,'Level Engine'!$AA$9:$AA$55,0)),""),$AL10<=IFERROR(INDEX('Level Engine'!$AU$9:$AU$55,MATCH('King Node Model'!$AL$51,'Level Engine'!$AA$9:$AA$55,0)),""),$AP$54="RASP"))),NOT(AND(ISNUMBER('King Node Model'!$F$24),$AL10='King Node Model'!$F$24,IFERROR(INDEX('Level Engine'!$JN$9:$JN$55,MATCH($AL10,'Level Engine'!$AA$9:$AA$55,0)),0)<>1,$AL10<>'King Node Model'!$AL$42,$AL10<>'King Node Model'!$AL$43,$AL10<>'King Node Model'!$AL$44,$AL10<>'King Node Model'!$AL$49,$AL10<>'King Node Model'!$AL$50,$AL10<>'King Node Model'!$AL$51))),1,0)) -> 0 | CO10: =IF(NOT(ISNUMBER($AL10)),"",IF(NOT(ISNUMBER(IFERROR(INDEX('Level Engine'!$FT$9:$FT$55,MATCH($AL10,'Level Engine'!$AA$9:$AA$55,0)),""))),"",IF(IFERROR(INDEX('Level Engine'!$FT$9:$FT$55,MATCH($AL10,'Level Engine'!$AA$9:$AA$55,0)),"")<0,0,2)+IF(ABS(IFERROR(INDEX('Level Engine'!$FT$9:$FT$55,MATCH($AL10,'Level Engine'!$AA$9:$AA$55,0)),""))>='Level Engine'!$FT$2,2,1))) -> 4 | DJ10: =IF(ISNUMBER($AL10),IF($AL10='Level Engine'!$BG$122," ⫪","")&IF($AL10='Level Engine'!$BG$118," S↑"&IFERROR(INDEX('Level Engine'!$MV$9:$MV$55,MATCH($AL10,'Level Engine'!$AA$9:$AA$55,0)),""),"")&IF($AL10='Level Engine'!$BG$119," S↓"&IFERROR(INDEX('Level Engine'!$MV$9:$MV$55,MATCH($AL10,'Level Engine'!$AA$9:$AA$55,0)),""),"")&IF($AL10='Level Engine'!$BG$120," D↑","")&IF($AL10='Level Engine'!$BG$121," D↓","")&IFERROR(INDEX('Level Engine'!$LG$9:$LG$55,MATCH($AL10,'Level Engine'!$AA$9:$AA$55,0)),"")&IF(IFERROR(INDEX('Level Engine'!$MA$9:$MA$55,MATCH($AL10,'Level Engine'!$AA$9:$AA$55,0)),0)=1," SAND","")&IF(IFERROR(INDEX('Level Engine'!$LM$9:$LM$55,MATCH($AL10,'Level Engine'!$AA$9:$AA$55,0)),0)>0," TP","")&IFERROR(" r"&MATCH($AL10,'Level Engine'!$W$9:$W$14,0),IFERROR(" s"&MATCH($AL10,'Level Engine'!$W$18:$W$23,0),""))&IF($AL10='Level Engine'!$BG$165," ◇","")&IF(N($DZ10)=1,IF($AL10>'Level Engine'!$BG$165," ⚠ DOM↓"," ⚠ DOM↑")&'Level Engine'!$BG$165,""),"") | DK10: =IF(AND(ISNUMBER($AL10),OR($AL10='King Node Model'!$AL$42,$AL10='King Node Model'!$AL$43,$AL10='King Node Model'!$AL$44)),IFERROR(MATCH($AL10,'Level Engine'!$W$9:$W$14,0),""),"") | DL10: =IF(AND(ISNUMBER($AL10),OR($AL10='King Node Model'!$AL$49,$AL10='King Node Model'!$AL$50,$AL10='King Node Model'!$AL$51)),IFERROR(MATCH($AL10,'Level Engine'!$W$18:$W$23,0),""),"") | DM10: =IF(AND(ISNUMBER($AL10),IFERROR(INDEX('Level Engine'!$LC$9:$LC$55,MATCH($AL10,'Level Engine'!$AA$9:$AA$55,0)),0)=1,OR($AL10=$AN$3,IFERROR(INDEX('Level Engine'!$LB$9:$LB$55,MATCH($AL10,'Level Engine'!$AA$9:$AA$55,0)),0)=1)),1,0) -> 0 | DZ10: =IF(ISNUMBER($AL10),IF(IFERROR(INDEX('Level Engine'!$NJ$9:$NJ$55,MATCH($AL10,'Level Engine'!$AA$9:$AA$55,0)),0)=1,1,0),0)
A11: =IF(AND(ISNUMBER($AM11),$AM11<0,ISNUMBER($AO11),$AO$1>0),REPT("█",ROUND($AO11/$AO$1*26,0)),"") | B11: =TEXT(IF(IF('Level Engine'!$GJ$4=1,$AL11='Level Engine'!$GJ$3,AND($AL11-$AM$2>-2.5,$AL11-$AM$2<=2.5)),$AM$2,$AL11),"0")&IF($AL11=$AN$1," ★","")&IF($AL11=$AN$2," ★","")&IF($AL11=$AN$3," ◆","")&IF(AND(ISNUMBER($AN$4),$AL11=$AN$4)," Ⓕ","")&IF(OR(AND(ISNUMBER('Level Engine'!$BG$87),$AL11='Level Engine'!$BG$87),AND(ISNUMBER('Level Engine'!$BG$105),$AL11='Level Engine'!$BG$105))," ζ","")&IF(AND(ISNUMBER($AN$35),$AL11=$AN$35)," ⓏⒼ","")&IF(OR($AL11='Level Engine'!$CP$4,$AL11='Level Engine'!$CP$5,$AL11='Level Engine'!$CP$6,$AL11='Level Engine'!$CP$7)," ☄","")&IF(OR($AL11=$AN$5,$AL11=$AN$8)," ║1","")&IF(OR($AL11=$AN$6,$AL11=$AN$10)," ║2","")&IF(OR($AL11=$AN$7,$AL11=$AN$11)," ║3","")&IF(OR($AL11=$AN$13,$AL11=$AN$16)," ▣1","")&IF(OR($AL11=$AN$14,$AL11=$AN$17)," ▣2","")&IF(OR($AL11=$AN$15,$AL11=$AN$18)," ▣3","")&IF(AND(NOT(OR(AND(ISNUMBER(SEARCH("chop edge",$E$45)),IFERROR(ABS($AL11-'King Node Model'!$AL$42)<=5,FALSE),NOT(ISNUMBER(SEARCH("UNSAFE",$L$45)))),AND(ISNUMBER(SEARCH("chop edge",$E$46)),IFERROR(ABS($AL11-'King Node Model'!$AL$43)<=5,FALSE),NOT(ISNUMBER(SEARCH("UNSAFE",$L$46)))),AND(ISNUMBER(SEARCH("chop edge",$E$52)),IFERROR(ABS($AL11-'King Node Model'!$AL$49)<=5,FALSE),NOT(ISNUMBER(SEARCH("UNSAFE",$L$52)))),AND(ISNUMBER(SEARCH("chop edge",$E$53)),IFERROR(ABS($AL11-'King Node Model'!$AL$50)<=5,FALSE),NOT(ISNUMBER(SEARCH("UNSAFE",$L$53)))))),OR(AND(IFERROR(INDEX('Level Engine'!$IB$9:$IB$55,MATCH('King Node Model'!$AL$49,'Level Engine'!$AA$9:$AA$55,0)),0)<>1,$AL11=IFERROR(INDEX('Level Engine'!$AU$9:$AU$55,MATCH('King Node Model'!$AL$49,'Level Engine'!$AA$9:$AA$55,0)),""),IFERROR(INDEX('Level Engine'!$AU$9:$AU$55,MATCH('King Node Model'!$AL$49,'Level Engine'!$AA$9:$AA$55,0)),"")<>IFERROR(INDEX('Level Engine'!$AT$9:$AT$55,MATCH('King Node Model'!$AL$49,'Level Engine'!$AA$9:$AA$55,0)),"")),AND(IFERROR(INDEX('Level Engine'!$IB$9:$IB$55,MATCH('King Node Model'!$AL$50,'Level Engine'!$AA$9:$AA$55,0)),0)<>1,$AL11=IFERROR(INDEX('Level Engine'!$AU$9:$AU$55,MATCH('King Node Model'!$AL$50,'Level Engine'!$AA$9:$AA$55,0)),""),IFERROR(INDEX('Level Engine'!$AU$9:$AU$55,MATCH('King Node Model'!$AL$50,'Level Engine'!$AA$9:$AA$55,0)),"")<>IFERROR(INDEX('Level Engine'!$AT$9:$AT$55,MATCH('King Node Model'!$AL$50,'Level Engine'!$AA$9:$AA$55,0)),"")))),IF(OR('King Node Model'!$A$8="Neg",N('Level Engine'!$BG$72)=1),""," ⒷⒽ"),"")&IF(AND(NOT(OR(AND(ISNUMBER(SEARCH("chop edge",$E$45)),IFERROR(ABS($AL11-'King Node Model'!$AL$42)<=5,FALSE),NOT(ISNUMBER(SEARCH("UNSAFE",$L$45)))),AND(ISNUMBER(SEARCH("chop edge",$E$46)),IFERROR(ABS($AL11-'King Node Model'!$AL$43)<=5,FALSE),NOT(ISNUMBER(SEARCH("UNSAFE",$L$46)))),AND(ISNUMBER(SEARCH("chop edge",$E$52)),IFERROR(ABS($AL11-'King Node Model'!$AL$49)<=5,FALSE),NOT(ISNUMBER(SEARCH("UNSAFE",$L$52)))),AND(ISNUMBER(SEARCH("chop edge",$E$53)),IFERROR(ABS($AL11-'King Node Model'!$AL$50)<=5,FALSE),NOT(ISNUMBER(SEARCH("UNSAFE",$L$53)))))),OR(AND(IFERROR(INDEX('Level Engine'!$IB$9:$IB$55,MATCH('King Node Model'!$AL$42,'Level Engine'!$AA$9:$AA$55,0)),0)<>1,$AL11=IFERROR(INDEX('Level Engine'!$AT$9:$AT$55,MATCH('King Node Model'!$AL$42,'Level Engine'!$AA$9:$AA$55,0)),""),IFERROR(INDEX('Level Engine'!$AT$9:$AT$55,MATCH('King Node Model'!$AL$42,'Level Engine'!$AA$9:$AA$55,0)),"")<>IFERROR(INDEX('Level Engine'!$AU$9:$AU$55,MATCH('King Node Model'!$AL$42,'Level Engine'!$AA$9:$AA$55,0)),"")),AND(IFERROR(INDEX('Level Engine'!$IB$9:$IB$55,MATCH('King Node Model'!$AL$43,'Level Engine'!$AA$9:$AA$55,0)),0)<>1,$AL11=IFERROR(INDEX('Level Engine'!$AT$9:$AT$55,MATCH('King Node Model'!$AL$43,'Level Engine'!$AA$9:$AA$55,0)),""),IFERROR(INDEX('Level Engine'!$AT$9:$AT$55,MATCH('King Node Model'!$AL$43,'Level Engine'!$AA$9:$AA$55,0)),"")<>IFERROR(INDEX('Level Engine'!$AU$9:$AU$55,MATCH('King Node Model'!$AL$43,'Level Engine'!$AA$9:$AA$55,0)),"")))),IF(OR('King Node Model'!$A$8="Neg",N('Level Engine'!$BG$72)=1),""," ⒷⓁ"),"")&IF(OR(AND($AL11>='King Node Model'!$AM$17,$AL11<='King Node Model'!$AN$17,$AP$45="RASP"),AND($AL11>='King Node Model'!$AM$18,$AL11<='King Node Model'!$AN$18,$AP$46="RASP"),AND($AL11>='King Node Model'!$AM$19,$AL11<='King Node Model'!$AN$19,$AP$47="RASP"),AND($AL11>='King Node Model'!$AM$20,$AL11<='King Node Model'!$AN$20,$AP$52="RASP"),AND($AL11>='King Node Model'!$AM$21,$AL11<='King Node Model'!$AN$21,$AP$53="RASP"),AND($AL11>='King Node Model'!$AM$22,$AL11<='King Node Model'!$AN$22,$AP$54="RASP")),"","")&IF(IF('Level Engine'!$GJ$4=1,$AL11='Level Engine'!$GJ$3,AND($AL11-$AM$2>-2.5,$AL11-$AM$2<=2.5))," ◄","")&IF(IFERROR(INDEX('Level Engine'!$GV$9:$GV$55,MATCH($AL11,'Level Engine'!$AA$9:$AA$55,0)),0)=1," Ⓥ"&IF(IFERROR(INDEX('Level Engine'!$ET$9:$ET$55,MATCH($AL11,'Level Engine'!$AA$9:$AA$55,0)),0)=1,"+",""),"")&IF(OR(AND($AL11=$AN$38,IFERROR(INDEX('Level Engine'!$AN$9:$AN$55,MATCH($AL11,'Level Engine'!$AA$9:$AA$55,0)),0)<>1),$AL11=$AN$39)," ⊙","")&IF(AND(OR('King Node Model'!$A$8="Neg",N('Level Engine'!$BG$72)=1),ABS(MIN($AM$3:$AM$64))>MAX($AM$3:$AM$64),$AN$2<$AM$2,$AL11<$AM$2,ABS($AL11-$AN$2)<=5,IFERROR(VALUE(MID('King Node Model'!$K$26,FIND(":",'King Node Model'!$K$26)-2,2)),0)>=19,IFERROR(INDEX('Level Engine'!$EJ$9:$EJ$55,MATCH($AL11,'Level Engine'!$AA$9:$AA$55,0)),0)=0,$AN$3>$AM$2)," ⟲rev","")&IF($AL11='King Node Model'!$F$24," ⟂","")&$DJ11&IF(IFERROR(INDEX('Level Engine'!$EN$9:$EN$55,MATCH($AL11,'Level Engine'!$AA$9:$AA$55,0)),0)=1," Ⓟ"&IF(AND(OR('King Node Model'!$A$8="Neg",N('Level Engine'!$BG$72)=1),IFERROR(INDEX('Level Engine'!$AN$9:$AN$55,MATCH($AL11,'Level Engine'!$AA$9:$AA$55,0)),0)<>1)," NO-REV",""),"")&IF(AND(ISNUMBER($AL11),OR(AND(ISNUMBER(SEARCH("chop edge",$E$45)),$AL11='King Node Model'!$AL$42),AND(ISNUMBER(SEARCH("chop edge",$E$46)),$AL11='King Node Model'!$AL$43),AND(ISNUMBER(SEARCH("chop edge",$E$52)),$AL11='King Node Model'!$AL$49),AND(ISNUMBER(SEARCH("chop edge",$E$53)),$AL11='King Node Model'!$AL$50)))," ⒸⒺ","")&IF(AND('Level Engine'!$GJ$4=1,OR($AL11='Level Engine'!$GJ$1,$AL11='Level Engine'!$GJ$2)),"","")&IF(ABS(N(IFERROR(INDEX('Level Engine'!$AE$9:$AE$55,MATCH($AL11,'Level Engine'!$AA$9:$AA$55,0)),0)))>='Level Engine'!$BG$85,IF(N(IFERROR(INDEX('Level Engine'!$AE$9:$AE$55,MATCH($AL11,'Level Engine'!$AA$9:$AA$55,0)),0))>0," Δ+"," Δ−"),"")&IFERROR(IF(AND(ISNUMBER(MATCH($AL11,'Level Engine'!$AA$9:$AA$55,0)),ABS(N(IFERROR(INDEX('Level Engine'!$AE$9:$AE$55,MATCH($AL11,'Level Engine'!$AA$9:$AA$55,0)),0)))<'Level Engine'!$BG$85,ABS(N(IFERROR(INDEX('Level Engine'!$AE$9:$AE$55,MATCH($AL11,'Level Engine'!$AA$9:$AA$55,0)),0)))<=ABS(N(IFERROR(INDEX('Level Engine'!$AE$9:$AE$55,MATCH($AL11+5,'Level Engine'!$AA$9:$AA$55,0)),0))),ABS(N(IFERROR(INDEX('Level Engine'!$AE$9:$AE$55,MATCH($AL11,'Level Engine'!$AA$9:$AA$55,0)),0)))<=ABS(N(IFERROR(INDEX('Level Engine'!$AE$9:$AE$55,MATCH($AL11-5,'Level Engine'!$AA$9:$AA$55,0)),0))),OR(AND(ABS(N(IFERROR(INDEX('Level Engine'!$AE$9:$AE$55,MATCH($AL11+5,'Level Engine'!$AA$9:$AA$55,0)),0)))>='Level Engine'!$BG$85,ABS(N(IFERROR(INDEX('Level Engine'!$AE$9:$AE$55,MATCH($AL11,'Level Engine'!$AA$9:$AA$55,0)),0)))<='Level Engine'!$BG$88*ABS(N(IFERROR(INDEX('Level Engine'!$AE$9:$AE$55,MATCH($AL11+5,'Level Engine'!$AA$9:$AA$55,0)),0)))),AND(ABS(N(IFERROR(INDEX('Level Engine'!$AE$9:$AE$55,MATCH($AL11-5,'Level Engine'!$AA$9:$AA$55,0)),0)))>='Level Engine'!$BG$85,ABS(N(IFERROR(INDEX('Level Engine'!$AE$9:$AE$55,MATCH($AL11,'Level Engine'!$AA$9:$AA$55,0)),0)))<='Level Engine'!$BG$88*ABS(N(IFERROR(INDEX('Level Engine'!$AE$9:$AE$55,MATCH($AL11-5,'Level Engine'!$AA$9:$AA$55,0)),0)))))),IF(AND('King Node Model'!$A$8="Pos",N('Level Engine'!$BG$72)<>1),""," ∅"),""),"")&IF(IFERROR(INDEX('Level Engine'!$JD$9:$JD$55,MATCH($AL11,'Level Engine'!$AA$9:$AA$55,0)),"")="P"," P-OI",IF(IFERROR(INDEX('Level Engine'!$JD$9:$JD$55,MATCH($AL11,'Level Engine'!$AA$9:$AA$55,0)),"")="C"," C-OI","")) -> 7845 C-OI | C11: =IF(AND(ISNUMBER($AM11),$AM11>0,ISNUMBER($AO11),$AO$1>0),REPT("█",ROUND($AO11/$AO$1*26,0)),"") -> █ | D11: =IF(NOT(ISNUMBER($AL11)),"",IF(IFERROR(INDEX('Level Engine'!$FS$9:$FS$55,MATCH($AL11,'Level Engine'!$AA$9:$AA$55,0)),0)=1,"⊙","")) | E11: Dealer is | F11: ='King Node Model'!C12 -> Short ATM/near-ATM calls (dominant gamma) + Long OTM puts | Q11: Reading | R11: Tracker | S11: ATM IV | AL11: ='King Node Model'!A37 -> 7845 | AM11: ='King Node Model'!C37 -> 92046 | AN11: ='King Node Model'!T30 -> 7780 | AO11: ='King Node Model'!B37 -> 101575 | AY11: =IF(AND($B$2="Hide unsafe",$BB11=1),0,IF(AND(OR(AND(AND(ISNUMBER($AL11),OR(AND($AL11>=$AQ$22,$AL11<=$AR$22,$AS$22=1),$AL11=$AQ$22,$AL11=$AR$22,$AL11=$AQ$23,$AL11=$AR$23,$AL11=$AQ$24,$AL11=$AR$24),NOT(OR($AL11=$AN$5,$AL11=$AN$6,$AL11=$AN$7,$AL11=$AN$8,$AL11=$AN$10,$AL11=$AN$11))),NOT(OR(AND('King Node Model'!$P$13="Up",OR($AL11=$AQ$22,$AL11=$AQ$23,$AL11=$AQ$24,$AL11='King Node Model'!$AM$20,$AL11='King Node Model'!$AM$21,$AL11='King Node Model'!$AM$22),OR(AND('King Node Model'!$B$23-$AL11>=0,'King Node Model'!$B$23-$AL11<=5),AND('King Node Model'!$C$23-$AL11>=0,'King Node Model'!$C$23-$AL11<=5))),AND('King Node Model'!$P$13="Down",OR($AL11=$AR$22,$AL11=$AR$23,$AL11=$AR$24,$AL11='King Node Model'!$AN$20,$AL11='King Node Model'!$AN$21,$AL11='King Node Model'!$AN$22),OR(AND($AL11-'King Node Model'!$B$23>=0,$AL11-'King Node Model'!$B$23<=5),AND($AL11-'King Node Model'!$C$24>=0,$AL11-'King Node Model'!$C$24<=5)))))),AND(AND(ISNUMBER($AL11),OR(AND($AL11>=$AQ$22,$AL11<=$AR$22,$AS$22=1),$AL11=$AQ$22,$AL11=$AR$22,$AL11=$AQ$23,$AL11=$AR$23,$AL11=$AQ$24,$AL11=$AR$24,$AL11='King Node Model'!$AL$42,$AL11='King Node Model'!$AL$43),OR($AL11=$AN$5,$AL11=$AN$6,$AL11=$AN$7,$AL11=$AN$8,$AL11=$AN$10,$AL11=$AN$11)),NOT(OR(AND('King Node Model'!$P$13="Up",OR($AL11=$AQ$22,$AL11=$AQ$23,$AL11=$AQ$24,$AL11='King Node Model'!$AM$20,$AL11='King Node Model'!$AM$21,$AL11='King Node Model'!$AM$22),OR(AND('King Node Model'!$B$23-$AL11>=0,'King Node Model'!$B$23-$AL11<=5),AND('King Node Model'!$C$23-$AL11>=0,'King Node Model'!$C$23-$AL11<=5))),AND('King Node Model'!$P$13="Down",OR($AL11=$AR$22,$AL11=$AR$23,$AL11=$AR$24,$AL11='King Node Model'!$AN$20,$AL11='King Node Model'!$AN$21,$AL11='King Node Model'!$AN$22),OR(AND($AL11-'King Node Model'!$B$23>=0,$AL11-'King Node Model'!$B$23<=5),AND($AL11-'King Node Model'!$C$24>=0,$AL11-'King Node Model'!$C$24<=5)))))),AND(AND(ISNUMBER($AL11),OR(AND($AL11>='King Node Model'!$AM$20,$AL11<='King Node Model'!$AN$20,$AS$23=1),$AL11='King Node Model'!$AM$20,$AL11='King Node Model'!$AN$20,$AL11='King Node Model'!$AM$21,$AL11='King Node Model'!$AN$21,$AL11='King Node Model'!$AM$22,$AL11='King Node Model'!$AN$22),NOT(OR($AL11=$AN$5,$AL11=$AN$6,$AL11=$AN$7,$AL11=$AN$8,$AL11=$AN$10,$AL11=$AN$11))),NOT(AND(ISNUMBER('King Node Model'!$F$24),$AL11='King Node Model'!$F$24,IFERROR(INDEX('Level Engine'!$JN$9:$JN$55,MATCH($AL11,'Level Engine'!$AA$9:$AA$55,0)),0)<>1))),AND(AND(ISNUMBER($AL11),OR(AND($AL11>='King Node Model'!$AM$20,$AL11<='King Node Model'!$AN$20,$AS$23=1),$AL11='King Node Model'!$AM$20,$AL11='King Node Model'!$AN$20,$AL11='King Node Model'!$AM$21,$AL11='King Node Model'!$AN$21,$AL11='King Node Model'!$AM$22,$AL11='King Node Model'!$AN$22,$AL11='King Node Model'!$AL$49,$AL11='King Node Model'!$AL$50),OR($AL11=$AN$5,$AL11=$AN$6,$AL11=$AN$7,$AL11=$AN$8,$AL11=$AN$10,$AL11=$AN$11)),NOT(OR(AND('King Node Model'!$P$13="Up",OR($AL11=$AQ$22,$AL11=$AQ$23,$AL11=$AQ$24,$AL11='King Node Model'!$AM$20,$AL11='King Node Model'!$AM$21,$AL11='King Node Model'!$AM$22),OR(AND('King Node Model'!$B$23-$AL11>=0,'King Node Model'!$B$23-$AL11<=5),AND('King Node Model'!$C$23-$AL11>=0,'King Node Model'!$C$23-$AL11<=5))),AND('King Node Model'!$P$13="Down",OR($AL11=$AR$22,$AL11=$AR$23,$AL11=$AR$24,$AL11='King Node Model'!$AN$20,$AL11='King Node Model'!$AN$21,$AL11='King Node Model'!$AN$22),OR(AND($AL11-'King Node Model'!$B$23>=0,$AL11-'King Node Model'!$B$23<=5),AND($AL11-'King Node Model'!$C$24>=0,$AL11-'King Node Model'!$C$24<=5))))))),OR(COUNTIF('Level Engine'!$W$9:$W$14,$AL11)>0,COUNTIF('Level Engine'!$W$18:$W$23,$AL11)>0)),1,0)) -> 0 | AZ11: =IF($B$2="Hide unsafe",0,$BB11) -> 0 | BB11: =IF(OR(AND($AL11='King Node Model'!$AL$42,$AP$45<>"RASP"),AND($AL11='King Node Model'!$AL$43,$AP$46<>"RASP"),AND($AL11='King Node Model'!$AL$49,$AP$52<>"RASP"),AND($AL11='King Node Model'!$AL$50,$AP$53<>"RASP"),AND($AL11='King Node Model'!$AL$44,$AP$47<>"RASP"),AND($AL11='King Node Model'!$AL$51,$AP$54<>"RASP")),0,IF(AND(AND(ISNUMBER($AL11),OR(AND($AL11>=$AQ$22,$AL11<=$AR$22,$AP$45="RASP"),AND($AL11>=$AQ$23,$AL11<=$AR$23,$AP$46="RASP"),AND($AL11>=$AQ$24,$AL11<=$AR$24,$AP$47="RASP"),AND($AL11>='King Node Model'!$AM$20,$AL11<='King Node Model'!$AN$20,$AP$52="RASP",NOT($L$52=$AW$52)),AND($AL11='King Node Model'!$B$23,$AP$52="RASP",$L$52=$AW$52),AND($AL11>='King Node Model'!$AM$21,$AL11<='King Node Model'!$AN$21,$AP$53="RASP",NOT($L$53=$AW$53)),AND($AL11='King Node Model'!$B$23,$AP$53="RASP",$L$53=$AW$53),AND($AL11>='King Node Model'!$AM$22,$AL11<='King Node Model'!$AN$22,$AP$54="RASP"),AND($AL11>=IFERROR(INDEX('Level Engine'!$AT$9:$AT$55,MATCH('King Node Model'!$AL$42,'Level Engine'!$AA$9:$AA$55,0)),""),$AL11<=IFERROR(INDEX('Level Engine'!$AU$9:$AU$55,MATCH('King Node Model'!$AL$42,'Level Engine'!$AA$9:$AA$55,0)),""),$AP$45="RASP"),AND($AL11>=IFERROR(INDEX('Level Engine'!$AT$9:$AT$55,MATCH('King Node Model'!$AL$43,'Level Engine'!$AA$9:$AA$55,0)),""),$AL11<=IFERROR(INDEX('Level Engine'!$AU$9:$AU$55,MATCH('King Node Model'!$AL$43,'Level Engine'!$AA$9:$AA$55,0)),""),$AP$46="RASP"),AND($AL11>=IFERROR(INDEX('Level Engine'!$AT$9:$AT$55,MATCH('King Node Model'!$AL$44,'Level Engine'!$AA$9:$AA$55,0)),""),$AL11<=IFERROR(INDEX('Level Engine'!$AU$9:$AU$55,MATCH('King Node Model'!$AL$44,'Level Engine'!$AA$9:$AA$55,0)),""),$AP$47="RASP"),AND($AL11>=IFERROR(INDEX('Level Engine'!$AT$9:$AT$55,MATCH('King Node Model'!$AL$49,'Level Engine'!$AA$9:$AA$55,0)),""),$AL11<=IFERROR(INDEX('Level Engine'!$AU$9:$AU$55,MATCH('King Node Model'!$AL$49,'Level Engine'!$AA$9:$AA$55,0)),""),$AP$52="RASP",NOT($L$52=$AW$52)),AND($AL11>=IFERROR(INDEX('Level Engine'!$AT$9:$AT$55,MATCH('King Node Model'!$AL$50,'Level Engine'!$AA$9:$AA$55,0)),""),$AL11<=IFERROR(INDEX('Level Engine'!$AU$9:$AU$55,MATCH('King Node Model'!$AL$50,'Level Engine'!$AA$9:$AA$55,0)),""),$AP$53="RASP",NOT($L$53=$AW$53)),AND($AL11>=IFERROR(INDEX('Level Engine'!$AT$9:$AT$55,MATCH('King Node Model'!$AL$51,'Level Engine'!$AA$9:$AA$55,0)),""),$AL11<=IFERROR(INDEX('Level Engine'!$AU$9:$AU$55,MATCH('King Node Model'!$AL$51,'Level Engine'!$AA$9:$AA$55,0)),""),$AP$54="RASP"))),NOT(AND(ISNUMBER('King Node Model'!$F$24),$AL11='King Node Model'!$F$24,IFERROR(INDEX('Level Engine'!$JN$9:$JN$55,MATCH($AL11,'Level Engine'!$AA$9:$AA$55,0)),0)<>1,$AL11<>'King Node Model'!$AL$42,$AL11<>'King Node Model'!$AL$43,$AL11<>'King Node Model'!$AL$44,$AL11<>'King Node Model'!$AL$49,$AL11<>'King Node Model'!$AL$50,$AL11<>'King Node Model'!$AL$51))),1,0)) -> 0 | CO11: =IF(NOT(ISNUMBER($AL11)),"",IF(NOT(ISNUMBER(IFERROR(INDEX('Level Engine'!$FT$9:$FT$55,MATCH($AL11,'Level Engine'!$AA$9:$AA$55,0)),""))),"",IF(IFERROR(INDEX('Level Engine'!$FT$9:$FT$55,MATCH($AL11,'Level Engine'!$AA$9:$AA$55,0)),"")<0,0,2)+IF(ABS(IFERROR(INDEX('Level Engine'!$FT$9:$FT$55,MATCH($AL11,'Level Engine'!$AA$9:$AA$55,0)),""))>='Level Engine'!$FT$2,2,1))) -> 4 | DJ11: =IF(ISNUMBER($AL11),IF($AL11='Level Engine'!$BG$122," ⫪","")&IF($AL11='Level Engine'!$BG$118," S↑"&IFERROR(INDEX('Level Engine'!$MV$9:$MV$55,MATCH($AL11,'Level Engine'!$AA$9:$AA$55,0)),""),"")&IF($AL11='Level Engine'!$BG$119," S↓"&IFERROR(INDEX('Level Engine'!$MV$9:$MV$55,MATCH($AL11,'Level Engine'!$AA$9:$AA$55,0)),""),"")&IF($AL11='Level Engine'!$BG$120," D↑","")&IF($AL11='Level Engine'!$BG$121," D↓","")&IFERROR(INDEX('Level Engine'!$LG$9:$LG$55,MATCH($AL11,'Level Engine'!$AA$9:$AA$55,0)),"")&IF(IFERROR(INDEX('Level Engine'!$MA$9:$MA$55,MATCH($AL11,'Level Engine'!$AA$9:$AA$55,0)),0)=1," SAND","")&IF(IFERROR(INDEX('Level Engine'!$LM$9:$LM$55,MATCH($AL11,'Level Engine'!$AA$9:$AA$55,0)),0)>0," TP","")&IFERROR(" r"&MATCH($AL11,'Level Engine'!$W$9:$W$14,0),IFERROR(" s"&MATCH($AL11,'Level Engine'!$W$18:$W$23,0),""))&IF($AL11='Level Engine'!$BG$165," ◇","")&IF(N($DZ11)=1,IF($AL11>'Level Engine'!$BG$165," ⚠ DOM↓"," ⚠ DOM↑")&'Level Engine'!$BG$165,""),"") | DK11: =IF(AND(ISNUMBER($AL11),OR($AL11='King Node Model'!$AL$42,$AL11='King Node Model'!$AL$43,$AL11='King Node Model'!$AL$44)),IFERROR(MATCH($AL11,'Level Engine'!$W$9:$W$14,0),""),"") | DL11: =IF(AND(ISNUMBER($AL11),OR($AL11='King Node Model'!$AL$49,$AL11='King Node Model'!$AL$50,$AL11='King Node Model'!$AL$51)),IFERROR(MATCH($AL11,'Level Engine'!$W$18:$W$23,0),""),"") | DM11: =IF(AND(ISNUMBER($AL11),IFERROR(INDEX('Level Engine'!$LC$9:$LC$55,MATCH($AL11,'Level Engine'!$AA$9:$AA$55,0)),0)=1,OR($AL11=$AN$3,IFERROR(INDEX('Level Engine'!$LB$9:$LB$55,MATCH($AL11,'Level Engine'!$AA$9:$AA$55,0)),0)=1)),1,0) -> 0 | DZ11: =IF(ISNUMBER($AL11),IF(IFERROR(INDEX('Level Engine'!$NJ$9:$NJ$55,MATCH($AL11,'Level Engine'!$AA$9:$AA$55,0)),0)=1,1,0),0)
A12: =IF(AND(ISNUMBER($AM12),$AM12<0,ISNUMBER($AO12),$AO$1>0),REPT("█",ROUND($AO12/$AO$1*26,0)),"") | B12: =TEXT(IF(IF('Level Engine'!$GJ$4=1,$AL12='Level Engine'!$GJ$3,AND($AL12-$AM$2>-2.5,$AL12-$AM$2<=2.5)),$AM$2,$AL12),"0")&IF($AL12=$AN$1," ★","")&IF($AL12=$AN$2," ★","")&IF($AL12=$AN$3," ◆","")&IF(AND(ISNUMBER($AN$4),$AL12=$AN$4)," Ⓕ","")&IF(OR(AND(ISNUMBER('Level Engine'!$BG$87),$AL12='Level Engine'!$BG$87),AND(ISNUMBER('Level Engine'!$BG$105),$AL12='Level Engine'!$BG$105))," ζ","")&IF(AND(ISNUMBER($AN$35),$AL12=$AN$35)," ⓏⒼ","")&IF(OR($AL12='Level Engine'!$CP$4,$AL12='Level Engine'!$CP$5,$AL12='Level Engine'!$CP$6,$AL12='Level Engine'!$CP$7)," ☄","")&IF(OR($AL12=$AN$5,$AL12=$AN$8)," ║1","")&IF(OR($AL12=$AN$6,$AL12=$AN$10)," ║2","")&IF(OR($AL12=$AN$7,$AL12=$AN$11)," ║3","")&IF(OR($AL12=$AN$13,$AL12=$AN$16)," ▣1","")&IF(OR($AL12=$AN$14,$AL12=$AN$17)," ▣2","")&IF(OR($AL12=$AN$15,$AL12=$AN$18)," ▣3","")&IF(AND(NOT(OR(AND(ISNUMBER(SEARCH("chop edge",$E$45)),IFERROR(ABS($AL12-'King Node Model'!$AL$42)<=5,FALSE),NOT(ISNUMBER(SEARCH("UNSAFE",$L$45)))),AND(ISNUMBER(SEARCH("chop edge",$E$46)),IFERROR(ABS($AL12-'King Node Model'!$AL$43)<=5,FALSE),NOT(ISNUMBER(SEARCH("UNSAFE",$L$46)))),AND(ISNUMBER(SEARCH("chop edge",$E$52)),IFERROR(ABS($AL12-'King Node Model'!$AL$49)<=5,FALSE),NOT(ISNUMBER(SEARCH("UNSAFE",$L$52)))),AND(ISNUMBER(SEARCH("chop edge",$E$53)),IFERROR(ABS($AL12-'King Node Model'!$AL$50)<=5,FALSE),NOT(ISNUMBER(SEARCH("UNSAFE",$L$53)))))),OR(AND(IFERROR(INDEX('Level Engine'!$IB$9:$IB$55,MATCH('King Node Model'!$AL$49,'Level Engine'!$AA$9:$AA$55,0)),0)<>1,$AL12=IFERROR(INDEX('Level Engine'!$AU$9:$AU$55,MATCH('King Node Model'!$AL$49,'Level Engine'!$AA$9:$AA$55,0)),""),IFERROR(INDEX('Level Engine'!$AU$9:$AU$55,MATCH('King Node Model'!$AL$49,'Level Engine'!$AA$9:$AA$55,0)),"")<>IFERROR(INDEX('Level Engine'!$AT$9:$AT$55,MATCH('King Node Model'!$AL$49,'Level Engine'!$AA$9:$AA$55,0)),"")),AND(IFERROR(INDEX('Level Engine'!$IB$9:$IB$55,MATCH('King Node Model'!$AL$50,'Level Engine'!$AA$9:$AA$55,0)),0)<>1,$AL12=IFERROR(INDEX('Level Engine'!$AU$9:$AU$55,MATCH('King Node Model'!$AL$50,'Level Engine'!$AA$9:$AA$55,0)),""),IFERROR(INDEX('Level Engine'!$AU$9:$AU$55,MATCH('King Node Model'!$AL$50,'Level Engine'!$AA$9:$AA$55,0)),"")<>IFERROR(INDEX('Level Engine'!$AT$9:$AT$55,MATCH('King Node Model'!$AL$50,'Level Engine'!$AA$9:$AA$55,0)),"")))),IF(OR('King Node Model'!$A$8="Neg",N('Level Engine'!$BG$72)=1),""," ⒷⒽ"),"")&IF(AND(NOT(OR(AND(ISNUMBER(SEARCH("chop edge",$E$45)),IFERROR(ABS($AL12-'King Node Model'!$AL$42)<=5,FALSE),NOT(ISNUMBER(SEARCH("UNSAFE",$L$45)))),AND(ISNUMBER(SEARCH("chop edge",$E$46)),IFERROR(ABS($AL12-'King Node Model'!$AL$43)<=5,FALSE),NOT(ISNUMBER(SEARCH("UNSAFE",$L$46)))),AND(ISNUMBER(SEARCH("chop edge",$E$52)),IFERROR(ABS($AL12-'King Node Model'!$AL$49)<=5,FALSE),NOT(ISNUMBER(SEARCH("UNSAFE",$L$52)))),AND(ISNUMBER(SEARCH("chop edge",$E$53)),IFERROR(ABS($AL12-'King Node Model'!$AL$50)<=5,FALSE),NOT(ISNUMBER(SEARCH("UNSAFE",$L$53)))))),OR(AND(IFERROR(INDEX('Level Engine'!$IB$9:$IB$55,MATCH('King Node Model'!$AL$42,'Level Engine'!$AA$9:$AA$55,0)),0)<>1,$AL12=IFERROR(INDEX('Level Engine'!$AT$9:$AT$55,MATCH('King Node Model'!$AL$42,'Level Engine'!$AA$9:$AA$55,0)),""),IFERROR(INDEX('Level Engine'!$AT$9:$AT$55,MATCH('King Node Model'!$AL$42,'Level Engine'!$AA$9:$AA$55,0)),"")<>IFERROR(INDEX('Level Engine'!$AU$9:$AU$55,MATCH('King Node Model'!$AL$42,'Level Engine'!$AA$9:$AA$55,0)),"")),AND(IFERROR(INDEX('Level Engine'!$IB$9:$IB$55,MATCH('King Node Model'!$AL$43,'Level Engine'!$AA$9:$AA$55,0)),0)<>1,$AL12=IFERROR(INDEX('Level Engine'!$AT$9:$AT$55,MATCH('King Node Model'!$AL$43,'Level Engine'!$AA$9:$AA$55,0)),""),IFERROR(INDEX('Level Engine'!$AT$9:$AT$55,MATCH('King Node Model'!$AL$43,'Level Engine'!$AA$9:$AA$55,0)),"")<>IFERROR(INDEX('Level Engine'!$AU$9:$AU$55,MATCH('King Node Model'!$AL$43,'Level Engine'!$AA$9:$AA$55,0)),"")))),IF(OR('King Node Model'!$A$8="Neg",N('Level Engine'!$BG$72)=1),""," ⒷⓁ"),"")&IF(OR(AND($AL12>='King Node Model'!$AM$17,$AL12<='King Node Model'!$AN$17,$AP$45="RASP"),AND($AL12>='King Node Model'!$AM$18,$AL12<='King Node Model'!$AN$18,$AP$46="RASP"),AND($AL12>='King Node Model'!$AM$19,$AL12<='King Node Model'!$AN$19,$AP$47="RASP"),AND($AL12>='King Node Model'!$AM$20,$AL12<='King Node Model'!$AN$20,$AP$52="RASP"),AND($AL12>='King Node Model'!$AM$21,$AL12<='King Node Model'!$AN$21,$AP$53="RASP"),AND($AL12>='King Node Model'!$AM$22,$AL12<='King Node Model'!$AN$22,$AP$54="RASP")),"","")&IF(IF('Level Engine'!$GJ$4=1,$AL12='Level Engine'!$GJ$3,AND($AL12-$AM$2>-2.5,$AL12-$AM$2<=2.5))," ◄","")&IF(IFERROR(INDEX('Level Engine'!$GV$9:$GV$55,MATCH($AL12,'Level Engine'!$AA$9:$AA$55,0)),0)=1," Ⓥ"&IF(IFERROR(INDEX('Level Engine'!$ET$9:$ET$55,MATCH($AL12,'Level Engine'!$AA$9:$AA$55,0)),0)=1,"+",""),"")&IF(OR(AND($AL12=$AN$38,IFERROR(INDEX('Level Engine'!$AN$9:$AN$55,MATCH($AL12,'Level Engine'!$AA$9:$AA$55,0)),0)<>1),$AL12=$AN$39)," ⊙","")&IF(AND(OR('King Node Model'!$A$8="Neg",N('Level Engine'!$BG$72)=1),ABS(MIN($AM$3:$AM$64))>MAX($AM$3:$AM$64),$AN$2<$AM$2,$AL12<$AM$2,ABS($AL12-$AN$2)<=5,IFERROR(VALUE(MID('King Node Model'!$K$26,FIND(":",'King Node Model'!$K$26)-2,2)),0)>=19,IFERROR(INDEX('Level Engine'!$EJ$9:$EJ$55,MATCH($AL12,'Level Engine'!$AA$9:$AA$55,0)),0)=0,$AN$3>$AM$2)," ⟲rev","")&IF($AL12='King Node Model'!$F$24," ⟂","")&$DJ12&IF(IFERROR(INDEX('Level Engine'!$EN$9:$EN$55,MATCH($AL12,'Level Engine'!$AA$9:$AA$55,0)),0)=1," Ⓟ"&IF(AND(OR('King Node Model'!$A$8="Neg",N('Level Engine'!$BG$72)=1),IFERROR(INDEX('Level Engine'!$AN$9:$AN$55,MATCH($AL12,'Level Engine'!$AA$9:$AA$55,0)),0)<>1)," NO-REV",""),"")&IF(AND(ISNUMBER($AL12),OR(AND(ISNUMBER(SEARCH("chop edge",$E$45)),$AL12='King Node Model'!$AL$42),AND(ISNUMBER(SEARCH("chop edge",$E$46)),$AL12='King Node Model'!$AL$43),AND(ISNUMBER(SEARCH("chop edge",$E$52)),$AL12='King Node Model'!$AL$49),AND(ISNUMBER(SEARCH("chop edge",$E$53)),$AL12='King Node Model'!$AL$50)))," ⒸⒺ","")&IF(AND('Level Engine'!$GJ$4=1,OR($AL12='Level Engine'!$GJ$1,$AL12='Level Engine'!$GJ$2)),"","")&IF(ABS(N(IFERROR(INDEX('Level Engine'!$AE$9:$AE$55,MATCH($AL12,'Level Engine'!$AA$9:$AA$55,0)),0)))>='Level Engine'!$BG$85,IF(N(IFERROR(INDEX('Level Engine'!$AE$9:$AE$55,MATCH($AL12,'Level Engine'!$AA$9:$AA$55,0)),0))>0," Δ+"," Δ−"),"")&IFERROR(IF(AND(ISNUMBER(MATCH($AL12,'Level Engine'!$AA$9:$AA$55,0)),ABS(N(IFERROR(INDEX('Level Engine'!$AE$9:$AE$55,MATCH($AL12,'Level Engine'!$AA$9:$AA$55,0)),0)))<'Level Engine'!$BG$85,ABS(N(IFERROR(INDEX('Level Engine'!$AE$9:$AE$55,MATCH($AL12,'Level Engine'!$AA$9:$AA$55,0)),0)))<=ABS(N(IFERROR(INDEX('Level Engine'!$AE$9:$AE$55,MATCH($AL12+5,'Level Engine'!$AA$9:$AA$55,0)),0))),ABS(N(IFERROR(INDEX('Level Engine'!$AE$9:$AE$55,MATCH($AL12,'Level Engine'!$AA$9:$AA$55,0)),0)))<=ABS(N(IFERROR(INDEX('Level Engine'!$AE$9:$AE$55,MATCH($AL12-5,'Level Engine'!$AA$9:$AA$55,0)),0))),OR(AND(ABS(N(IFERROR(INDEX('Level Engine'!$AE$9:$AE$55,MATCH($AL12+5,'Level Engine'!$AA$9:$AA$55,0)),0)))>='Level Engine'!$BG$85,ABS(N(IFERROR(INDEX('Level Engine'!$AE$9:$AE$55,MATCH($AL12,'Level Engine'!$AA$9:$AA$55,0)),0)))<='Level Engine'!$BG$88*ABS(N(IFERROR(INDEX('Level Engine'!$AE$9:$AE$55,MATCH($AL12+5,'Level Engine'!$AA$9:$AA$55,0)),0)))),AND(ABS(N(IFERROR(INDEX('Level Engine'!$AE$9:$AE$55,MATCH($AL12-5,'Level Engine'!$AA$9:$AA$55,0)),0)))>='Level Engine'!$BG$85,ABS(N(IFERROR(INDEX('Level Engine'!$AE$9:$AE$55,MATCH($AL12,'Level Engine'!$AA$9:$AA$55,0)),0)))<='Level Engine'!$BG$88*ABS(N(IFERROR(INDEX('Level Engine'!$AE$9:$AE$55,MATCH($AL12-5,'Level Engine'!$AA$9:$AA$55,0)),0)))))),IF(AND('King Node Model'!$A$8="Pos",N('Level Engine'!$BG$72)<>1),""," ∅"),""),"")&IF(IFERROR(INDEX('Level Engine'!$JD$9:$JD$55,MATCH($AL12,'Level Engine'!$AA$9:$AA$55,0)),"")="P"," P-OI",IF(IFERROR(INDEX('Level Engine'!$JD$9:$JD$55,MATCH($AL12,'Level Engine'!$AA$9:$AA$55,0)),"")="C"," C-OI","")) -> 7840 | C12: =IF(AND(ISNUMBER($AM12),$AM12>0,ISNUMBER($AO12),$AO$1>0),REPT("█",ROUND($AO12/$AO$1*26,0)),"") -> ██ | D12: =IF(NOT(ISNUMBER($AL12)),"",IF(IFERROR(INDEX('Level Engine'!$FS$9:$FS$55,MATCH($AL12,'Level Engine'!$AA$9:$AA$55,0)),0)=1,"⊙","")) | E12: Testing Results | F12: =IFERROR(TRIM(INDEX(Matrix!$U$2:$U$79,MATCH('King Node Model'!$J$8,Matrix!$A$2:$A$79,0))&""),"") | AL12: ='King Node Model'!A38 -> 7840 | AM12: ='King Node Model'!C38 -> 225627 | AO12: ='King Node Model'!B38 -> 265851 | AY12: =IF(AND($B$2="Hide unsafe",$BB12=1),0,IF(AND(OR(AND(AND(ISNUMBER($AL12),OR(AND($AL12>=$AQ$22,$AL12<=$AR$22,$AS$22=1),$AL12=$AQ$22,$AL12=$AR$22,$AL12=$AQ$23,$AL12=$AR$23,$AL12=$AQ$24,$AL12=$AR$24),NOT(OR($AL12=$AN$5,$AL12=$AN$6,$AL12=$AN$7,$AL12=$AN$8,$AL12=$AN$10,$AL12=$AN$11))),NOT(OR(AND('King Node Model'!$P$13="Up",OR($AL12=$AQ$22,$AL12=$AQ$23,$AL12=$AQ$24,$AL12='King Node Model'!$AM$20,$AL12='King Node Model'!$AM$21,$AL12='King Node Model'!$AM$22),OR(AND('King Node Model'!$B$23-$AL12>=0,'King Node Model'!$B$23-$AL12<=5),AND('King Node Model'!$C$23-$AL12>=0,'King Node Model'!$C$23-$AL12<=5))),AND('King Node Model'!$P$13="Down",OR($AL12=$AR$22,$AL12=$AR$23,$AL12=$AR$24,$AL12='King Node Model'!$AN$20,$AL12='King Node Model'!$AN$21,$AL12='King Node Model'!$AN$22),OR(AND($AL12-'King Node Model'!$B$23>=0,$AL12-'King Node Model'!$B$23<=5),AND($AL12-'King Node Model'!$C$24>=0,$AL12-'King Node Model'!$C$24<=5)))))),AND(AND(ISNUMBER($AL12),OR(AND($AL12>=$AQ$22,$AL12<=$AR$22,$AS$22=1),$AL12=$AQ$22,$AL12=$AR$22,$AL12=$AQ$23,$AL12=$AR$23,$AL12=$AQ$24,$AL12=$AR$24,$AL12='King Node Model'!$AL$42,$AL12='King Node Model'!$AL$43),OR($AL12=$AN$5,$AL12=$AN$6,$AL12=$AN$7,$AL12=$AN$8,$AL12=$AN$10,$AL12=$AN$11)),NOT(OR(AND('King Node Model'!$P$13="Up",OR($AL12=$AQ$22,$AL12=$AQ$23,$AL12=$AQ$24,$AL12='King Node Model'!$AM$20,$AL12='King Node Model'!$AM$21,$AL12='King Node Model'!$AM$22),OR(AND('King Node Model'!$B$23-$AL12>=0,'King Node Model'!$B$23-$AL12<=5),AND('King Node Model'!$C$23-$AL12>=0,'King Node Model'!$C$23-$AL12<=5))),AND('King Node Model'!$P$13="Down",OR($AL12=$AR$22,$AL12=$AR$23,$AL12=$AR$24,$AL12='King Node Model'!$AN$20,$AL12='King Node Model'!$AN$21,$AL12='King Node Model'!$AN$22),OR(AND($AL12-'King Node Model'!$B$23>=0,$AL12-'King Node Model'!$B$23<=5),AND($AL12-'King Node Model'!$C$24>=0,$AL12-'King Node Model'!$C$24<=5)))))),AND(AND(ISNUMBER($AL12),OR(AND($AL12>='King Node Model'!$AM$20,$AL12<='King Node Model'!$AN$20,$AS$23=1),$AL12='King Node Model'!$AM$20,$AL12='King Node Model'!$AN$20,$AL12='King Node Model'!$AM$21,$AL12='King Node Model'!$AN$21,$AL12='King Node Model'!$AM$22,$AL12='King Node Model'!$AN$22),NOT(OR($AL12=$AN$5,$AL12=$AN$6,$AL12=$AN$7,$AL12=$AN$8,$AL12=$AN$10,$AL12=$AN$11))),NOT(AND(ISNUMBER('King Node Model'!$F$24),$AL12='King Node Model'!$F$24,IFERROR(INDEX('Level Engine'!$JN$9:$JN$55,MATCH($AL12,'Level Engine'!$AA$9:$AA$55,0)),0)<>1))),AND(AND(ISNUMBER($AL12),OR(AND($AL12>='King Node Model'!$AM$20,$AL12<='King Node Model'!$AN$20,$AS$23=1),$AL12='King Node Model'!$AM$20,$AL12='King Node Model'!$AN$20,$AL12='King Node Model'!$AM$21,$AL12='King Node Model'!$AN$21,$AL12='King Node Model'!$AM$22,$AL12='King Node Model'!$AN$22,$AL12='King Node Model'!$AL$49,$AL12='King Node Model'!$AL$50),OR($AL12=$AN$5,$AL12=$AN$6,$AL12=$AN$7,$AL12=$AN$8,$AL12=$AN$10,$AL12=$AN$11)),NOT(OR(AND('King Node Model'!$P$13="Up",OR($AL12=$AQ$22,$AL12=$AQ$23,$AL12=$AQ$24,$AL12='King Node Model'!$AM$20,$AL12='King Node Model'!$AM$21,$AL12='King Node Model'!$AM$22),OR(AND('King Node Model'!$B$23-$AL12>=0,'King Node Model'!$B$23-$AL12<=5),AND('King Node Model'!$C$23-$AL12>=0,'King Node Model'!$C$23-$AL12<=5))),AND('King Node Model'!$P$13="Down",OR($AL12=$AR$22,$AL12=$AR$23,$AL12=$AR$24,$AL12='King Node Model'!$AN$20,$AL12='King Node Model'!$AN$21,$AL12='King Node Model'!$AN$22),OR(AND($AL12-'King Node Model'!$B$23>=0,$AL12-'King Node Model'!$B$23<=5),AND($AL12-'King Node Model'!$C$24>=0,$AL12-'King Node Model'!$C$24<=5))))))),OR(COUNTIF('Level Engine'!$W$9:$W$14,$AL12)>0,COUNTIF('Level Engine'!$W$18:$W$23,$AL12)>0)),1,0)) -> 0 | AZ12: =IF($B$2="Hide unsafe",0,$BB12) -> 0 | BB12: =IF(OR(AND($AL12='King Node Model'!$AL$42,$AP$45<>"RASP"),AND($AL12='King Node Model'!$AL$43,$AP$46<>"RASP"),AND($AL12='King Node Model'!$AL$49,$AP$52<>"RASP"),AND($AL12='King Node Model'!$AL$50,$AP$53<>"RASP"),AND($AL12='King Node Model'!$AL$44,$AP$47<>"RASP"),AND($AL12='King Node Model'!$AL$51,$AP$54<>"RASP")),0,IF(AND(AND(ISNUMBER($AL12),OR(AND($AL12>=$AQ$22,$AL12<=$AR$22,$AP$45="RASP"),AND($AL12>=$AQ$23,$AL12<=$AR$23,$AP$46="RASP"),AND($AL12>=$AQ$24,$AL12<=$AR$24,$AP$47="RASP"),AND($AL12>='King Node Model'!$AM$20,$AL12<='King Node Model'!$AN$20,$AP$52="RASP",NOT($L$52=$AW$52)),AND($AL12='King Node Model'!$B$23,$AP$52="RASP",$L$52=$AW$52),AND($AL12>='King Node Model'!$AM$21,$AL12<='King Node Model'!$AN$21,$AP$53="RASP",NOT($L$53=$AW$53)),AND($AL12='King Node Model'!$B$23,$AP$53="RASP",$L$53=$AW$53),AND($AL12>='King Node Model'!$AM$22,$AL12<='King Node Model'!$AN$22,$AP$54="RASP"),AND($AL12>=IFERROR(INDEX('Level Engine'!$AT$9:$AT$55,MATCH('King Node Model'!$AL$42,'Level Engine'!$AA$9:$AA$55,0)),""),$AL12<=IFERROR(INDEX('Level Engine'!$AU$9:$AU$55,MATCH('King Node Model'!$AL$42,'Level Engine'!$AA$9:$AA$55,0)),""),$AP$45="RASP"),AND($AL12>=IFERROR(INDEX('Level Engine'!$AT$9:$AT$55,MATCH('King Node Model'!$AL$43,'Level Engine'!$AA$9:$AA$55,0)),""),$AL12<=IFERROR(INDEX('Level Engine'!$AU$9:$AU$55,MATCH('King Node Model'!$AL$43,'Level Engine'!$AA$9:$AA$55,0)),""),$AP$46="RASP"),AND($AL12>=IFERROR(INDEX('Level Engine'!$AT$9:$AT$55,MATCH('King Node Model'!$AL$44,'Level Engine'!$AA$9:$AA$55,0)),""),$AL12<=IFERROR(INDEX('Level Engine'!$AU$9:$AU$55,MATCH('King Node Model'!$AL$44,'Level Engine'!$AA$9:$AA$55,0)),""),$AP$47="RASP"),AND($AL12>=IFERROR(INDEX('Level Engine'!$AT$9:$AT$55,MATCH('King Node Model'!$AL$49,'Level Engine'!$AA$9:$AA$55,0)),""),$AL12<=IFERROR(INDEX('Level Engine'!$AU$9:$AU$55,MATCH('King Node Model'!$AL$49,'Level Engine'!$AA$9:$AA$55,0)),""),$AP$52="RASP",NOT($L$52=$AW$52)),AND($AL12>=IFERROR(INDEX('Level Engine'!$AT$9:$AT$55,MATCH('King Node Model'!$AL$50,'Level Engine'!$AA$9:$AA$55,0)),""),$AL12<=IFERROR(INDEX('Level Engine'!$AU$9:$AU$55,MATCH('King Node Model'!$AL$50,'Level Engine'!$AA$9:$AA$55,0)),""),$AP$53="RASP",NOT($L$53=$AW$53)),AND($AL12>=IFERROR(INDEX('Level Engine'!$AT$9:$AT$55,MATCH('King Node Model'!$AL$51,'Level Engine'!$AA$9:$AA$55,0)),""),$AL12<=IFERROR(INDEX('Level Engine'!$AU$9:$AU$55,MATCH('King Node Model'!$AL$51,'Level Engine'!$AA$9:$AA$55,0)),""),$AP$54="RASP"))),NOT(AND(ISNUMBER('King Node Model'!$F$24),$AL12='King Node Model'!$F$24,IFERROR(INDEX('Level Engine'!$JN$9:$JN$55,MATCH($AL12,'Level Engine'!$AA$9:$AA$55,0)),0)<>1,$AL12<>'King Node Model'!$AL$42,$AL12<>'King Node Model'!$AL$43,$AL12<>'King Node Model'!$AL$44,$AL12<>'King Node Model'!$AL$49,$AL12<>'King Node Model'!$AL$50,$AL12<>'King Node Model'!$AL$51))),1,0)) -> 0 | CO12: =IF(NOT(ISNUMBER($AL12)),"",IF(NOT(ISNUMBER(IFERROR(INDEX('Level Engine'!$FT$9:$FT$55,MATCH($AL12,'Level Engine'!$AA$9:$AA$55,0)),""))),"",IF(IFERROR(INDEX('Level Engine'!$FT$9:$FT$55,MATCH($AL12,'Level Engine'!$AA$9:$AA$55,0)),"")<0,0,2)+IF(ABS(IFERROR(INDEX('Level Engine'!$FT$9:$FT$55,MATCH($AL12,'Level Engine'!$AA$9:$AA$55,0)),""))>='Level Engine'!$FT$2,2,1))) -> 4 | DJ12: =IF(ISNUMBER($AL12),IF($AL12='Level Engine'!$BG$122," ⫪","")&IF($AL12='Level Engine'!$BG$118," S↑"&IFERROR(INDEX('Level Engine'!$MV$9:$MV$55,MATCH($AL12,'Level Engine'!$AA$9:$AA$55,0)),""),"")&IF($AL12='Level Engine'!$BG$119," S↓"&IFERROR(INDEX('Level Engine'!$MV$9:$MV$55,MATCH($AL12,'Level Engine'!$AA$9:$AA$55,0)),""),"")&IF($AL12='Level Engine'!$BG$120," D↑","")&IF($AL12='Level Engine'!$BG$121," D↓","")&IFERROR(INDEX('Level Engine'!$LG$9:$LG$55,MATCH($AL12,'Level Engine'!$AA$9:$AA$55,0)),"")&IF(IFERROR(INDEX('Level Engine'!$MA$9:$MA$55,MATCH($AL12,'Level Engine'!$AA$9:$AA$55,0)),0)=1," SAND","")&IF(IFERROR(INDEX('Level Engine'!$LM$9:$LM$55,MATCH($AL12,'Level Engine'!$AA$9:$AA$55,0)),0)>0," TP","")&IFERROR(" r"&MATCH($AL12,'Level Engine'!$W$9:$W$14,0),IFERROR(" s"&MATCH($AL12,'Level Engine'!$W$18:$W$23,0),""))&IF($AL12='Level Engine'!$BG$165," ◇","")&IF(N($DZ12)=1,IF($AL12>'Level Engine'!$BG$165," ⚠ DOM↓"," ⚠ DOM↑")&'Level Engine'!$BG$165,""),"") | DK12: =IF(AND(ISNUMBER($AL12),OR($AL12='King Node Model'!$AL$42,$AL12='King Node Model'!$AL$43,$AL12='King Node Model'!$AL$44)),IFERROR(MATCH($AL12,'Level Engine'!$W$9:$W$14,0),""),"") | DL12: =IF(AND(ISNUMBER($AL12),OR($AL12='King Node Model'!$AL$49,$AL12='King Node Model'!$AL$50,$AL12='King Node Model'!$AL$51)),IFERROR(MATCH($AL12,'Level Engine'!$W$18:$W$23,0),""),"") | DM12: =IF(AND(ISNUMBER($AL12),IFERROR(INDEX('Level Engine'!$LC$9:$LC$55,MATCH($AL12,'Level Engine'!$AA$9:$AA$55,0)),0)=1,OR($AL12=$AN$3,IFERROR(INDEX('Level Engine'!$LB$9:$LB$55,MATCH($AL12,'Level Engine'!$AA$9:$AA$55,0)),0)=1)),1,0) -> 0 | DZ12: =IF(ISNUMBER($AL12),IF(IFERROR(INDEX('Level Engine'!$NJ$9:$NJ$55,MATCH($AL12,'Level Engine'!$AA$9:$AA$55,0)),0)=1,1,0),0)
A13: =IF(AND(ISNUMBER($AM13),$AM13<0,ISNUMBER($AO13),$AO$1>0),REPT("█",ROUND($AO13/$AO$1*26,0)),"") | B13: =TEXT(IF(IF('Level Engine'!$GJ$4=1,$AL13='Level Engine'!$GJ$3,AND($AL13-$AM$2>-2.5,$AL13-$AM$2<=2.5)),$AM$2,$AL13),"0")&IF($AL13=$AN$1," ★","")&IF($AL13=$AN$2," ★","")&IF($AL13=$AN$3," ◆","")&IF(AND(ISNUMBER($AN$4),$AL13=$AN$4)," Ⓕ","")&IF(OR(AND(ISNUMBER('Level Engine'!$BG$87),$AL13='Level Engine'!$BG$87),AND(ISNUMBER('Level Engine'!$BG$105),$AL13='Level Engine'!$BG$105))," ζ","")&IF(AND(ISNUMBER($AN$35),$AL13=$AN$35)," ⓏⒼ","")&IF(OR($AL13='Level Engine'!$CP$4,$AL13='Level Engine'!$CP$5,$AL13='Level Engine'!$CP$6,$AL13='Level Engine'!$CP$7)," ☄","")&IF(OR($AL13=$AN$5,$AL13=$AN$8)," ║1","")&IF(OR($AL13=$AN$6,$AL13=$AN$10)," ║2","")&IF(OR($AL13=$AN$7,$AL13=$AN$11)," ║3","")&IF(OR($AL13=$AN$13,$AL13=$AN$16)," ▣1","")&IF(OR($AL13=$AN$14,$AL13=$AN$17)," ▣2","")&IF(OR($AL13=$AN$15,$AL13=$AN$18)," ▣3","")&IF(AND(NOT(OR(AND(ISNUMBER(SEARCH("chop edge",$E$45)),IFERROR(ABS($AL13-'King Node Model'!$AL$42)<=5,FALSE),NOT(ISNUMBER(SEARCH("UNSAFE",$L$45)))),AND(ISNUMBER(SEARCH("chop edge",$E$46)),IFERROR(ABS($AL13-'King Node Model'!$AL$43)<=5,FALSE),NOT(ISNUMBER(SEARCH("UNSAFE",$L$46)))),AND(ISNUMBER(SEARCH("chop edge",$E$52)),IFERROR(ABS($AL13-'King Node Model'!$AL$49)<=5,FALSE),NOT(ISNUMBER(SEARCH("UNSAFE",$L$52)))),AND(ISNUMBER(SEARCH("chop edge",$E$53)),IFERROR(ABS($AL13-'King Node Model'!$AL$50)<=5,FALSE),NOT(ISNUMBER(SEARCH("UNSAFE",$L$53)))))),OR(AND(IFERROR(INDEX('Level Engine'!$IB$9:$IB$55,MATCH('King Node Model'!$AL$49,'Level Engine'!$AA$9:$AA$55,0)),0)<>1,$AL13=IFERROR(INDEX('Level Engine'!$AU$9:$AU$55,MATCH('King Node Model'!$AL$49,'Level Engine'!$AA$9:$AA$55,0)),""),IFERROR(INDEX('Level Engine'!$AU$9:$AU$55,MATCH('King Node Model'!$AL$49,'Level Engine'!$AA$9:$AA$55,0)),"")<>IFERROR(INDEX('Level Engine'!$AT$9:$AT$55,MATCH('King Node Model'!$AL$49,'Level Engine'!$AA$9:$AA$55,0)),"")),AND(IFERROR(INDEX('Level Engine'!$IB$9:$IB$55,MATCH('King Node Model'!$AL$50,'Level Engine'!$AA$9:$AA$55,0)),0)<>1,$AL13=IFERROR(INDEX('Level Engine'!$AU$9:$AU$55,MATCH('King Node Model'!$AL$50,'Level Engine'!$AA$9:$AA$55,0)),""),IFERROR(INDEX('Level Engine'!$AU$9:$AU$55,MATCH('King Node Model'!$AL$50,'Level Engine'!$AA$9:$AA$55,0)),"")<>IFERROR(INDEX('Level Engine'!$AT$9:$AT$55,MATCH('King Node Model'!$AL$50,'Level Engine'!$AA$9:$AA$55,0)),"")))),IF(OR('King Node Model'!$A$8="Neg",N('Level Engine'!$BG$72)=1),""," ⒷⒽ"),"")&IF(AND(NOT(OR(AND(ISNUMBER(SEARCH("chop edge",$E$45)),IFERROR(ABS($AL13-'King Node Model'!$AL$42)<=5,FALSE),NOT(ISNUMBER(SEARCH("UNSAFE",$L$45)))),AND(ISNUMBER(SEARCH("chop edge",$E$46)),IFERROR(ABS($AL13-'King Node Model'!$AL$43)<=5,FALSE),NOT(ISNUMBER(SEARCH("UNSAFE",$L$46)))),AND(ISNUMBER(SEARCH("chop edge",$E$52)),IFERROR(ABS($AL13-'King Node Model'!$AL$49)<=5,FALSE),NOT(ISNUMBER(SEARCH("UNSAFE",$L$52)))),AND(ISNUMBER(SEARCH("chop edge",$E$53)),IFERROR(ABS($AL13-'King Node Model'!$AL$50)<=5,FALSE),NOT(ISNUMBER(SEARCH("UNSAFE",$L$53)))))),OR(AND(IFERROR(INDEX('Level Engine'!$IB$9:$IB$55,MATCH('King Node Model'!$AL$42,'Level Engine'!$AA$9:$AA$55,0)),0)<>1,$AL13=IFERROR(INDEX('Level Engine'!$AT$9:$AT$55,MATCH('King Node Model'!$AL$42,'Level Engine'!$AA$9:$AA$55,0)),""),IFERROR(INDEX('Level Engine'!$AT$9:$AT$55,MATCH('King Node Model'!$AL$42,'Level Engine'!$AA$9:$AA$55,0)),"")<>IFERROR(INDEX('Level Engine'!$AU$9:$AU$55,MATCH('King Node Model'!$AL$42,'Level Engine'!$AA$9:$AA$55,0)),"")),AND(IFERROR(INDEX('Level Engine'!$IB$9:$IB$55,MATCH('King Node Model'!$AL$43,'Level Engine'!$AA$9:$AA$55,0)),0)<>1,$AL13=IFERROR(INDEX('Level Engine'!$AT$9:$AT$55,MATCH('King Node Model'!$AL$43,'Level Engine'!$AA$9:$AA$55,0)),""),IFERROR(INDEX('Level Engine'!$AT$9:$AT$55,MATCH('King Node Model'!$AL$43,'Level Engine'!$AA$9:$AA$55,0)),"")<>IFERROR(INDEX('Level Engine'!$AU$9:$AU$55,MATCH('King Node Model'!$AL$43,'Level Engine'!$AA$9:$AA$55,0)),"")))),IF(OR('King Node Model'!$A$8="Neg",N('Level Engine'!$BG$72)=1),""," ⒷⓁ"),"")&IF(OR(AND($AL13>='King Node Model'!$AM$17,$AL13<='King Node Model'!$AN$17,$AP$45="RASP"),AND($AL13>='King Node Model'!$AM$18,$AL13<='King Node Model'!$AN$18,$AP$46="RASP"),AND($AL13>='King Node Model'!$AM$19,$AL13<='King Node Model'!$AN$19,$AP$47="RASP"),AND($AL13>='King Node Model'!$AM$20,$AL13<='King Node Model'!$AN$20,$AP$52="RASP"),AND($AL13>='King Node Model'!$AM$21,$AL13<='King Node Model'!$AN$21,$AP$53="RASP"),AND($AL13>='King Node Model'!$AM$22,$AL13<='King Node Model'!$AN$22,$AP$54="RASP")),"","")&IF(IF('Level Engine'!$GJ$4=1,$AL13='Level Engine'!$GJ$3,AND($AL13-$AM$2>-2.5,$AL13-$AM$2<=2.5))," ◄","")&IF(IFERROR(INDEX('Level Engine'!$GV$9:$GV$55,MATCH($AL13,'Level Engine'!$AA$9:$AA$55,0)),0)=1," Ⓥ"&IF(IFERROR(INDEX('Level Engine'!$ET$9:$ET$55,MATCH($AL13,'Level Engine'!$AA$9:$AA$55,0)),0)=1,"+",""),"")&IF(OR(AND($AL13=$AN$38,IFERROR(INDEX('Level Engine'!$AN$9:$AN$55,MATCH($AL13,'Level Engine'!$AA$9:$AA$55,0)),0)<>1),$AL13=$AN$39)," ⊙","")&IF(AND(OR('King Node Model'!$A$8="Neg",N('Level Engine'!$BG$72)=1),ABS(MIN($AM$3:$AM$64))>MAX($AM$3:$AM$64),$AN$2<$AM$2,$AL13<$AM$2,ABS($AL13-$AN$2)<=5,IFERROR(VALUE(MID('King Node Model'!$K$26,FIND(":",'King Node Model'!$K$26)-2,2)),0)>=19,IFERROR(INDEX('Level Engine'!$EJ$9:$EJ$55,MATCH($AL13,'Level Engine'!$AA$9:$AA$55,0)),0)=0,$AN$3>$AM$2)," ⟲rev","")&IF($AL13='King Node Model'!$F$24," ⟂","")&$DJ13&IF(IFERROR(INDEX('Level Engine'!$EN$9:$EN$55,MATCH($AL13,'Level Engine'!$AA$9:$AA$55,0)),0)=1," Ⓟ"&IF(AND(OR('King Node Model'!$A$8="Neg",N('Level Engine'!$BG$72)=1),IFERROR(INDEX('Level Engine'!$AN$9:$AN$55,MATCH($AL13,'Level Engine'!$AA$9:$AA$55,0)),0)<>1)," NO-REV",""),"")&IF(AND(ISNUMBER($AL13),OR(AND(ISNUMBER(SEARCH("chop edge",$E$45)),$AL13='King Node Model'!$AL$42),AND(ISNUMBER(SEARCH("chop edge",$E$46)),$AL13='King Node Model'!$AL$43),AND(ISNUMBER(SEARCH("chop edge",$E$52)),$AL13='King Node Model'!$AL$49),AND(ISNUMBER(SEARCH("chop edge",$E$53)),$AL13='King Node Model'!$AL$50)))," ⒸⒺ","")&IF(AND('Level Engine'!$GJ$4=1,OR($AL13='Level Engine'!$GJ$1,$AL13='Level Engine'!$GJ$2)),"","")&IF(ABS(N(IFERROR(INDEX('Level Engine'!$AE$9:$AE$55,MATCH($AL13,'Level Engine'!$AA$9:$AA$55,0)),0)))>='Level Engine'!$BG$85,IF(N(IFERROR(INDEX('Level Engine'!$AE$9:$AE$55,MATCH($AL13,'Level Engine'!$AA$9:$AA$55,0)),0))>0," Δ+"," Δ−"),"")&IFERROR(IF(AND(ISNUMBER(MATCH($AL13,'Level Engine'!$AA$9:$AA$55,0)),ABS(N(IFERROR(INDEX('Level Engine'!$AE$9:$AE$55,MATCH($AL13,'Level Engine'!$AA$9:$AA$55,0)),0)))<'Level Engine'!$BG$85,ABS(N(IFERROR(INDEX('Level Engine'!$AE$9:$AE$55,MATCH($AL13,'Level Engine'!$AA$9:$AA$55,0)),0)))<=ABS(N(IFERROR(INDEX('Level Engine'!$AE$9:$AE$55,MATCH($AL13+5,'Level Engine'!$AA$9:$AA$55,0)),0))),ABS(N(IFERROR(INDEX('Level Engine'!$AE$9:$AE$55,MATCH($AL13,'Level Engine'!$AA$9:$AA$55,0)),0)))<=ABS(N(IFERROR(INDEX('Level Engine'!$AE$9:$AE$55,MATCH($AL13-5,'Level Engine'!$AA$9:$AA$55,0)),0))),OR(AND(ABS(N(IFERROR(INDEX('Level Engine'!$AE$9:$AE$55,MATCH($AL13+5,'Level Engine'!$AA$9:$AA$55,0)),0)))>='Level Engine'!$BG$85,ABS(N(IFERROR(INDEX('Level Engine'!$AE$9:$AE$55,MATCH($AL13,'Level Engine'!$AA$9:$AA$55,0)),0)))<='Level Engine'!$BG$88*ABS(N(IFERROR(INDEX('Level Engine'!$AE$9:$AE$55,MATCH($AL13+5,'Level Engine'!$AA$9:$AA$55,0)),0)))),AND(ABS(N(IFERROR(INDEX('Level Engine'!$AE$9:$AE$55,MATCH($AL13-5,'Level Engine'!$AA$9:$AA$55,0)),0)))>='Level Engine'!$BG$85,ABS(N(IFERROR(INDEX('Level Engine'!$AE$9:$AE$55,MATCH($AL13,'Level Engine'!$AA$9:$AA$55,0)),0)))<='Level Engine'!$BG$88*ABS(N(IFERROR(INDEX('Level Engine'!$AE$9:$AE$55,MATCH($AL13-5,'Level Engine'!$AA$9:$AA$55,0)),0)))))),IF(AND('King Node Model'!$A$8="Pos",N('Level Engine'!$BG$72)<>1),""," ∅"),""),"")&IF(IFERROR(INDEX('Level Engine'!$JD$9:$JD$55,MATCH($AL13,'Level Engine'!$AA$9:$AA$55,0)),"")="P"," P-OI",IF(IFERROR(INDEX('Level Engine'!$JD$9:$JD$55,MATCH($AL13,'Level Engine'!$AA$9:$AA$55,0)),"")="C"," C-OI","")) -> 7835 | C13: =IF(AND(ISNUMBER($AM13),$AM13>0,ISNUMBER($AO13),$AO$1>0),REPT("█",ROUND($AO13/$AO$1*26,0)),"") -> █ | D13: =IF(NOT(ISNUMBER($AL13)),"",IF(IFERROR(INDEX('Level Engine'!$FS$9:$FS$55,MATCH($AL13,'Level Engine'!$AA$9:$AA$55,0)),0)=1,"⊙","")) | E13: Dealer action | F13: ='King Node Model'!C13 -> BUY the dip dominant. Pro-cyclical hedging — buying into strength, chase accelerates on rallies. Ride the trend — on IV spike trend changes to dominant selling. | Q13: =IF(OR($Q$5="",$R$5=""),"",IF(AND($Q$5="High",$R$5="Rising"),"Genuine volatility expansion",IF(AND($Q$5="High",$R$5="Falling"),"Possible false alarm / shakeout",IF(AND($Q$5="Low",$R$5="Falling"),"Genuine compression",IF(AND($Q$5="Low",$R$5="Rising"),"Early warning of regime change","—"))))) -> — | R13: =$Q$5 -> Low | S13: =$R$5 -> Rising (fast: Rising) | AL13: ='King Node Model'!A39 -> 7835 | AM13: ='King Node Model'!C39 -> 176610 | AN13: =IFERROR(INDEX('King Node Model'!$A$29:$A$75,MATCH(LARGE('King Node Model'!$AU$29:$AU$75,1),'King Node Model'!$AU$29:$AU$75,0)),"-") -> 7850 | AO13: ='King Node Model'!B39 -> 229319 | AY13: =IF(AND($B$2="Hide unsafe",$BB13=1),0,IF(AND(OR(AND(AND(ISNUMBER($AL13),OR(AND($AL13>=$AQ$22,$AL13<=$AR$22,$AS$22=1),$AL13=$AQ$22,$AL13=$AR$22,$AL13=$AQ$23,$AL13=$AR$23,$AL13=$AQ$24,$AL13=$AR$24),NOT(OR($AL13=$AN$5,$AL13=$AN$6,$AL13=$AN$7,$AL13=$AN$8,$AL13=$AN$10,$AL13=$AN$11))),NOT(OR(AND('King Node Model'!$P$13="Up",OR($AL13=$AQ$22,$AL13=$AQ$23,$AL13=$AQ$24,$AL13='King Node Model'!$AM$20,$AL13='King Node Model'!$AM$21,$AL13='King Node Model'!$AM$22),OR(AND('King Node Model'!$B$23-$AL13>=0,'King Node Model'!$B$23-$AL13<=5),AND('King Node Model'!$C$23-$AL13>=0,'King Node Model'!$C$23-$AL13<=5))),AND('King Node Model'!$P$13="Down",OR($AL13=$AR$22,$AL13=$AR$23,$AL13=$AR$24,$AL13='King Node Model'!$AN$20,$AL13='King Node Model'!$AN$21,$AL13='King Node Model'!$AN$22),OR(AND($AL13-'King Node Model'!$B$23>=0,$AL13-'King Node Model'!$B$23<=5),AND($AL13-'King Node Model'!$C$24>=0,$AL13-'King Node Model'!$C$24<=5)))))),AND(AND(ISNUMBER($AL13),OR(AND($AL13>=$AQ$22,$AL13<=$AR$22,$AS$22=1),$AL13=$AQ$22,$AL13=$AR$22,$AL13=$AQ$23,$AL13=$AR$23,$AL13=$AQ$24,$AL13=$AR$24,$AL13='King Node Model'!$AL$42,$AL13='King Node Model'!$AL$43),OR($AL13=$AN$5,$AL13=$AN$6,$AL13=$AN$7,$AL13=$AN$8,$AL13=$AN$10,$AL13=$AN$11)),NOT(OR(AND('King Node Model'!$P$13="Up",OR($AL13=$AQ$22,$AL13=$AQ$23,$AL13=$AQ$24,$AL13='King Node Model'!$AM$20,$AL13='King Node Model'!$AM$21,$AL13='King Node Model'!$AM$22),OR(AND('King Node Model'!$B$23-$AL13>=0,'King Node Model'!$B$23-$AL13<=5),AND('King Node Model'!$C$23-$AL13>=0,'King Node Model'!$C$23-$AL13<=5))),AND('King Node Model'!$P$13="Down",OR($AL13=$AR$22,$AL13=$AR$23,$AL13=$AR$24,$AL13='King Node Model'!$AN$20,$AL13='King Node Model'!$AN$21,$AL13='King Node Model'!$AN$22),OR(AND($AL13-'King Node Model'!$B$23>=0,$AL13-'King Node Model'!$B$23<=5),AND($AL13-'King Node Model'!$C$24>=0,$AL13-'King Node Model'!$C$24<=5)))))),AND(AND(ISNUMBER($AL13),OR(AND($AL13>='King Node Model'!$AM$20,$AL13<='King Node Model'!$AN$20,$AS$23=1),$AL13='King Node Model'!$AM$20,$AL13='King Node Model'!$AN$20,$AL13='King Node Model'!$AM$21,$AL13='King Node Model'!$AN$21,$AL13='King Node Model'!$AM$22,$AL13='King Node Model'!$AN$22),NOT(OR($AL13=$AN$5,$AL13=$AN$6,$AL13=$AN$7,$AL13=$AN$8,$AL13=$AN$10,$AL13=$AN$11))),NOT(AND(ISNUMBER('King Node Model'!$F$24),$AL13='King Node Model'!$F$24,IFERROR(INDEX('Level Engine'!$JN$9:$JN$55,MATCH($AL13,'Level Engine'!$AA$9:$AA$55,0)),0)<>1))),AND(AND(ISNUMBER($AL13),OR(AND($AL13>='King Node Model'!$AM$20,$AL13<='King Node Model'!$AN$20,$AS$23=1),$AL13='King Node Model'!$AM$20,$AL13='King Node Model'!$AN$20,$AL13='King Node Model'!$AM$21,$AL13='King Node Model'!$AN$21,$AL13='King Node Model'!$AM$22,$AL13='King Node Model'!$AN$22,$AL13='King Node Model'!$AL$49,$AL13='King Node Model'!$AL$50),OR($AL13=$AN$5,$AL13=$AN$6,$AL13=$AN$7,$AL13=$AN$8,$AL13=$AN$10,$AL13=$AN$11)),NOT(OR(AND('King Node Model'!$P$13="Up",OR($AL13=$AQ$22,$AL13=$AQ$23,$AL13=$AQ$24,$AL13='King Node Model'!$AM$20,$AL13='King Node Model'!$AM$21,$AL13='King Node Model'!$AM$22),OR(AND('King Node Model'!$B$23-$AL13>=0,'King Node Model'!$B$23-$AL13<=5),AND('King Node Model'!$C$23-$AL13>=0,'King Node Model'!$C$23-$AL13<=5))),AND('King Node Model'!$P$13="Down",OR($AL13=$AR$22,$AL13=$AR$23,$AL13=$AR$24,$AL13='King Node Model'!$AN$20,$AL13='King Node Model'!$AN$21,$AL13='King Node Model'!$AN$22),OR(AND($AL13-'King Node Model'!$B$23>=0,$AL13-'King Node Model'!$B$23<=5),AND($AL13-'King Node Model'!$C$24>=0,$AL13-'King Node Model'!$C$24<=5))))))),OR(COUNTIF('Level Engine'!$W$9:$W$14,$AL13)>0,COUNTIF('Level Engine'!$W$18:$W$23,$AL13)>0)),1,0)) -> 0 | AZ13: =IF($B$2="Hide unsafe",0,$BB13) -> 0 | BB13: =IF(OR(AND($AL13='King Node Model'!$AL$42,$AP$45<>"RASP"),AND($AL13='King Node Model'!$AL$43,$AP$46<>"RASP"),AND($AL13='King Node Model'!$AL$49,$AP$52<>"RASP"),AND($AL13='King Node Model'!$AL$50,$AP$53<>"RASP"),AND($AL13='King Node Model'!$AL$44,$AP$47<>"RASP"),AND($AL13='King Node Model'!$AL$51,$AP$54<>"RASP")),0,IF(AND(AND(ISNUMBER($AL13),OR(AND($AL13>=$AQ$22,$AL13<=$AR$22,$AP$45="RASP"),AND($AL13>=$AQ$23,$AL13<=$AR$23,$AP$46="RASP"),AND($AL13>=$AQ$24,$AL13<=$AR$24,$AP$47="RASP"),AND($AL13>='King Node Model'!$AM$20,$AL13<='King Node Model'!$AN$20,$AP$52="RASP",NOT($L$52=$AW$52)),AND($AL13='King Node Model'!$B$23,$AP$52="RASP",$L$52=$AW$52),AND($AL13>='King Node Model'!$AM$21,$AL13<='King Node Model'!$AN$21,$AP$53="RASP",NOT($L$53=$AW$53)),AND($AL13='King Node Model'!$B$23,$AP$53="RASP",$L$53=$AW$53),AND($AL13>='King Node Model'!$AM$22,$AL13<='King Node Model'!$AN$22,$AP$54="RASP"),AND($AL13>=IFERROR(INDEX('Level Engine'!$AT$9:$AT$55,MATCH('King Node Model'!$AL$42,'Level Engine'!$AA$9:$AA$55,0)),""),$AL13<=IFERROR(INDEX('Level Engine'!$AU$9:$AU$55,MATCH('King Node Model'!$AL$42,'Level Engine'!$AA$9:$AA$55,0)),""),$AP$45="RASP"),AND($AL13>=IFERROR(INDEX('Level Engine'!$AT$9:$AT$55,MATCH('King Node Model'!$AL$43,'Level Engine'!$AA$9:$AA$55,0)),""),$AL13<=IFERROR(INDEX('Level Engine'!$AU$9:$AU$55,MATCH('King Node Model'!$AL$43,'Level Engine'!$AA$9:$AA$55,0)),""),$AP$46="RASP"),AND($AL13>=IFERROR(INDEX('Level Engine'!$AT$9:$AT$55,MATCH('King Node Model'!$AL$44,'Level Engine'!$AA$9:$AA$55,0)),""),$AL13<=IFERROR(INDEX('Level Engine'!$AU$9:$AU$55,MATCH('King Node Model'!$AL$44,'Level Engine'!$AA$9:$AA$55,0)),""),$AP$47="RASP"),AND($AL13>=IFERROR(INDEX('Level Engine'!$AT$9:$AT$55,MATCH('King Node Model'!$AL$49,'Level Engine'!$AA$9:$AA$55,0)),""),$AL13<=IFERROR(INDEX('Level Engine'!$AU$9:$AU$55,MATCH('King Node Model'!$AL$49,'Level Engine'!$AA$9:$AA$55,0)),""),$AP$52="RASP",NOT($L$52=$AW$52)),AND($AL13>=IFERROR(INDEX('Level Engine'!$AT$9:$AT$55,MATCH('King Node Model'!$AL$50,'Level Engine'!$AA$9:$AA$55,0)),""),$AL13<=IFERROR(INDEX('Level Engine'!$AU$9:$AU$55,MATCH('King Node Model'!$AL$50,'Level Engine'!$AA$9:$AA$55,0)),""),$AP$53="RASP",NOT($L$53=$AW$53)),AND($AL13>=IFERROR(INDEX('Level Engine'!$AT$9:$AT$55,MATCH('King Node Model'!$AL$51,'Level Engine'!$AA$9:$AA$55,0)),""),$AL13<=IFERROR(INDEX('Level Engine'!$AU$9:$AU$55,MATCH('King Node Model'!$AL$51,'Level Engine'!$AA$9:$AA$55,0)),""),$AP$54="RASP"))),NOT(AND(ISNUMBER('King Node Model'!$F$24),$AL13='King Node Model'!$F$24,IFERROR(INDEX('Level Engine'!$JN$9:$JN$55,MATCH($AL13,'Level Engine'!$AA$9:$AA$55,0)),0)<>1,$AL13<>'King Node Model'!$AL$42,$AL13<>'King Node Model'!$AL$43,$AL13<>'King Node Model'!$AL$44,$AL13<>'King Node Model'!$AL$49,$AL13<>'King Node Model'!$AL$50,$AL13<>'King Node Model'!$AL$51))),1,0)) -> 0 | CO13: =IF(NOT(ISNUMBER($AL13)),"",IF(NOT(ISNUMBER(IFERROR(INDEX('Level Engine'!$FT$9:$FT$55,MATCH($AL13,'Level Engine'!$AA$9:$AA$55,0)),""))),"",IF(IFERROR(INDEX('Level Engine'!$FT$9:$FT$55,MATCH($AL13,'Level Engine'!$AA$9:$AA$55,0)),"")<0,0,2)+IF(ABS(IFERROR(INDEX('Level Engine'!$FT$9:$FT$55,MATCH($AL13,'Level Engine'!$AA$9:$AA$55,0)),""))>='Level Engine'!$FT$2,2,1))) -> 4 | DJ13: =IF(ISNUMBER($AL13),IF($AL13='Level Engine'!$BG$122," ⫪","")&IF($AL13='Level Engine'!$BG$118," S↑"&IFERROR(INDEX('Level Engine'!$MV$9:$MV$55,MATCH($AL13,'Level Engine'!$AA$9:$AA$55,0)),""),"")&IF($AL13='Level Engine'!$BG$119," S↓"&IFERROR(INDEX('Level Engine'!$MV$9:$MV$55,MATCH($AL13,'Level Engine'!$AA$9:$AA$55,0)),""),"")&IF($AL13='Level Engine'!$BG$120," D↑","")&IF($AL13='Level Engine'!$BG$121," D↓","")&IFERROR(INDEX('Level Engine'!$LG$9:$LG$55,MATCH($AL13,'Level Engine'!$AA$9:$AA$55,0)),"")&IF(IFERROR(INDEX('Level Engine'!$MA$9:$MA$55,MATCH($AL13,'Level Engine'!$AA$9:$AA$55,0)),0)=1," SAND","")&IF(IFERROR(INDEX('Level Engine'!$LM$9:$LM$55,MATCH($AL13,'Level Engine'!$AA$9:$AA$55,0)),0)>0," TP","")&IFERROR(" r"&MATCH($AL13,'Level Engine'!$W$9:$W$14,0),IFERROR(" s"&MATCH($AL13,'Level Engine'!$W$18:$W$23,0),""))&IF($AL13='Level Engine'!$BG$165," ◇","")&IF(N($DZ13)=1,IF($AL13>'Level Engine'!$BG$165," ⚠ DOM↓"," ⚠ DOM↑")&'Level Engine'!$BG$165,""),"") | DK13: =IF(AND(ISNUMBER($AL13),OR($AL13='King Node Model'!$AL$42,$AL13='King Node Model'!$AL$43,$AL13='King Node Model'!$AL$44)),IFERROR(MATCH($AL13,'Level Engine'!$W$9:$W$14,0),""),"") | DL13: =IF(AND(ISNUMBER($AL13),OR($AL13='King Node Model'!$AL$49,$AL13='King Node Model'!$AL$50,$AL13='King Node Model'!$AL$51)),IFERROR(MATCH($AL13,'Level Engine'!$W$18:$W$23,0),""),"") | DM13: =IF(AND(ISNUMBER($AL13),IFERROR(INDEX('Level Engine'!$LC$9:$LC$55,MATCH($AL13,'Level Engine'!$AA$9:$AA$55,0)),0)=1,OR($AL13=$AN$3,IFERROR(INDEX('Level Engine'!$LB$9:$LB$55,MATCH($AL13,'Level Engine'!$AA$9:$AA$55,0)),0)=1)),1,0) -> 0 | DZ13: =IF(ISNUMBER($AL13),IF(IFERROR(INDEX('Level Engine'!$NJ$9:$NJ$55,MATCH($AL13,'Level Engine'!$AA$9:$AA$55,0)),0)=1,1,0),0)
